Workbook

Sheet Cover
B2: DULCINEA
B3: Portfolio Investment Model — Medellín & El Retiro, Colombia
B4: =TEXT(Input!$C$57,"0")&"-year buy · remodel · rent · sell fund · USD · TRM COP "&TEXT(Input!$C$5,"#,##0")&" per USD (reference) · Model start "&TEXT(Input!$C$7,"mmm yyyy") -> 4-year buy · remodel · rent · sell fund · USD · TRM COP 3,090 per USD (reference) · Model start Oct 2026
B5: Color Coding
B6: Hardcoded input — Input tab levers; Properties deal terms; ServCo cost & comp tabs; sensitivity steps on Portfolio Analysis & Portfolio Analysis. Nowhere else.
B7: Formula calculated on the same sheet — never overwrite
B8: Link pulling from another sheet in this workbook — trace to its source tab before changing anything
B9: Key result / subtotal row (light-blue fill); navy bands are section headers
B10: Guidance verdicts — automatic traffic lights vs researched benchmarks: green within range · yellow below · red above
B11: Zeros display as “–”; negatives in (parentheses); all amounts USD unless marked COP
B12: Workbook Guide
B14: Business Description | C14: What Dulcinea I is, how it makes money, the Equity Investor Kickers, structure and key risks — in plain language, no numbers
B15: Dashboard | C15: Start here for the numbers: Equity Investor results first, then the kickers, value creation, STR operations, taxes and the charts
B16: The Buy Box | C16: The criteria a property must meet to enter the fund, the live check of the five properties, and the sourcing funnel
B17: Input | C17: Every assumption in one place — FX, exit and rental drivers, costs, Colombian taxes, per-property inputs, capital terms — plus the model checks
B18: Income Statement | C18: Contribution-margin statement by property: revenue, variable costs, contribution margin, fixed costs, taxes and net income
B19: Balance Sheet / Statement of Cash Flows | C19: Integrated statements with balance and cash tie-out checks every year
B20: Investor Return | C20: Equity Investor capital calls, distributions and carry, with MOIC, IRR (on dated monthly cash flows) and payback
B21: Properties / Property Detail | C21: Deal-by-deal underwriting and per-property annual income and expenses
B22: Portfolio Analysis / Sources & Uses | C22: Exit and hold-period sensitivities, deal-level returns, cap-rate analysis and capital deployment
B23: ServCo Financials | C23: ServCo's fees to the fund, benchmarked, with time-based executive allocation
B24: Medellín Market Data | C24: Official DANE price series and the USD/COP reference, cross-checked against the model's appreciation assumption
B25: Lola & Ber / Glossary | C25: The hospitality brand associated with Dulcinea, and definitions of every term (including Colombian taxes, in Spanish with legal references)
B26: Working tabs (_ prefix) | C26: _Month Engine (monthly cash-flow engine) · _Seasonality (STR pricing and seasonality) · _IRR Engine (dated flows behind every IRR) · _Forced Assumptions · _ICP Archive · _Handoff
B27: Confidential
B29: Prepared for internal use and qualified investors. Contains proprietary assumptions and negotiated pricing. Do not distribute without authorization.

Sheet Dashboard
B1: Dulcinea — Dashboard | G1: =Input!$C$146 -> ALL CHECKS PASS
B2: =TEXT(Input!$C$57,"0")&"-year program (through final exit) · USD · TRM COP "&TEXT(Input!$C$5,"#,##0")&" per USD · Model start "&TEXT(Input!$C$7,"mmm yyyy") -> 4-year program (through final exit) · USD · TRM COP 3,090 per USD · Model start Oct 2026
B4: 1. Equity Investor Results
B5: Equity Investor IRR (net of fees, tax & carry) | C5: ='Investor Return'!$C$22 -> 0.15722408 | E5: Equity Investor MOIC (after carry) | G5: ='Investor Return'!$C$21 -> 1.43553
B6: Net profit to Equity Investors after carry (USD) | C6: ='Investor Return'!$C$20 -> 2926674.4 | E6: Total distributions to Equity Investors (USD) | G6: ='Investor Return'!$C$19 -> 9646474.6
B7: Capital drawn (USD) | C7: ='Investor Return'!$C$16 -> 6719800.2 | E7: Payback (model year) | G7: ='Investor Return'!$C$23 -> 4
B8: Authorized capital raise (USD) | C8: =Input!$C$37 -> 7000000 | E8: Fund life (years, through final sale) | G8: =Input!$C$57 -> 4
B9: 2. Equity Investor Kickers
B10: Kicker 1 — Lola & Ber Hospitality Brand Company equity interest | C10: =Input!$C$50 -> 0.03 | E10: Lola & Ber equity interest at current commitments | G10: =Input!$C$51 -> 0.009
B11: Kicker 2 — Dulcinea II pro-rata right of first refusal | C11: Pro rata | E11: Basis of pro-rata allocation | G11: Dulcinea I commitment
B12: Kicker 3 — Managing Partner structure of future funds | C12: Priority | E12: Applies to | G12: Future funds incl. Dulcinea chapters
B13: 3. Portfolio Value Creation
B14: All-in investment — active properties (USD) | C14: =SUMPRODUCT(Properties!$D$6:$D$15,Properties!$P$6:$P$15) -> 6571966 | E14: Portfolio IRR (deal-level, after gains tax) | G14: ='_IRR Engine'!$Q$17 -> 0.2081031
B15: Projected gross exit value (USD) | C15: =SUMPRODUCT(Properties!$D$6:$D$15,Properties!$W$6:$W$15) -> 11376911 | E15: Exit value ÷ all-in cost | G15: =IFERROR(C15/C14,0) -> 1.7311275
B16: Gross gain on property sales (USD) | C16: =SUMPRODUCT(Properties!$D$6:$D$15,Properties!$AC$6:$AC$15) -> 4372622.4 | E16: Average hold per property (years) | G16: =SUMPRODUCT(Properties!$D$6:$D$15,Properties!$V$6:$V$15)/SUM(Properties!$D$6:$D$15) -> 2.5
B17: Carry to Managing Partner (KIT Capital) (USD) | C17: =-'Investor Return'!$C$18 -> 731668.59 | E17: Active properties · backup properties | G17: =TEXT(SUM(Properties!$D$6:$D$15),"0")&" · "&TEXT(COUNTIF(Properties!$C$6:$C$19,"*Backup*"),"0") -> 5 · 4
B18: 4. STR Operations
B19: Stabilized STR revenue — active portfolio (USD/yr) | C19: =SUMPRODUCT(Properties!$D$6:$D$15,Properties!$Y$6:$Y$15) -> 307290.91 | E19: STR daily rates (USD/night) | G19: =TEXT(_xlfn.MINIFS(Input!$J$80:$J$89,Properties!$D$6:$D$15,1),"$#,##0")&"–"&TEXT(_xlfn.MAXIFS(Input!$J$80:$J$89,Properties!$D$6:$D$15,1),"$#,##0") -> $250–$340
B20: STR revenue over fund life (USD) | C20: =SUM('Income Statement'!$C$7:$L$7) -> 643426.99 | E20: Average booked occupancy | G20: =1-Input!$C$10 -> 0.6
B21: Rental contribution margin over fund life (USD) | C21: =SUM('Income Statement'!$C$112:$L$112) -> 506698.75 | E21: Rental CM % of STR revenue | G21: =IFERROR(C21/C20,0) -> 0.7875
B22: Fixed costs over fund life (USD) | C22: =SUM('Income Statement'!$C$145:$L$145) -> 652369.41 | E22: Minimum stay · price cap per 28 nights | G22: =TEXT(Input!$C$171,"0")&" nights · "&TEXT(Input!$C$170,"$#,##0") -> 28 nights · $9,500
B23: 5. Taxes & Macro
B24: Impuesto de Ganancia Ocasional — total (USD) | C24: =SUM('Income Statement'!$C$152:$L$152) -> 568608.75 | E24: Gains-tax rate (fixed, all sales) | G24: =Input!$C$26 -> 0.15
B25: Tax-basis indexation at US CPI (USD) | C25: =SUMPRODUCT(Properties!$D$6:$D$15,Properties!$AN$6:$AN$15)-SUMPRODUCT(Properties!$D$6:$D$15,Properties!$P$6:$P$15) -> 581897.37 | E25: US inflation — FRED CPI-U (YoY) | G25: =Input!$C$28 -> 0.0335
B26: STR revenue taxes over fund life (USD) | C26: =SUM('Income Statement'!$C$106:$L$106) -> 8042.8373 | E26: TRM (COP per USD, reference only) | G26: =Input!$C$5 -> 3090
B28: 6. Sensitivities, Portfolio & Cash-Flow Charts
B37: ="The "&TEXT(SUM(Properties!$D$6:$D$15),"0")&" active properties carry "&TEXT(SUMPRODUCT(Properties!$D$6:$D$15,Properties!$P$6:$P$15),"$#,##0")&" of all-in cost against "&TEXT(SUMPRODUCT(Properties!$D$6:$D$15,Properties!$W$6:$W$15),"$#,##0")&" of projected exit value — every one exits above cost, at a "&TEXT(SUMPRODUCT(Properties!$D$6:$D$15,Properties!$W$6:$W$15)/SUMPRODUCT(Properties!$D$6:$D$15,Properties!$P$6:$P$15)-1,"0%")&" uplift. "&TEXT(COUNTIF(Properties!$C$6:$C$19,"*Backup*"),"0")&" backup properties stay available as substitutes if a deal does not close." -> The 5 active properties carry $6,571,966 of all-in cost against $11,376,911 of projected exit value — every one exits above cost, at a 73% uplift. 4 backup properties stay available as substitutes if a deal does not close.
B46: {="Capital of "&TEXT(Input!$C$37,"$#,##0")&" is called only as acquisitions close, never up front. The first distribution lands in Year "&TEXT(MATCH(TRUE,INDEX('Investor Return'!$C$8:$L$8,0)>0,0),"0")&" as the first properties exit, cumulative investor cash turns positive in Year "&TEXT('Investor Return'!$C$23,"0")&", and the program returns "&TEXT('Investor Return'!$C$19,"$#,##0")&" on "&TEXT(Input!$C$37,"$#,##0")&" invested."} -> Capital of $7,000,000 is called only as acquisitions close, never up front. The first distribution lands in Year 3 as the first properties exit, cumulative investor cash turns positive in Year 4, and the program returns $9,646,475 on $7,000,000 invested.
B48: How Returns Are Generated
B49: ="Property sales of "&TEXT(SUM('Income Statement'!$C$18:$L$18),"$#,##0")&" and rental revenue of "&TEXT(SUM('Income Statement'!$C$7:$L$7),"$#,##0")&" over the life of the fund produce cumulative net income of "&TEXT(SUM('Income Statement'!$C$155:$L$155),"$#,##0;($#,##0)")&" after all Colombian taxes and operating costs." -> Property sales of $11,376,911 and rental revenue of $643,427 over the life of the fund produce cumulative net income of $3,658,343 after all Colombian taxes and operating costs.
B50: ="Equity Investors commit "&TEXT(Input!$C$37,"$#,##0")&", drawn only as acquisitions close, and receive distributions as each property exits — "&TEXT('Investor Return'!$C$19,"$#,##0")&" returned in total after the "&TEXT(Input!$C$46,"0%")&" Carry to the Managing Partner ("&TEXT(-'Investor Return'!$C$18,"$#,##0")&"), a "&TEXT('Investor Return'!$C$21,"0.00")&"x multiple and a "&TEXT('Investor Return'!$C$22,"0.0%")&" IRR, with capital fully recovered by Year "&TEXT('Investor Return'!$C$23,"0")&"." -> Equity Investors commit $7,000,000, drawn only as acquisitions close, and receive distributions as each property exits — $9,646,475 returned in total after the 20% Carry to the Managing Partner ($731,669), a 1.44x multiple and a 15.7% IRR, with capital fully recovered by Year 4.
B60: =_xlfn.LET(_xlpm.r,INDEX('Income Statement'!$C$155:$L$155,1,1):INDEX('Income Statement'!$C$155:$L$155,1,Input!$C$57),"Earnings arrive in the exit years, not evenly: Year "&TEXT(MATCH(MAX(_xlpm.r),_xlpm.r,0),"0")&" delivers "&TEXT(MAX(_xlpm.r),"$#,##0")&" and the fund totals "&TEXT(SUM(_xlpm.r),"$#,##0")&" of net income. Holding years carry STR rental contribution against fixed costs while capital is working in renovation and marketing rather than in rent.") -> Earnings arrive in the exit years, not evenly: Year 4 delivers $1,945,121 and the fund totals $3,658,343 of net income. Holding years carry STR rental contribution against fixed costs while capital is working in renovation and marketing rather than in rent.
B62: Discipline & Integrity
B63: ="Dulcinea carries no debt; properties are held at cost until sold. All operating services are provided by ServCo (an Ashoka unit) at benchmarked arm's-length fees, with executive costs allocated by time served. Every input lives on the Input tab; "&TEXT(COUNTA(Input!$C$99:$C$145),"0")&" automated integrity checks — foot and cross-foot on all three statements, engine reconciliations and reasonableness controls — currently read: "&Input!$C$146&"." -> Dulcinea carries no debt; properties are held at cost until sold. All operating services are provided by ServCo (an Ashoka unit) at benchmarked arm's-length fees, with executive costs allocated by time served. Every input lives on the Input tab; 43 automated integrity checks — foot and cross-foot on all three statements, engine reconciliations and reasonableness controls — currently read: ALL CHECKS PASS.
B73: {="No debt is drawn at any point and cash never goes negative in any year. The working capital reserve peaks at "&TEXT(MAX('Statement of Cash Flows'!$C$54:$L$54),"$#,##0")&" in Year "&TEXT(MATCH(MAX('Statement of Cash Flows'!$C$54:$L$54),'Statement of Cash Flows'!$C$54:$L$54,0),"0")&", runs down as the acquisition program completes, and the program closes at "&TEXT(INDEX('Statement of Cash Flows'!$C$54:$L$54,Input!$C$57),"$#,##0")&" at the final sale in Year "&TEXT(Input!$C$57,"0")&" — every purchase and works package funded from called capital rather than a facility."} -> No debt is drawn at any point and cash never goes negative in any year. The working capital reserve peaks at $24,326 in Year 1, runs down as the acquisition program completes, and the program closes at $0 at the final sale in Year 4 — every purchase and works package funded from called capital rather than a facility.
B74: Portfolio IRR (after gains tax) and Equity Investor IRR by entry discount — both anchored to the model at the base-case discount; other columns scale with the deal-level sensitivity on Portfolio Analysis
B75: Chart data (grouped — expand to view)
B76: Scenario | C76: ="Entry "&TEXT('Portfolio Analysis'!$C$178,"0%") -> Entry 20% | D76: ="Entry "&TEXT('Portfolio Analysis'!$C$179,"0%") -> Entry 25% | E76: ="Entry "&TEXT('Portfolio Analysis'!$C$180,"0%") -> Entry 30% | F76: ="Entry "&TEXT('Portfolio Analysis'!$C$181,"0%") -> Entry 35% | G76: ="Entry "&TEXT('Portfolio Analysis'!$C$182,"0%") -> Entry 40%
B77: Portfolio IRR | C77: ='Portfolio Analysis'!$E$178*'_IRR Engine'!$Q$17/'Portfolio Analysis'!$E$180 -> 0.15170478 | D77: ='Portfolio Analysis'!$E$179*'_IRR Engine'!$Q$17/'Portfolio Analysis'!$E$180 -> 0.17856188 | E77: ='Portfolio Analysis'!$E$180*'_IRR Engine'!$Q$17/'Portfolio Analysis'!$E$180 -> 0.2081031 | F77: ='Portfolio Analysis'!$E$181*'_IRR Engine'!$Q$17/'Portfolio Analysis'!$E$180 -> 0.2408201 | G77: ='Portfolio Analysis'!$E$182*'_IRR Engine'!$Q$17/'Portfolio Analysis'!$E$180 -> 0.27734213
B78: Equity Investor IRR | C78: ='Portfolio Analysis'!$E$178*'Investor Return'!$C$22/'Portfolio Analysis'!$E$180 -> 0.11461455 | D78: ='Portfolio Analysis'!$E$179*'Investor Return'!$C$22/'Portfolio Analysis'!$E$180 -> 0.13490537 | E78: ='Portfolio Analysis'!$E$180*'Investor Return'!$C$22/'Portfolio Analysis'!$E$180 -> 0.15722408 | F78: ='Portfolio Analysis'!$E$181*'Investor Return'!$C$22/'Portfolio Analysis'!$E$180 -> 0.18194211 | G78: ='Portfolio Analysis'!$E$182*'Investor Return'!$C$22/'Portfolio Analysis'!$E$180 -> 0.20953489
B79: Period | C79: ="Year "&TEXT('Income Statement'!C$4,"0") -> Year 1 | D79: ="Year "&TEXT('Income Statement'!D$4,"0") -> Year 2 | E79: ="Year "&TEXT('Income Statement'!E$4,"0") -> Year 3 | F79: ="Year "&TEXT('Income Statement'!F$4,"0") -> Year 4 | G79: ="Year "&TEXT('Income Statement'!G$4,"0") -> Year 5 | H79: ="Year "&TEXT('Income Statement'!H$4,"0") -> Year 6 | I79: ="Year "&TEXT('Income Statement'!I$4,"0") -> Year 7
B80: Ending cash (USD) | C80: ='Statement of Cash Flows'!C54 -> 24326.267 | D80: ='Statement of Cash Flows'!D54 -> 19430.894 | E80: ='Statement of Cash Flows'!E54 -> 6569.2389 | F80: ='Statement of Cash Flows'!F54 -> -4.2200554e-10 | G80: ='Statement of Cash Flows'!G54 -> -4.2200554e-10 | H80: ='Statement of Cash Flows'!H54 -> -4.2200554e-10 | I80: ='Statement of Cash Flows'!I54 -> -4.2200554e-10
B82: Period | C82: ="Year "&TEXT('Income Statement'!C$4,"0") -> Year 1 | D82: ="Year "&TEXT('Income Statement'!D$4,"0") -> Year 2 | E82: ="Year "&TEXT('Income Statement'!E$4,"0") -> Year 3 | F82: ="Year "&TEXT('Income Statement'!F$4,"0") -> Year 4 | G82: ="Year "&TEXT('Income Statement'!G$4,"0") -> Year 5 | H82: ="Year "&TEXT('Income Statement'!H$4,"0") -> Year 6 | I82: ="Year "&TEXT('Income Statement'!I$4,"0") -> Year 7
B83: Equity Investor cash flow (USD) | C83: ='Investor Return'!C12 -> -6630682.3 | D83: ='Investor Return'!D12 -> -84829.977 | E83: ='Investor Return'!E12 -> 5057197.2 | F83: ='Investor Return'!F12 -> 4584989.4 | G83: ='Investor Return'!G12 -> 0 | H83: ='Investor Return'!H12 -> 0 | I83: ='Investor Return'!I12 -> 0
B84: Cumulative (USD) | C84: ='Investor Return'!C13 -> -6630682.3 | D84: ='Investor Return'!D13 -> -6715512.2 | E84: ='Investor Return'!E13 -> -1658315.1 | F84: ='Investor Return'!F13 -> 2926674.4 | G84: ='Investor Return'!G13 -> 2926674.4 | H84: ='Investor Return'!H13 -> 2926674.4 | I84: ='Investor Return'!I13 -> 2926674.4
B86: Property | C86: All-in cost | D86: Exit value
A87: {=_xlfn._xlws.FILTER(Properties!$A$6:$A$15,Properties!$D$6:$D$15=1)} -> 1 | B87: {=IF($A87="","",INDEX(Properties!$E$6:$E$15,$A87))} -> Aires de Campestre Apto 801 (Penthouse) | C87: {=IF($A87="","",INDEX(Properties!$P$6:$P$15,$A87))} -> 1168770.2 | D87: {=IF($A87="","",INDEX(Properties!$W$6:$W$15,$A87))} -> 2019763.4
A88: 2 | B88: {=IF($A88="","",INDEX(Properties!$E$6:$E$15,$A88))} -> Fontanar Apto 201 (Penthouse) | C88: {=IF($A88="","",INDEX(Properties!$P$6:$P$15,$A88))} -> 1290857.6 | D88: {=IF($A88="","",INDEX(Properties!$W$6:$W$15,$A88))} -> 2261281.6
A89: 3 | B89: {=IF($A89="","",INDEX(Properties!$E$6:$E$15,$A89))} -> San Lucas Apto 101 | C89: {=IF($A89="","",INDEX(Properties!$P$6:$P$15,$A89))} -> 747370.55 | D89: {=IF($A89="","",INDEX(Properties!$W$6:$W$15,$A89))} -> 1265464.3
A90: 4 | B90: {=IF($A90="","",INDEX(Properties!$E$6:$E$15,$A90))} -> Casa Montana Lote 2 (Samuel Gaviria House) | C90: {=IF($A90="","",INDEX(Properties!$P$6:$P$15,$A90))} -> 1714482.2 | D90: {=IF($A90="","",INDEX(Properties!$W$6:$W$15,$A90))} -> 2995795.2
A91: 5 | B91: {=IF($A91="","",INDEX(Properties!$E$6:$E$15,$A91))} -> Casa Monte Sereno | C91: {=IF($A91="","",INDEX(Properties!$P$6:$P$15,$A91))} -> 1650485.4 | D91: {=IF($A91="","",INDEX(Properties!$W$6:$W$15,$A91))} -> 2834606.6
B92: {=IF($A92="","",INDEX(Properties!$E$6:$E$15,$A92))} | C92: {=IF($A92="","",INDEX(Properties!$P$6:$P$15,$A92))} | D92: {=IF($A92="","",INDEX(Properties!$W$6:$W$15,$A92))}
B93: {=IF($A93="","",INDEX(Properties!$E$6:$E$15,$A93))} | C93: {=IF($A93="","",INDEX(Properties!$P$6:$P$15,$A93))} | D93: {=IF($A93="","",INDEX(Properties!$W$6:$W$15,$A93))}
B94: {=IF($A94="","",INDEX(Properties!$E$6:$E$15,$A94))} | C94: {=IF($A94="","",INDEX(Properties!$P$6:$P$15,$A94))} | D94: {=IF($A94="","",INDEX(Properties!$W$6:$W$15,$A94))}
B95: {=IF($A95="","",INDEX(Properties!$E$6:$E$15,$A95))} | C95: {=IF($A95="","",INDEX(Properties!$P$6:$P$15,$A95))} | D95: {=IF($A95="","",INDEX(Properties!$W$6:$W$15,$A95))}
B96: {=IF($A96="","",INDEX(Properties!$E$6:$E$15,$A96))} | C96: {=IF($A96="","",INDEX(Properties!$P$6:$P$15,$A96))} | D96: {=IF($A96="","",INDEX(Properties!$W$6:$W$15,$A96))}

Sheet Input
B1: Dulcinea Portfolio Investment Model — Input
B2: Global model variables live on this tab. Per-deal inputs — selection flag, size, purchase & renovation prices, timing months — are the indigo cells on the Properties tab and feed the Portfolio Analysis analysis. Edit indigo-font cells only; formulas and linked values update automatically. USD presentation; COP inputs converted at the TRM below.
B4: General & FX | D4: Source / basis
B5: USD/COP exchange rate (TRM) | C5: 3090 | D5: Applied TRM per Dulcinea portfolio overview, 8/26/26
B6: COP depreciation vs USD (%/yr, projected) | C6: 0 | D6: Set to 0.0% on the post-election view — the peso strengthened from TRM ~3,757 to ~3,130 during 2026. Entry basis converts at the fixed TRM in C5. Raise this input to stress a weaker peso. Reference 11.
B7: Model start (Month 1 begins) | C7: 46296 | D7: First title transfers scheduled Sep 2026; model months run from Oct 2026
B8: Real rent growth (%/yr) — above inflation, excludes market appreciation | C8: 0.02
B9: Revenue & Exit
B10: Vacancy — active portfolio average, m²-weighted (derived from the per-property inputs) | C10: =SUMPRODUCT(Properties!$D$6:$D$15,Properties!$I$6:$I$15,$H$80:$H$89)/SUMPRODUCT(Properties!$D$6:$D$15,Properties!$I$6:$I$15) -> 0.4 | D10: ="Derived: m²-weighted average of the per-property vacancy inputs across the active portfolio, currently "&TEXT($C$10,"0%")&". Vacancy is set by unit size: the two mid-size El Poblado apartments are held at "&TEXT($H$81,"0%")&", inside the prime professionally-managed band of "&TEXT($C$168,"0%")&"–"&TEXT($D$168,"0%")&", while the "&TEXT(Properties!$I$6,"0")&" m² penthouse is held at "&TEXT($H$80,"0%")&" because the largest units are the slowest to let. The two El Retiro estates stay at "&TEXT($H$83,"0%")&" as no published series covers them. Market-wide Medellín runs "&TEXT($C$167,"0%")&"–"&TEXT($D$167,"0%")&" vacancy. References 14–16." -> Derived: m²-weighted average of the per-property vacancy inputs across the active portfolio, currently 40%. Vacancy is set by unit size: the two mid-size El Poblado apartments are held at 40%, inside the prime professionally-managed band of 35%–50%, while the 489 m² penthouse is held at 40% because the largest units are the slowest to let. The two El Retiro estates stay at 40% as no published series covers them. Market-wide Medellín runs 43%–57% vacancy. References 14–16.
B11: Rental ramp-up (months to stabilize) | C11: 1 | D11: Linear ramp after renovation completes
B12: Value uplift on all-in basis at exit (active portfolio) | C12: =SUMPRODUCT(Properties!$W$6:$W$15,Properties!$D$6:$D$15)/SUMPRODUCT(Properties!$P$6:$P$15,Properties!$D$6:$D$15)-1 -> 0.73112748
B13: Acquisition & Selling Costs
B14: Buyer closing costs — registration tax, registry rights & notary fees (Impuesto de Registro, Derechos de Registro y Derechos Notariales) (% of purchase price) | C14: 0.025 | D14: Notary share, registration tax and registry rights; market range 1.5%–3.5% of deed value
B15: Selling costs (% of sale price) | C15: 0.038 | D15: Broker commission (3%–5% market) plus seller notary share; 1% retención is a credit against capital gains tax, not an added cost
B17: Holding Costs — Global Rates
B18: Insurance — all-risk (%/yr of all-in basis) | C18: 0.0015 | D18: All-risk homeowner policies in Colombia typically run 0.1%–0.2% of value per year. Charged from rental start only — during the 6-month works the contractor carries construction all-risk cover.
B19: Maintenance reserve (%/yr of all-in basis) | C19: 0.005 | D19: Preventive upkeep on renovated luxury product
B20: Housekeeping & turnover (% of gross rent) — eliminated, now inside Property Management & Housekeeping (C31) | C20: 0 | D20: Set to zero 25 Sep 2026: cleaning and guest turnover are now covered by the combined 20% Property Management & Housekeeping fee.
B21: STR revenue taxes — Industry & Commerce Tax + Signage Tax + Tourism Promotion Levy (ICA + Avisos y Tableros + Contribución Parafiscal FONTUR) (revenue-weighted, derived) | C21: =IFERROR(SUMPRODUCT(Properties!$D$6:$D$15,Properties!$Y$6:$Y$15,Input!$U$80:$U$89)/SUMPRODUCT(Properties!$D$6:$D$15,Properties!$Y$6:$Y$15),0) -> 0.0125 | D21: Derived from the per-property tax columns O–U of the property table (per municipality). Used only for portfolio-level summaries; each property's P&L uses its own rate.
B22: Financial transactions tax (Gravamen a los Movimientos Financieros — GMF 4×1000, Art. 871 ET) (% of cash disbursements) | C22: 0.004 | D22: Financial transactions tax on bank debits
B24: Taxes
B25: Income tax on rental operation — capped at 15% per counsel (statutory Impuesto sobre la Renta, Art. 240 ET, is 35%) | C25: 0.15 | D25: Per counsel (25 Sep 2026): the fund's structure means it will never pay the 35% general rate; maximum effective tax rate on any income is 15%. Statutory reference: tarifa general 35% (Ley 2277 de 2022).
B26: Occasional gains tax on property sales — FIXED for all holds (Impuesto de Ganancia Ocasional, Arts. 300 y 313 ET) | C26: 0.15 | D26: Model convention: 15% applies to every sale regardless of hold length. Per counsel (25 Sep 2026) the fund's maximum tax rate on any income is 15%, so no sale or rental profit is taxed at the 35% statutory rate. See Glossary — Gains Tax Fixed at 15% (Model Exception).
B27: Value-added tax on lodging (IVA — servicio de hospedaje / vivienda turística, Art. 468 ET) — pass-through, not in P&L | C27: 0.19 | D27: STR rates are modeled NET of IVA (charged on top to the guest). Stays by non-resident foreign guests are exempt (Art. 481 lit. d ET; DUR 1625/2016 art. 1.3.1.11.1) if the unit is inscribed in the Registro Nacional de Turismo (RNT) and the passport/entry stamp is kept on file. Reference only — no formula uses this cell.
B28: US inflation rate for tax-cost adjustment (reajuste fiscal, Art. 70 ET — applied in USD) (%/yr) | C28: 0.0335 | D28: US CPI-U year over year to Aug 2026 from FRED series CPIAUCSL (334.131 vs 323.291 = +3.35%). Because all fund transactions are in USD, the all-in basis is indexed by US inflation (not the COP reajuste fiscal factor) for each year of hold, reducing the taxable gain. Blue input — update when FRED publishes new data.
B29: ServCo — Fees Charged to Dulcinea
B30: Asset management fee (% of basis owned, annual) | C30: 0.01
B31: Property management & housekeeping (% of gross rental revenue) | C31: 0.2 | D31: Single ServCo fee for running the rentals, including cleaning and guest turnover; replaces 15% management + 8% housekeeping.
B32: Service fee per owned property (USD / month) — consolidated into property management | C32: 0 | D32: Set to zero: concierge, housekeeping coordination and guest services are already covered by the single Property Management & Housekeeping fee (C31, 20% of gross rent), so a flat per-door charge would double-count the same service. A flat amount would also charge the $14/m² estates the same as the $28/m² penthouses. Reference 13 supports no flat per-door fee. Raise this input to reinstate one.
B34: Dulcinea Overhead
B35: Dulcinea legal, accounting & admin (USD / year) | C35: 30000
B36: Capital
B37: Total capital raise (USD) | C37: 7000000 | D37: Sized for acquisitions + works + closing + reserve; ServCo is compensated via fees within Dulcinea opex, not funded by the raise
B38: Total capital deployed (called capital plus shortfall absorbed, derived) | C38: ='Sources & Uses'!$C$8 -> 6806601.6 | D38: ="First "&TEXT($C$37/1000000,"$0.0")&"M of the raise is allocated to Dulcinea for property acquisition and improvements" -> First $7.0M of the raise is allocated to Dulcinea for property acquisition and improvements
B39: Working capital reserve (months of forward fund overheads held in cash) | C39: 3
B40: Unit price (USD per Unit, per Operating Agreement) | C40: 10000 | D40: Membership Units of Dulcinea Investments, LLC are issued at US$10,000 each
B41: Units issued to date | C41: 210 | D41: 210 Units issued under the Operating Agreement (3 Mar 2026) and First Amendment (2 Jul 2026)
B42: Capital committed to date (USD, derived) | C42: =C40*C41 -> 2100000 | D42: Capital already subscribed by existing Equity Investors — deployed to the two signed acquisitions (Aires de Campestre, Fontanar)
B43: Authorized capital ceiling (USD, Second Amendment) | C43: =C37 -> 7000000 | D43: Authorized capital raised from US$5.0M to US$7.0M — Second Amendment to the Operating Agreement (pending signature, Sep 2026)
B44: Supermajority Approval threshold (% of Equity Investors, excluding the Managing Partner) | C44: 0.8 | D44: Raised from 75% to 80% by the First Amendment; required for new acquisitions, dispositions, debt and capital increases
B45: Remaining raise to reach the authorized ceiling (USD, derived) | C45: =C43-C42 -> 4900000 | D45: Balance of the raise still to be subscribed by new Equity Investors
B46: Carry to Managing Partner (% of net profits, per Operating Agreement §4.3) | C46: 0.2 | D46: After Equity Investors recover their Capital Contributions, 20% of every distribution (rental income and sale proceeds) goes to the Managing Partner (KIT Capital) as Carry; Equity Investors receive the remaining 80%
B47: First model year with distributions (none paid before this year) | C47: 2 | D47: Per the 23 Sep 2026 corporate update call: no distributions to Equity Investors in Year 1. Surplus cash in earlier years is held in the fund and rolls forward to the first distribution year.
B48: Lola & Ber Hospitality Brand Company — maximum equity interest for Dulcinea I investors (at full subscription) | C48: 0.03 | D48: Equity investors in Dulcinea I are eligible for up to 3% of the Lola & Ber Hospitality Brand business, which launches at the same time as the fund. The full 3% applies at full subscription of the authorized raise.
B49: Modeled subscription of the authorized raise (%) | C49: 1 | D49: Model assumes the full authorized raise is subscribed. Change to test partial subscription.
B50: Lola & Ber equity interest earned by Dulcinea I investors (derived) | C50: =C48*MIN(1,C49) -> 0.03 | D50: Derived: maximum interest × modeled subscription (pro rata).
B51: Lola & Ber equity interest at current commitments (reference, derived) | C51: =C48*MIN(1,C42/C43) -> 0.009 | D51: Derived: maximum interest × capital committed to date ÷ authorized ceiling. Rises to the full 3% as the raise completes.
B52: Carrying value of Lola & Ber equity interest (USD) | C52: 0 | D52: Recorded on the Balance Sheet as an intangible asset valued at zero at present (early-stage brand business, no reliable valuation yet). Blue input — update if a valuation is established.
B53: Derived Values
B54: Market appreciation in COP (%/yr) — basis-weighted average of the per-property inputs (derived) | C54: =SUMPRODUCT(Properties!$D$6:$D$15,Properties!$P$6:$P$15,$F$80:$F$89)/SUMPRODUCT(Properties!$D$6:$D$15,Properties!$P$6:$P$15) -> 0.078087751 | D54: ="Derived: basis-weighted average of the per-property COP inputs in column F. Seeded "&TEXT($F$80,"0.00%")&" for El Poblado apartments and "&TEXT($F$83,"0.00%")&" for El Retiro houses, anchored to the DANE IPVN national-by-type print for 2026 Q1. Reviewed and held at that anchor (Sep 2026): the 2026 Q2 print reads "&TEXT('Medellín Market Data'!$D$23,"0.00%")&" for apartments and "&TEXT('Medellín Market Data'!$E$23,"0.00%")&" for houses, and the Medellín estrato alto (5–6) annual print reads "&TEXT('Medellín Market Data'!$F$29,"0.00%")&"; the multi-year record supports the seeds in use. Set each property in F74:F83. Reference 10." -> Derived: basis-weighted average of the per-property COP inputs in column F. Seeded 8.50% for El Poblado apartments and 7.15% for El Retiro houses, anchored to the DANE IPVN national-by-type print for 2026 Q1. Reviewed and held at that anchor (Sep 2026): the 2026 Q2 print reads 8.88% for apartments and 6.67% for houses, and the Medellín estrato alto (5–6) annual print reads 6.18%; the multi-year record supports the seeds in use. Set each property in F74:F83. Reference 10.
B55: Market appreciation (%/yr in USD, derived: COP appreciation net of peso depreciation) | C55: =(1+C54)/(1+C6)-1 -> 0.078087751 | D55: ="Derived: (1 + COP appreciation) ÷ (1 + peso depreciation) − 1. Reads identical to the COP rate above while peso depreciation is "&TEXT($C$6,"0.0%")&" — the two separate as soon as that input moves. Each property carries its own rate in column G, and that is what exit values and the return grids read." -> Derived: (1 + COP appreciation) ÷ (1 + peso depreciation) − 1. Reads identical to the COP rate above while peso depreciation is 0.0% — the two separate as soon as that input moves. Each property carries its own rate in column G, and that is what exit values and the return grids read.
B56: Final exit — last selected property sale (model month) | C56: {=MAX(Properties!$U$6:$U$15*Properties!$D$6:$D$15)} -> 43
B57: Model horizon (years) — through final selected exit (derived) | C57: =ROUNDUP(C56/'_IRR Engine'!$Q$7,0) -> 4
B59: References
B60: 1. Property data: Dulcinea portfolio overview and status, 8/26/26 (internal document)
B61: 2. Casa Montana works detail: Valores Aprox Obras Adicionales — Casa Montana Lote 02 (architect estimate, COP 1,318.6M)
B62: 3. Capital gains 15% ≥ 2-yr hold (Ley 2277 de 2022): nexo.legal/capital-gains-tax-colombia-2026-foreigners-selling-property
B63: 4. Buyer closing costs 1.5%–3.5%: jericocolombiarealestate.com — hidden costs of buying real estate in Colombia
B64: 5. Broker commission 3%–5%, notary tariffs: thelatinvestor.com — Medellín property taxes and fees 2026
B65: 6. ICA 0.2%–1.0% and 35% ordinary rate under 2-yr holds: globalpropertyguide.com — Colombia taxes and costs
B66: 7. Predial benchmarks: TheLatinvestor — Medellín property taxes (0.2%–0.6% of market price/yr) + El Poblado estrato-6 listings (Primavera Realty), 2026. thelatinvestor.com/blogs/news/medellin-property-taxes-fees
B67: 8. Administración & utilities: Colombia Move — Medellín rent guide 2026 (premium El Poblado towers COP 600k–2M+/mo administración; utilities COP 350k–600k/mo) + TheLatinvestor 2026. colombiamove.com/blog/average-rent-medellin-neighborhood-prices
B68: 9. Colombia compensation: LHH via La República — SME gerente/presidente COP 25–35M/mo; Computrabajo/Indeed — gerente general benchmarks, 2026. larepublica.co/empresas/cuanto-gana-un-gerente-ceo-o-presidente-de-empresa-en-colombia-3685939 | Business development & marketing roles: Michael Page Colombia salary comparison tool — Gerencia Comercial COP 17.5M/mo, Gerencia de Mercadeo COP 18.7M/mo (placement averages, excl. bonus); Computrabajo — gerente de desarrollo de negocios median COP 6.1M/mo, 2026. michaelpage.com.co/salary-comparison-tool
B69: 10. Market appreciation in USD (per-property inputs): PRIMARY SOURCE — DANE, Boletín técnico Índice de Precios de Vivienda Nueva (IPVN), II trimestre 2026: national annual variation 8.80% (Q2 2026 vs Q2 2025), apartments 8.88% and houses 6.67% annual; quarterly +2.41% vs Q1 2026 (houses +3.68%, apartments +2.37%). The IPVN measures PESO prices. Model holds COP appreciation as PER-PROPERTY inputs (Input F74:F83), seeded 8.50% for El Poblado apartments and 7.15% for El Retiro houses off the 2026 Q1 print, basis-weighting to 7.81% at C48. Peso depreciation at C6 is held at 0.0% by decision (see D6), so the derived USD rate at C49 is also 7.81% — the model applies no currency drag. Netting off the ~1.5%/yr long-run depreciation in ref 11 would instead give roughly 6.2% USD; that is a stress case, not the live assumption. dane.gov.co/files/operaciones/IPVN/bol-IPVN-IItrim2026.pdf | series page: dane.gov.co/index.php/estadisticas-por-tema/construccion/indice-de-precios-de-vivienda-nueva-ipvn. SECONDARY (city-level prints, press coverage of earlier DANE releases): Medellín +8.29% annual Q4 2025 and +8.77% full-year 2025 — elcolombiano.com, semana.com, infobae.com (Mar–May 2026)
B70: 11. USD/COP for the peso-to-dollar bridge: ~2,000 COP/USD in the early 2000s; all-time high 5,118 (Nov 2022); 2026 average 3,596–3,611, range 3,175–3,806; spot ~3,100–3,660 (Apr–Aug 2026), with the peso up 13–22% against the dollar over the trailing twelve months. Long-run depreciation therefore averages roughly 1.5%/yr, but the path is highly volatile. Model TRM is fixed at the Input input and FX is not projected. tradingeconomics.com/colombia/currency, exchangerates.org.uk, theglobaleconomy.com (2026)
... B75: 16. Long-term letting vacancy — El Poblado prime: roughly one month of vacancy a year for prime units in El Poblado or Laureles, up to two months in less desirable buildings (TheLatinvestor 2026); monthly-rental occupancy in El Poblado reported at 92.8% in Q1 2025 against 87% in 2024 (Medellín Advisors). Held at C160 for reference ONLY — the model underwrites short-stay letting, not long-term tenancy, so the short-stay band in reference 15 is the one that governs. NOT AN OFFICIAL SERIES. thelatinvestor.com/blogs/news/medellin-buy-rent-out
B78: Per-Property Operating Cost Inputs | C78: Unified property tax (IPU), effective (%/yr of all-in basis, derived = rate × cadastral valuation ÷ basis) | D78: Administración / HOA (COP M per month) | E78: Utilities (COP M per month) | F78: Market appreciation in COP (%/yr) | G78: Market appreciation in USD (%/yr, derived) | H78: STR vacancy (% of nights unbooked) | I78: Entry discount vs comparable (fully improved) | J78: STR daily rate (USD/night) | K78: Guidance — 4-week price vs 4-week cap (C170) | L78: Vacancy guidance — input vs researched band | M78: Renovation period (months) — no rent while under works | N78: Municipality — tax jurisdiction (Municipio) | O78: Unified property tax rate (Impuesto Predial Unificado — IPU) (‰ of cadastral valuation) | P78: Cadastral valuation (Avalúo Catastral) (% of purchase price) | Q78: Industry & commerce tax rate (Impuesto de Industria y Comercio — ICA) (‰ of gross revenue, CIIU 5519) | R78: Signage tax (Impuesto de Avisos y Tableros) (% of ICA) | S78: Tourism promotion levy (Contribución Parafiscal para la Promoción del Turismo — FONTUR) (‰ of operating revenue) | T78: Tax source / status | U78: STR revenue taxes — combined (Impuestos sobre ingresos STR) (% of revenue, derived)
B79: Property
B80: =Properties!E6 -> Aires de Campestre Apto 801 (Penthouse) | C80: =IFERROR(IF(N($O80)=0,0,$O80/1000*$P80*INDEX(Properties!$M$6:$M$15,MATCH($B80,Properties!$E$6:$E$15,0))/INDEX(Properties!$P$6:$P$15,MATCH($B80,Properties!$E$6:$E$15,0))),0) -> 0.005133601 | D80: 2.5 | E80: 1.2 | F80: 0.085 | G80: =IF($B80="","",(1+$F80)/(1+Input!$C$6)-1) -> 0.085 | H80: 0.4 | I80: 0.3 | J80: 270 | K80: =IF($B80="","","$"&TEXT($J80,"0")&"/night · 4-week stay $"&TEXT(MIN($C$171*$J80,$C$170),"#,##0")&IF($C$171*$J80>$C$170," · at cap"," · below cap")) -> $270/night · 4-week stay $7,560 · below cap | L80: =IF($B80="","",TEXT($H80,"0%")&" vacancy · "&IF(ISNUMBER(SEARCH("Retiro",INDEX(Properties!$F$6:$F$15,MATCH($B80,Properties!$E$6:$E$15,0)))),"El Retiro — no published series","Poblado prime "&TEXT($C$168,"0%")&"–"&TEXT($D$168,"0%")&" · "&IF($H80>$D$168,"above band (conservative)",IF($H80<$C$168,"below band","within band")))) -> 40% vacancy · Poblado prime 35%–50% · within band | M80: 6 | N80: =IF($B80="","",IFERROR(IF(ISNUMBER(SEARCH("Medellín",INDEX(Properties!$F$6:$F$15,MATCH($B80,Properties!$E$6:$E$15,0)))),"Medellín",TRIM(LEFT(INDEX(Properties!$F$6:$F$15,MATCH($B80,Properties!$E$6:$E$15,0)),FIND(",",INDEX(Properties!$F$6:$F$15,MATCH($B80,Properties!$E$6:$E$15,0))&",")-1))),"")) -> Medellín | O80: 15 | P80: 0.6 | Q80: 10 | R80: 0 | S80: 2.5 | T80: Medellín: IPU Acuerdo 066/2017 art. 20 (residencial >COP 811M avalúo = 14‰, >1,159M = 15‰); ICA 5519B 10‰ (7‰ with NTS-TS); Avisos 15% only if signage posted; FONTUR Ley 1101/2006 art. 2. | U80: =IF(N($Q80)=0,0,$Q80/1000*(1+N($R80))+N($S80)/1000) -> 0.0125
B81: =Properties!E7 -> Fontanar Apto 201 (Penthouse) | C81: =IFERROR(IF(N($O81)=0,0,$O81/1000*$P81*INDEX(Properties!$M$6:$M$15,MATCH($B81,Properties!$E$6:$E$15,0))/INDEX(Properties!$P$6:$P$15,MATCH($B81,Properties!$E$6:$E$15,0))),0) -> 0.0071074898 | D81: 2.2 | E81: 1 | F81: 0.085 | G81: =IF($B81="","",(1+$F81)/(1+Input!$C$6)-1) -> 0.085 | H81: 0.4 | I81: 0.3 | J81: 270 | K81: =IF($B81="","","$"&TEXT($J81,"0")&"/night · 4-week stay $"&TEXT(MIN($C$171*$J81,$C$170),"#,##0")&IF($C$171*$J81>$C$170," · at cap"," · below cap")) -> $270/night · 4-week stay $7,560 · below cap | L81: =IF($B81="","",TEXT($H81,"0%")&" vacancy · "&IF(ISNUMBER(SEARCH("Retiro",INDEX(Properties!$F$6:$F$15,MATCH($B81,Properties!$E$6:$E$15,0)))),"El Retiro — no published series","Poblado prime "&TEXT($C$168,"0%")&"–"&TEXT($D$168,"0%")&" · "&IF($H81>$D$168,"above band (conservative)",IF($H81<$C$168,"below band","within band")))) -> 40% vacancy · Poblado prime 35%–50% · within band | M81: 6 | N81: =IF($B81="","",IFERROR(IF(ISNUMBER(SEARCH("Medellín",INDEX(Properties!$F$6:$F$15,MATCH($B81,Properties!$E$6:$E$15,0)))),"Medellín",TRIM(LEFT(INDEX(Properties!$F$6:$F$15,MATCH($B81,Properties!$E$6:$E$15,0)),FIND(",",INDEX(Properties!$F$6:$F$15,MATCH($B81,Properties!$E$6:$E$15,0))&",")-1))),"")) -> Medellín | O81: 15 | P81: 0.6 | Q81: 10 | R81: 0 | S81: 2.5 | T81: Medellín: IPU Acuerdo 066/2017 art. 20 (residencial >COP 811M avalúo = 14‰, >1,159M = 15‰); ICA 5519B 10‰ (7‰ with NTS-TS); Avisos 15% only if signage posted; FONTUR Ley 1101/2006 art. 2. | U81: =IF(N($Q81)=0,0,$Q81/1000*(1+N($R81))+N($S81)/1000) -> 0.0125
B82: =Properties!E8 -> San Lucas Apto 101 | C82: =IFERROR(IF(N($O82)=0,0,$O82/1000*$P82*INDEX(Properties!$M$6:$M$15,MATCH($B82,Properties!$E$6:$E$15,0))/INDEX(Properties!$P$6:$P$15,MATCH($B82,Properties!$E$6:$E$15,0))),0) -> 0.0050013532 | D82: 1.8 | E82: 0.9 | F82: 0.085 | G82: =IF($B82="","",(1+$F82)/(1+Input!$C$6)-1) -> 0.085 | H82: 0.4 | I82: 0.3 | J82: 250 | K82: =IF($B82="","","$"&TEXT($J82,"0")&"/night · 4-week stay $"&TEXT(MIN($C$171*$J82,$C$170),"#,##0")&IF($C$171*$J82>$C$170," · at cap"," · below cap")) -> $250/night · 4-week stay $7,000 · below cap | L82: =IF($B82="","",TEXT($H82,"0%")&" vacancy · "&IF(ISNUMBER(SEARCH("Retiro",INDEX(Properties!$F$6:$F$15,MATCH($B82,Properties!$E$6:$E$15,0)))),"El Retiro — no published series","Poblado prime "&TEXT($C$168,"0%")&"–"&TEXT($D$168,"0%")&" · "&IF($H82>$D$168,"above band (conservative)",IF($H82<$C$168,"below band","within band")))) -> 40% vacancy · Poblado prime 35%–50% · within band | M82: 6 | N82: =IF($B82="","",IFERROR(IF(ISNUMBER(SEARCH("Medellín",INDEX(Properties!$F$6:$F$15,MATCH($B82,Properties!$E$6:$E$15,0)))),"Medellín",TRIM(LEFT(INDEX(Properties!$F$6:$F$15,MATCH($B82,Properties!$E$6:$E$15,0)),FIND(",",INDEX(Properties!$F$6:$F$15,MATCH($B82,Properties!$E$6:$E$15,0))&",")-1))),"")) -> Medellín | O82: 14 | P82: 0.6 | Q82: 10 | R82: 0 | S82: 2.5 | T82: Medellín: IPU Acuerdo 066/2017 art. 20 (residencial >COP 811M avalúo = 14‰, >1,159M = 15‰); ICA 5519B 10‰ (7‰ with NTS-TS); Avisos 15% only if signage posted; FONTUR Ley 1101/2006 art. 2. | U82: =IF(N($Q82)=0,0,$Q82/1000*(1+N($R82))+N($S82)/1000) -> 0.0125
B83: =Properties!E9 -> Casa Montana Lote 2 (Samuel Gaviria House) | C83: =IFERROR(IF(N($O83)=0,0,$O83/1000*$P83*INDEX(Properties!$M$6:$M$15,MATCH($B83,Properties!$E$6:$E$15,0))/INDEX(Properties!$P$6:$P$15,MATCH($B83,Properties!$E$6:$E$15,0))),0) -> 0.004770327 | D83: 2 | E83: 1.5 | F83: 0.0715 | G83: =IF($B83="","",(1+$F83)/(1+Input!$C$6)-1) -> 0.0715 | H83: 0.4 | I83: 0.3 | J83: 340 | K83: =IF($B83="","","$"&TEXT($J83,"0")&"/night · 4-week stay $"&TEXT(MIN($C$171*$J83,$C$170),"#,##0")&IF($C$171*$J83>$C$170," · at cap"," · below cap")) -> $340/night · 4-week stay $9,500 · at cap | L83: =IF($B83="","",TEXT($H83,"0%")&" vacancy · "&IF(ISNUMBER(SEARCH("Retiro",INDEX(Properties!$F$6:$F$15,MATCH($B83,Properties!$E$6:$E$15,0)))),"El Retiro — no published series","Poblado prime "&TEXT($C$168,"0%")&"–"&TEXT($D$168,"0%")&" · "&IF($H83>$D$168,"above band (conservative)",IF($H83<$C$168,"below band","within band")))) -> 40% vacancy · El Retiro — no published series | M83: 6 | N83: =IF($B83="","",IFERROR(IF(ISNUMBER(SEARCH("Medellín",INDEX(Properties!$F$6:$F$15,MATCH($B83,Properties!$E$6:$E$15,0)))),"Medellín",TRIM(LEFT(INDEX(Properties!$F$6:$F$15,MATCH($B83,Properties!$E$6:$E$15,0)),FIND(",",INDEX(Properties!$F$6:$F$15,MATCH($B83,Properties!$E$6:$E$15,0))&",")-1))),"")) -> El Retiro | O83: 12 | P83: 0.6 | Q83: 10 | R83: 0 | S83: 2.5 | T83: El Retiro: Acuerdo 016/2017 (Estatuto Tributario) — IPU and ICA tarifas NOT verified online (scanned acuerdo); placeholder rates, confirm with Secretaría de Hacienda El Retiro. FONTUR Ley 1101/2006 art. 2. | U83: =IF(N($Q83)=0,0,$Q83/1000*(1+N($R83))+N($S83)/1000) -> 0.0125
B84: =Properties!E10 -> Casa Monte Sereno | C84: =IFERROR(IF(N($O84)=0,0,$O84/1000*$P84*INDEX(Properties!$M$6:$M$15,MATCH($B84,Properties!$E$6:$E$15,0))/INDEX(Properties!$P$6:$P$15,MATCH($B84,Properties!$E$6:$E$15,0))),0) -> 0.0056470588 | D84: 2.5 | E84: 1.2 | F84: 0.0715 | G84: =IF($B84="","",(1+$F84)/(1+Input!$C$6)-1) -> 0.0715 | H84: 0.4 | I84: 0.3 | J84: 270 | K84: =IF($B84="","","$"&TEXT($J84,"0")&"/night · 4-week stay $"&TEXT(MIN($C$171*$J84,$C$170),"#,##0")&IF($C$171*$J84>$C$170," · at cap"," · below cap")) -> $270/night · 4-week stay $7,560 · below cap | L84: =IF($B84="","",TEXT($H84,"0%")&" vacancy · "&IF(ISNUMBER(SEARCH("Retiro",INDEX(Properties!$F$6:$F$15,MATCH($B84,Properties!$E$6:$E$15,0)))),"El Retiro — no published series","Poblado prime "&TEXT($C$168,"0%")&"–"&TEXT($D$168,"0%")&" · "&IF($H84>$D$168,"above band (conservative)",IF($H84<$C$168,"below band","within band")))) -> 40% vacancy · El Retiro — no published series | M84: 6 | N84: =IF($B84="","",IFERROR(IF(ISNUMBER(SEARCH("Medellín",INDEX(Properties!$F$6:$F$15,MATCH($B84,Properties!$E$6:$E$15,0)))),"Medellín",TRIM(LEFT(INDEX(Properties!$F$6:$F$15,MATCH($B84,Properties!$E$6:$E$15,0)),FIND(",",INDEX(Properties!$F$6:$F$15,MATCH($B84,Properties!$E$6:$E$15,0))&",")-1))),"")) -> El Retiro | O84: 12 | P84: 0.6 | Q84: 10 | R84: 0 | S84: 2.5 | T84: El Retiro: Acuerdo 016/2017 (Estatuto Tributario) — IPU and ICA tarifas NOT verified online (scanned acuerdo); placeholder rates, confirm with Secretaría de Hacienda El Retiro. FONTUR Ley 1101/2006 art. 2. | U84: =IF(N($Q84)=0,0,$Q84/1000*(1+N($R84))+N($S84)/1000) -> 0.0125
B85: =IF(Properties!$E11="","",Properties!$E11) | C85: =IFERROR(IF(N($O85)=0,0,$O85/1000*$P85*INDEX(Properties!$M$6:$M$15,MATCH($B85,Properties!$E$6:$E$15,0))/INDEX(Properties!$P$6:$P$15,MATCH($B85,Properties!$E$6:$E$15,0))),0) -> 0 | K85: =IF($B85="","","$"&TEXT($J85,"0")&"/night · 4-week stay $"&TEXT(MIN($C$171*$J85,$C$170),"#,##0")&IF($C$171*$J85>$C$170," · at cap"," · below cap")) | L85: =IF($B85="","",TEXT($H85,"0%")&" vacancy · "&IF(ISNUMBER(SEARCH("Retiro",INDEX(Properties!$F$6:$F$15,MATCH($B85,Properties!$E$6:$E$15,0)))),"El Retiro — no published series","Poblado prime "&TEXT($C$168,"0%")&"–"&TEXT($D$168,"0%")&" · "&IF($H85>$D$168,"above band (conservative)",IF($H85<$C$168,"below band","within band")))) | N85: =IF($B85="","",IFERROR(IF(ISNUMBER(SEARCH("Medellín",INDEX(Properties!$F$6:$F$15,MATCH($B85,Properties!$E$6:$E$15,0)))),"Medellín",TRIM(LEFT(INDEX(Properties!$F$6:$F$15,MATCH($B85,Properties!$E$6:$E$15,0)),FIND(",",INDEX(Properties!$F$6:$F$15,MATCH($B85,Properties!$E$6:$E$15,0))&",")-1))),"")) | U85: =IF(N($Q85)=0,0,$Q85/1000*(1+N($R85))+N($S85)/1000) -> 0
B86: =IF(Properties!$E12="","",Properties!$E12) | C86: =IFERROR(IF(N($O86)=0,0,$O86/1000*$P86*INDEX(Properties!$M$6:$M$15,MATCH($B86,Properties!$E$6:$E$15,0))/INDEX(Properties!$P$6:$P$15,MATCH($B86,Properties!$E$6:$E$15,0))),0) -> 0 | K86: =IF($B86="","","$"&TEXT($J86,"0")&"/night · 4-week stay $"&TEXT(MIN($C$171*$J86,$C$170),"#,##0")&IF($C$171*$J86>$C$170," · at cap"," · below cap")) | L86: =IF($B86="","",TEXT($H86,"0%")&" vacancy · "&IF(ISNUMBER(SEARCH("Retiro",INDEX(Properties!$F$6:$F$15,MATCH($B86,Properties!$E$6:$E$15,0)))),"El Retiro — no published series","Poblado prime "&TEXT($C$168,"0%")&"–"&TEXT($D$168,"0%")&" · "&IF($H86>$D$168,"above band (conservative)",IF($H86<$C$168,"below band","within band")))) | N86: =IF($B86="","",IFERROR(IF(ISNUMBER(SEARCH("Medellín",INDEX(Properties!$F$6:$F$15,MATCH($B86,Properties!$E$6:$E$15,0)))),"Medellín",TRIM(LEFT(INDEX(Properties!$F$6:$F$15,MATCH($B86,Properties!$E$6:$E$15,0)),FIND(",",INDEX(Properties!$F$6:$F$15,MATCH($B86,Properties!$E$6:$E$15,0))&",")-1))),"")) | U86: =IF(N($Q86)=0,0,$Q86/1000*(1+N($R86))+N($S86)/1000) -> 0
B87: =IF(Properties!$E13="","",Properties!$E13) | C87: =IFERROR(IF(N($O87)=0,0,$O87/1000*$P87*INDEX(Properties!$M$6:$M$15,MATCH($B87,Properties!$E$6:$E$15,0))/INDEX(Properties!$P$6:$P$15,MATCH($B87,Properties!$E$6:$E$15,0))),0) -> 0 | K87: =IF($B87="","","$"&TEXT($J87,"0")&"/night · 4-week stay $"&TEXT(MIN($C$171*$J87,$C$170),"#,##0")&IF($C$171*$J87>$C$170," · at cap"," · below cap")) | L87: =IF($B87="","",TEXT($H87,"0%")&" vacancy · "&IF(ISNUMBER(SEARCH("Retiro",INDEX(Properties!$F$6:$F$15,MATCH($B87,Properties!$E$6:$E$15,0)))),"El Retiro — no published series","Poblado prime "&TEXT($C$168,"0%")&"–"&TEXT($D$168,"0%")&" · "&IF($H87>$D$168,"above band (conservative)",IF($H87<$C$168,"below band","within band")))) | N87: =IF($B87="","",IFERROR(IF(ISNUMBER(SEARCH("Medellín",INDEX(Properties!$F$6:$F$15,MATCH($B87,Properties!$E$6:$E$15,0)))),"Medellín",TRIM(LEFT(INDEX(Properties!$F$6:$F$15,MATCH($B87,Properties!$E$6:$E$15,0)),FIND(",",INDEX(Properties!$F$6:$F$15,MATCH($B87,Properties!$E$6:$E$15,0))&",")-1))),"")) | U87: =IF(N($Q87)=0,0,$Q87/1000*(1+N($R87))+N($S87)/1000) -> 0
B88: =IF(Properties!$E14="","",Properties!$E14) | C88: =IFERROR(IF(N($O88)=0,0,$O88/1000*$P88*INDEX(Properties!$M$6:$M$15,MATCH($B88,Properties!$E$6:$E$15,0))/INDEX(Properties!$P$6:$P$15,MATCH($B88,Properties!$E$6:$E$15,0))),0) -> 0 | K88: =IF($B88="","","$"&TEXT($J88,"0")&"/night · 4-week stay $"&TEXT(MIN($C$171*$J88,$C$170),"#,##0")&IF($C$171*$J88>$C$170," · at cap"," · below cap")) | L88: =IF($B88="","",TEXT($H88,"0%")&" vacancy · "&IF(ISNUMBER(SEARCH("Retiro",INDEX(Properties!$F$6:$F$15,MATCH($B88,Properties!$E$6:$E$15,0)))),"El Retiro — no published series","Poblado prime "&TEXT($C$168,"0%")&"–"&TEXT($D$168,"0%")&" · "&IF($H88>$D$168,"above band (conservative)",IF($H88<$C$168,"below band","within band")))) | N88: =IF($B88="","",IFERROR(IF(ISNUMBER(SEARCH("Medellín",INDEX(Properties!$F$6:$F$15,MATCH($B88,Properties!$E$6:$E$15,0)))),"Medellín",TRIM(LEFT(INDEX(Properties!$F$6:$F$15,MATCH($B88,Properties!$E$6:$E$15,0)),FIND(",",INDEX(Properties!$F$6:$F$15,MATCH($B88,Properties!$E$6:$E$15,0))&",")-1))),"")) | U88: =IF(N($Q88)=0,0,$Q88/1000*(1+N($R88))+N($S88)/1000) -> 0
B89: =IF(Properties!$E15="","",Properties!$E15) | C89: =IFERROR(IF(N($O89)=0,0,$O89/1000*$P89*INDEX(Properties!$M$6:$M$15,MATCH($B89,Properties!$E$6:$E$15,0))/INDEX(Properties!$P$6:$P$15,MATCH($B89,Properties!$E$6:$E$15,0))),0) -> 0 | K89: =IF($B89="","","$"&TEXT($J89,"0")&"/night · 4-week stay $"&TEXT(MIN($C$171*$J89,$C$170),"#,##0")&IF($C$171*$J89>$C$170," · at cap"," · below cap")) | L89: =IF($B89="","",TEXT($H89,"0%")&" vacancy · "&IF(ISNUMBER(SEARCH("Retiro",INDEX(Properties!$F$6:$F$15,MATCH($B89,Properties!$E$6:$E$15,0)))),"El Retiro — no published series","Poblado prime "&TEXT($C$168,"0%")&"–"&TEXT($D$168,"0%")&" · "&IF($H89>$D$168,"above band (conservative)",IF($H89<$C$168,"below band","within band")))) | N89: =IF($B89="","",IFERROR(IF(ISNUMBER(SEARCH("Medellín",INDEX(Properties!$F$6:$F$15,MATCH($B89,Properties!$E$6:$E$15,0)))),"Medellín",TRIM(LEFT(INDEX(Properties!$F$6:$F$15,MATCH($B89,Properties!$E$6:$E$15,0)),FIND(",",INDEX(Properties!$F$6:$F$15,MATCH($B89,Properties!$E$6:$E$15,0))&",")-1))),"")) | U89: =IF(N($Q89)=0,0,$Q89/1000*(1+N($R89))+N($S89)/1000) -> 0
B91: ServCo Team
B92: ServCo personnel costs and per-role detail are handled on the confidential ServCo Personnel US and Colombia worksheets.
B93: ServCo — Transaction Fees (available, not charged) | D93: Source / basis
B94: Acquisition fee (% of purchase price) | C94: 0.01 | D94: Industry standard 1–2% of purchase price for sourcing, diligence, and closing
B95: Renovation management fee (% of works) | C95: 0.05 | D95: Development/construction-management standard 3–5% of project cost
B96: Disposition fee (% of gross sale price) | C96: 0.005 | D96: Industry standard 0.5–1% of sale price for marketing and closing the exit
B98: Model Checks
B99: Balance Sheet balances (Assets = Liabilities + Equity, all years) | C99: {=IF(SUMPRODUCT(ABS('Balance Sheet'!C22:L22))<1,"OK","CHECK")} -> OK
B100: Cash ties (Balance Sheet cash = Cash Flow Statement ending cash) | C100: {=IF(SUMPRODUCT(ABS('Balance Sheet'!C7:L7-'Statement of Cash Flows'!C54:L54))<1,"OK","CHECK")} -> OK
B101: Retained earnings roll-forward ties to cumulative net income | C101: =IF(ABS('Balance Sheet'!L18-SUM('Income Statement'!C155:L155))<1,"OK","CHECK") -> OK
B102: Property Detail rent ties to Income Statement rental revenue (all years) | C102: {=IF(SUMPRODUCT(ABS('Property Detail'!C232:L232-'Income Statement'!C7:L7))<1,"OK","CHECK")} -> OK
B103: All properties fully released at sale (engine basis = underwriting basis) | C103: =IF(ABS(SUM('_Month Engine'!$C$83:$DR$83)-SUMPRODUCT(Properties!$P$6:$P$15,Properties!$D$6:$D$15))<1,"OK","CHECK") -> OK
B104: Gross distributions (before carry) reconcile to cash paid out in the Cash Flow | C104: =IF(ABS('Investor Return'!C17+SUM('Statement of Cash Flows'!$C$48:$L$49))<1,"OK","CHECK") -> OK
B105: Capital-gains tax applied matches each property's actual hold (15% at ≥ 24 months, otherwise the 35% ordinary rate) | C105: {=IF(SUMPRODUCT(Properties!$D$6:$D$19*ABS(Properties!$AD$6:$AD$19-(Properties!$AB$6:$AB$19>Properties!$AN$6:$AN$19)*(Properties!$AB$6:$AB$19-Properties!$AN$6:$AN$19)*$C$26))<1,"OK","CHECK")} -> OK
B106: Rental operation income tax uses the 15% counsel-capped rate (no income taxed above 15%) | C106: =IF(MAX(Input!$C$25,Input!$C$26)<=0.15,"OK","CHECK") -> OK
B107: Monthly engine ties to the statements (capital called and distributions) | C107: ='_IRR Engine'!$Q$28 -> OK
B108: Monthly engine ties to Properties (basis deployed, net sale proceeds, gains tax) | C108: =IF(AND('_IRR Engine'!$Q$31="OK",'_IRR Engine'!$Q$34="OK",'_IRR Engine'!$Q$37="OK"),"OK","CHECK") -> OK
B109: Deal-level XIRR on Portfolio Analysis ties to the monthly engine | C109: =IF(ABS('Portfolio Analysis'!$E$13-'_IRR Engine'!$Q$16)<0.00001,"OK","CHECK") -> OK
B111: Statement Integrity — Foot & Cross-Foot
B112: Income Statement: total revenue = rental revenue + property sales | C112: {=IF(SUMPRODUCT(ABS('Income Statement'!$C$29:$L$29-('Income Statement'!$C$7:$L$7+'Income Statement'!$C$18:$L$18)))<1,"OK","CHECK")} -> OK
B113: Income Statement: rental revenue = sum of the per-property lines | C113: {=IF(MAX(ABS(_xlfn.BYCOL('Income Statement'!$C$8:$L$17,_xlfn.LAMBDA(_xlpm.c,SUM(_xlpm.c)))-'Income Statement'!$C$7:$L$7))<1,"OK","CHECK")} -> OK
B114: Income Statement: property sales = sum of the per-property lines | C114: {=IF(MAX(ABS(_xlfn.BYCOL('Income Statement'!$C$19:$L$28,_xlfn.LAMBDA(_xlpm.c,SUM(_xlpm.c)))-'Income Statement'!$C$18:$L$18))<1,"OK","CHECK")} -> OK
...

Sheet The Buy Box
B1: The Buy Box — Dulcinea I Acquisition Criteria
B2: What a property must look like to enter the fund · blue = Buy Box target · green = live link to the model
B4: Definition
B5: The Buy Box is our filter for what the fund buys. A property has to pass every criterion below — location, enjoyment, product, price, due diligence, remodel, operation, hold, deal size and return — before Dulcinea I commits capital. The short version: good homes in the right neighborhoods that Equity Investors will want to use, bought 20–30% below their renovated value, checked thoroughly so there are no expensive surprises, remodeled on schedule, and sold within the target hold.
B7: The Criteria
B8: Criterion | C8: Requirement | D8: Target
B9: 1 · Location | C9: El Poblado, Medellín (apartments and penthouses) and El Retiro, Antioquia (houses on land). Nothing outside these submarkets. | D9: El Poblado · El Retiro
B10: 2 · Enjoyment for Equity Investors | C10: A place Equity Investors would actually want to spend time in. Enjoying the homes is one of the core objectives of Dulcinea, alongside the return. | D10: Homes Equity Investors want to use
B11: 3 · Product | C11: Distinctive, larger homes with clear room to add value and appeal to international buyers and guests. | D11: 300–600 m²
B12: 4 · Entry price | C12: At least 20–30% below the home's renovated comparable value. This discount is the main source of return. | D12: 20–30% below improved value
B13: 5 · Transformation | C13: A full remodel including all furniture, fixtures and equipment, delivered turnkey on a defined schedule and budget. | D13: About 6 months of works
B14: 6 · Deep due diligence | C14: A thorough technical, legal and regulatory review before purchase — structure, roof, waterproofing, plumbing, electrical, humidity, site and soil, permits and licensing, title (tradición y libertad), liens, HOA rules for short-term rentals and pending assessments. The goal is to catch problems that would raise remodel costs or cause delays and push the property outside the other criteria. | D14: Full technical, legal & title review · works budget with contingency before commitment
B15: 7 · Operation | C15: Ready to rent as a fully equipped furnished home with a four-week minimum stay, priced in US dollars within the per-stay cap. | D15: $300–$1,000 per night · $9,500 cap per 28 nights
B16: 8 · Hold & exit | C16: Sell within about two to three years of purchase, once remodeled and seasoned as a rental. | D16: 24–36 months
B17: 9 · Deal size | C17: All-in cost per property sized to the fund so no single home dominates the portfolio. | D17: $750K–$2M all-in
B18: 10 · Minimum return | C18: Minimum deal-level IRR, after gains tax, each property must be underwritten to (per the 23 Sep 2026 corporate update). | D18: 20% IRR minimum
B20: Portfolio Check — Active Properties Against the Buy Box
B21: Property | C21: Location | D21: Size (m²) | E21: Entry discount | F21: Works (months) | G21: Daily rate (USD) | H21: Hold (months) | I21: All-in basis (USD) | J21: Inside the Buy Box?
B22: =Properties!$E$6 -> Aires de Campestre Apto 801 (Penthouse) | C22: =Properties!$F$6 -> El Poblado, Medellín | D22: =Properties!$I$6 -> 489 | E22: =Input!$I$80 -> 0.3 | F22: =Input!$M$80 -> 6 | G22: =Input!$J$80 -> 270 | H22: =Properties!$S$6 -> 28 | I22: =Properties!$P$6 -> 1168770.2 | J22: =IF(AND(OR(ISNUMBER(SEARCH("Poblado",C22)),ISNUMBER(SEARCH("Retiro",C22))),E22>=$C$35,H22<=$C$36,I22>0),"Yes","Review") -> Yes
B23: =Properties!$E$7 -> Fontanar Apto 201 (Penthouse) | C23: =Properties!$F$7 -> El Poblado, Medellín | D23: =Properties!$I$7 -> 389 | E23: =Input!$I$81 -> 0.3 | F23: =Input!$M$81 -> 6 | G23: =Input!$J$81 -> 270 | H23: =Properties!$S$7 -> 30 | I23: =Properties!$P$7 -> 1290857.6 | J23: =IF(AND(OR(ISNUMBER(SEARCH("Poblado",C23)),ISNUMBER(SEARCH("Retiro",C23))),E23>=$C$35,H23<=$C$36,I23>0),"Yes","Review") -> Yes
B24: =Properties!$E$8 -> San Lucas Apto 101 | C24: =Properties!$F$8 -> El Poblado, Medellín | D24: =Properties!$I$8 -> 325 | E24: =Input!$I$82 -> 0.3 | F24: =Input!$M$82 -> 6 | G24: =Input!$J$82 -> 250 | H24: =Properties!$S$8 -> 25 | I24: =Properties!$P$8 -> 747370.55 | J24: =IF(AND(OR(ISNUMBER(SEARCH("Poblado",C24)),ISNUMBER(SEARCH("Retiro",C24))),E24>=$C$35,H24<=$C$36,I24>0),"Yes","Review") -> Yes
B25: =Properties!$E$9 -> Casa Montana Lote 2 (Samuel Gaviria House) | C25: =Properties!$F$9 -> El Retiro, Antioquia | D25: =Properties!$I$9 -> 591 | E25: =Input!$I$83 -> 0.3 | F25: =Input!$M$83 -> 6 | G25: =Input!$J$83 -> 340 | H25: =Properties!$S$9 -> 35 | I25: =Properties!$P$9 -> 1714482.2 | J25: =IF(AND(OR(ISNUMBER(SEARCH("Poblado",C25)),ISNUMBER(SEARCH("Retiro",C25))),E25>=$C$35,H25<=$C$36,I25>0),"Yes","Review") -> Yes
B26: =Properties!$E$10 -> Casa Monte Sereno | C26: =Properties!$F$10 -> El Retiro, Antioquia | D26: =Properties!$I$10 -> 420 | E26: =Input!$I$84 -> 0.3 | F26: =Input!$M$84 -> 6 | G26: =Input!$J$84 -> 270 | H26: =Properties!$S$10 -> 32 | I26: =Properties!$P$10 -> 1650485.4 | J26: =IF(AND(OR(ISNUMBER(SEARCH("Poblado",C26)),ISNUMBER(SEARCH("Retiro",C26))),E26>=$C$35,H26<=$C$36,I26>0),"Yes","Review") -> Yes
B27: Test applied: target submarket · entry discount at or above the minimum · hold at or below the maximum (thresholds below).
B28: Portfolio deal-level IRR (after gains tax) vs 20% minimum | C28: ='_IRR Engine'!$Q$17 -> 0.2081031 | D28: =IF(C28>=$C$37,"Meets minimum","Below minimum") -> Meets minimum
B29: Sourcing Funnel (per the 23 Sep 2026 corporate update)
B30: Properties seen | C30: 60+ | D30: Visited and screened by the team
B31: Catalogued inside the Buy Box | C31: 14 | D31: Met the criteria and were documented
B32: Selected for Dulcinea I | C32: =SUM(Properties!$D$6:$D$15) -> 5 | D32: Active properties in the fund
B34: Buy Box Test Thresholds
B35: Minimum entry discount | C35: 0.2 | D35: Lower bound of the 20–30% entry-price criterion
B36: Maximum hold (months) | C36: 36 | D36: Upper bound of the two-to-three-year hold criterion
B37: Minimum deal-level IRR (after gains tax) | C37: 0.2 | D37: Buy Box minimum return — portfolio deal-level IRR is tested against it

Sheet Income Statement
B1: ="Dulcinea — Income Statement, Years 1–"&TEXT(Input!$C$57,"0")&" (USD) · through final sale" -> Dulcinea — Income Statement, Years 1–4 (USD) · through final sale
B2: Contribution-margin format. See Notes to Financials.
B4: Model year | C4: =COLUMN()-2 -> 1 | D4: =COLUMN()-2 -> 2 | E4: =COLUMN()-2 -> 3 | F4: =COLUMN()-2 -> 4 | G4: =COLUMN()-2 -> 5 | H4: =COLUMN()-2 -> 6 | I4: =COLUMN()-2 -> 7 | J4: =COLUMN()-2 -> 8 | ... L4: =COLUMN()-2 -> 10
B5: Period | C5: =TEXT(EDATE(Input!$C$7,(C4-1)*12),"mmm-yy")&" – "&TEXT(EDATE(Input!$C$7,C4*12-1),"mmm-yy") -> Oct-26 – Sep-27 | D5: =TEXT(EDATE(Input!$C$7,(D4-1)*12),"mmm-yy")&" – "&TEXT(EDATE(Input!$C$7,D4*12-1),"mmm-yy") -> Oct-27 – Sep-28 | E5: =TEXT(EDATE(Input!$C$7,(E4-1)*12),"mmm-yy")&" – "&TEXT(EDATE(Input!$C$7,E4*12-1),"mmm-yy") -> Oct-28 – Sep-29 | F5: =TEXT(EDATE(Input!$C$7,(F4-1)*12),"mmm-yy")&" – "&TEXT(EDATE(Input!$C$7,F4*12-1),"mmm-yy") -> Oct-29 – Sep-30 | G5: =TEXT(EDATE(Input!$C$7,(G4-1)*12),"mmm-yy")&" – "&TEXT(EDATE(Input!$C$7,G4*12-1),"mmm-yy") -> Oct-30 – Sep-31 | H5: =TEXT(EDATE(Input!$C$7,(H4-1)*12),"mmm-yy")&" – "&TEXT(EDATE(Input!$C$7,H4*12-1),"mmm-yy") -> Oct-31 – Sep-32 | I5: =TEXT(EDATE(Input!$C$7,(I4-1)*12),"mmm-yy")&" – "&TEXT(EDATE(Input!$C$7,I4*12-1),"mmm-yy") -> Oct-32 – Sep-33 | J5: =TEXT(EDATE(Input!$C$7,(J4-1)*12),"mmm-yy")&" – "&TEXT(EDATE(Input!$C$7,J4*12-1),"mmm-yy") -> Oct-33 – Sep-34 | ... L5: =TEXT(EDATE(Input!$C$7,(L4-1)*12),"mmm-yy")&" – "&TEXT(EDATE(Input!$C$7,L4*12-1),"mmm-yy") -> Oct-35 – Sep-36
B6: Revenue
B7: STR rental revenue | C7: =SUMIF('_Month Engine'!$C$5:$DR$5,C$4,'_Month Engine'!$C$44:$DR$44) -> 84225.675 | D7: =SUMIF('_Month Engine'!$C$5:$DR$5,D$4,'_Month Engine'!$C$44:$DR$44) -> 308211.84 | E7: =SUMIF('_Month Engine'!$C$5:$DR$5,E$4,'_Month Engine'!$C$44:$DR$44) -> 210510.48 | F7: =SUMIF('_Month Engine'!$C$5:$DR$5,F$4,'_Month Engine'!$C$44:$DR$44) -> 40478.989 | G7: =SUMIF('_Month Engine'!$C$5:$DR$5,G$4,'_Month Engine'!$C$44:$DR$44) -> 0 | H7: =SUMIF('_Month Engine'!$C$5:$DR$5,H$4,'_Month Engine'!$C$44:$DR$44) -> 0 | I7: =SUMIF('_Month Engine'!$C$5:$DR$5,I$4,'_Month Engine'!$C$44:$DR$44) -> 0 | J7: =SUMIF('_Month Engine'!$C$5:$DR$5,J$4,'_Month Engine'!$C$44:$DR$44) -> 0 | ... L7: =SUMIF('_Month Engine'!$C$5:$DR$5,L$4,'_Month Engine'!$C$44:$DR$44) -> 0
B8: =IF(Properties!$D$6=0,"",Properties!E6) -> Aires de Campestre Apto 801 (Penthouse) | C8: ='Property Detail'!C8 -> 25517.025 | D8: ='Property Detail'!D8 -> 60811.625 | E8: ='Property Detail'!E8 -> 26681.485 | F8: ='Property Detail'!F8 -> 0 | G8: ='Property Detail'!G8 -> 0 | H8: ='Property Detail'!H8 -> 0 | I8: ='Property Detail'!I8 -> 0 | J8: ='Property Detail'!J8 -> 0 | ... L8: ='Property Detail'!L8 -> 0
B9: =IF(Properties!$D$7=0,"",Properties!E7) -> Fontanar Apto 201 (Penthouse) | C9: ='Property Detail'!C24 -> 29441.475 | D9: ='Property Detail'!D24 -> 60811.625 | E9: ='Property Detail'!E24 -> 31396.947 | F9: ='Property Detail'!F24 -> 0 | G9: ='Property Detail'!G24 -> 0 | H9: ='Property Detail'!H24 -> 0 | I9: ='Property Detail'!I24 -> 0 | J9: ='Property Detail'!J24 -> 0 | ... L9: ='Property Detail'!L24 -> 0
B10: =IF(Properties!$D$8=0,"",Properties!E8) -> San Lucas Apto 101 | C10: ='Property Detail'!C40 -> 20069.625 | D10: ='Property Detail'!D40 -> 56307.06 | E10: ='Property Detail'!E40 -> 14215.505 | F10: ='Property Detail'!F40 -> 0 | G10: ='Property Detail'!G40 -> 0 | H10: ='Property Detail'!H40 -> 0 | I10: ='Property Detail'!I40 -> 0 | J10: ='Property Detail'!J40 -> 0 | ... L10: ='Property Detail'!L40 -> 0
B11: =IF(Properties!$D$9=0,"",Properties!E9) -> Casa Montana Lote 2 (Samuel Gaviria House) | C11: ='Property Detail'!C56 -> 0 | D11: ='Property Detail'!D56 -> 69124.14 | E11: ='Property Detail'!E56 -> 75836.01 | F11: ='Property Detail'!F56 -> 40478.989 | G11: ='Property Detail'!G56 -> 0 | H11: ='Property Detail'!H56 -> 0 | I11: ='Property Detail'!I56 -> 0 | J11: ='Property Detail'!J56 -> 0 | ... L11: ='Property Detail'!L56 -> 0
B12: =IF(Properties!$D$10=0,"",Properties!E10) -> Casa Monte Sereno | C12: ='Property Detail'!C72 -> 9197.55 | D12: ='Property Detail'!D72 -> 61157.389 | E12: ='Property Detail'!E72 -> 62380.537 | F12: ='Property Detail'!F72 -> 0 | G12: ='Property Detail'!G72 -> 0 | H12: ='Property Detail'!H72 -> 0 | I12: ='Property Detail'!I72 -> 0 | J12: ='Property Detail'!J72 -> 0 | ... L12: ='Property Detail'!L72 -> 0
B13: =IF(Properties!$D$11=0,"",Properties!E11) | C13: ='Property Detail'!C88 -> 0 | D13: ='Property Detail'!D88 -> 0 | E13: ='Property Detail'!E88 -> 0 | F13: ='Property Detail'!F88 -> 0 | G13: ='Property Detail'!G88 -> 0 | H13: ='Property Detail'!H88 -> 0 | I13: ='Property Detail'!I88 -> 0 | J13: ='Property Detail'!J88 -> 0 | ... L13: ='Property Detail'!L88 -> 0
B14: =IF(Properties!$D$12=0,"",Properties!E12) | C14: ='Property Detail'!C104 -> 0 | D14: ='Property Detail'!D104 -> 0 | E14: ='Property Detail'!E104 -> 0 | F14: ='Property Detail'!F104 -> 0 | G14: ='Property Detail'!G104 -> 0 | H14: ='Property Detail'!H104 -> 0 | I14: ='Property Detail'!I104 -> 0 | J14: ='Property Detail'!J104 -> 0 | ... L14: ='Property Detail'!L104 -> 0
B15: =IF(Properties!$D$13=0,"",Properties!E13) | C15: ='Property Detail'!C120 -> 0 | D15: ='Property Detail'!D120 -> 0 | E15: ='Property Detail'!E120 -> 0 | F15: ='Property Detail'!F120 -> 0 | G15: ='Property Detail'!G120 -> 0 | H15: ='Property Detail'!H120 -> 0 | I15: ='Property Detail'!I120 -> 0 | J15: ='Property Detail'!J120 -> 0 | ... L15: ='Property Detail'!L120 -> 0
B16: =IF(Properties!$D$14=0,"",Properties!E14) | C16: ='Property Detail'!C136 -> 0 | D16: ='Property Detail'!D136 -> 0 | E16: ='Property Detail'!E136 -> 0 | F16: ='Property Detail'!F136 -> 0 | G16: ='Property Detail'!G136 -> 0 | H16: ='Property Detail'!H136 -> 0 | I16: ='Property Detail'!I136 -> 0 | J16: ='Property Detail'!J136 -> 0 | ... L16: ='Property Detail'!L136 -> 0
B17: =IF(Properties!$D$15=0,"",Properties!E15) | C17: ='Property Detail'!C152 -> 0 | D17: ='Property Detail'!D152 -> 0 | E17: ='Property Detail'!E152 -> 0 | F17: ='Property Detail'!F152 -> 0 | G17: ='Property Detail'!G152 -> 0 | H17: ='Property Detail'!H152 -> 0 | I17: ='Property Detail'!I152 -> 0 | J17: ='Property Detail'!J152 -> 0 | ... L17: ='Property Detail'!L152 -> 0
B18: Property sales (gross) | C18: =SUMIF('_Month Engine'!$C$5:$DR$5,C$4,'_Month Engine'!$C$71:$DR$71) -> 0 | D18: =SUMIF('_Month Engine'!$C$5:$DR$5,D$4,'_Month Engine'!$C$71:$DR$71) -> 0 | E18: =SUMIF('_Month Engine'!$C$5:$DR$5,E$4,'_Month Engine'!$C$71:$DR$71) -> 5546509.2 | F18: =SUMIF('_Month Engine'!$C$5:$DR$5,F$4,'_Month Engine'!$C$71:$DR$71) -> 5830401.8 | G18: =SUMIF('_Month Engine'!$C$5:$DR$5,G$4,'_Month Engine'!$C$71:$DR$71) -> 0 | H18: =SUMIF('_Month Engine'!$C$5:$DR$5,H$4,'_Month Engine'!$C$71:$DR$71) -> 0 | I18: =SUMIF('_Month Engine'!$C$5:$DR$5,I$4,'_Month Engine'!$C$71:$DR$71) -> 0 | J18: =SUMIF('_Month Engine'!$C$5:$DR$5,J$4,'_Month Engine'!$C$71:$DR$71) -> 0 | ... L18: =SUMIF('_Month Engine'!$C$5:$DR$5,L$4,'_Month Engine'!$C$71:$DR$71) -> 0
B19: =IF(Properties!$D$6=0,"",Properties!E6) -> Aires de Campestre Apto 801 (Penthouse) | C19: =IF(ROUNDUP(Properties!$U6/'_IRR Engine'!$Q$7,0)=C$4,Properties!$D6*Properties!$W6,0) -> 0 | D19: =IF(ROUNDUP(Properties!$U6/'_IRR Engine'!$Q$7,0)=D$4,Properties!$D6*Properties!$W6,0) -> 0 | E19: =IF(ROUNDUP(Properties!$U6/'_IRR Engine'!$Q$7,0)=E$4,Properties!$D6*Properties!$W6,0) -> 2019763.4 | F19: =IF(ROUNDUP(Properties!$U6/'_IRR Engine'!$Q$7,0)=F$4,Properties!$D6*Properties!$W6,0) -> 0 | G19: =IF(ROUNDUP(Properties!$U6/'_IRR Engine'!$Q$7,0)=G$4,Properties!$D6*Properties!$W6,0) -> 0 | H19: =IF(ROUNDUP(Properties!$U6/'_IRR Engine'!$Q$7,0)=H$4,Properties!$D6*Properties!$W6,0) -> 0 | I19: =IF(ROUNDUP(Properties!$U6/'_IRR Engine'!$Q$7,0)=I$4,Properties!$D6*Properties!$W6,0) -> 0 | J19: =IF(ROUNDUP(Properties!$U6/'_IRR Engine'!$Q$7,0)=J$4,Properties!$D6*Properties!$W6,0) -> 0 | ... L19: =IF(ROUNDUP(Properties!$U6/'_IRR Engine'!$Q$7,0)=L$4,Properties!$D6*Properties!$W6,0) -> 0
B20: =IF(Properties!$D$7=0,"",Properties!E7) -> Fontanar Apto 201 (Penthouse) | C20: =IF(ROUNDUP(Properties!$U7/'_IRR Engine'!$Q$7,0)=C$4,Properties!$D7*Properties!$W7,0) -> 0 | D20: =IF(ROUNDUP(Properties!$U7/'_IRR Engine'!$Q$7,0)=D$4,Properties!$D7*Properties!$W7,0) -> 0 | E20: =IF(ROUNDUP(Properties!$U7/'_IRR Engine'!$Q$7,0)=E$4,Properties!$D7*Properties!$W7,0) -> 2261281.6 | F20: =IF(ROUNDUP(Properties!$U7/'_IRR Engine'!$Q$7,0)=F$4,Properties!$D7*Properties!$W7,0) -> 0 | G20: =IF(ROUNDUP(Properties!$U7/'_IRR Engine'!$Q$7,0)=G$4,Properties!$D7*Properties!$W7,0) -> 0 | H20: =IF(ROUNDUP(Properties!$U7/'_IRR Engine'!$Q$7,0)=H$4,Properties!$D7*Properties!$W7,0) -> 0 | I20: =IF(ROUNDUP(Properties!$U7/'_IRR Engine'!$Q$7,0)=I$4,Properties!$D7*Properties!$W7,0) -> 0 | J20: =IF(ROUNDUP(Properties!$U7/'_IRR Engine'!$Q$7,0)=J$4,Properties!$D7*Properties!$W7,0) -> 0 | ... L20: =IF(ROUNDUP(Properties!$U7/'_IRR Engine'!$Q$7,0)=L$4,Properties!$D7*Properties!$W7,0) -> 0
B21: =IF(Properties!$D$8=0,"",Properties!E8) -> San Lucas Apto 101 | C21: =IF(ROUNDUP(Properties!$U8/'_IRR Engine'!$Q$7,0)=C$4,Properties!$D8*Properties!$W8,0) -> 0 | D21: =IF(ROUNDUP(Properties!$U8/'_IRR Engine'!$Q$7,0)=D$4,Properties!$D8*Properties!$W8,0) -> 0 | E21: =IF(ROUNDUP(Properties!$U8/'_IRR Engine'!$Q$7,0)=E$4,Properties!$D8*Properties!$W8,0) -> 1265464.3 | F21: =IF(ROUNDUP(Properties!$U8/'_IRR Engine'!$Q$7,0)=F$4,Properties!$D8*Properties!$W8,0) -> 0 | G21: =IF(ROUNDUP(Properties!$U8/'_IRR Engine'!$Q$7,0)=G$4,Properties!$D8*Properties!$W8,0) -> 0 | H21: =IF(ROUNDUP(Properties!$U8/'_IRR Engine'!$Q$7,0)=H$4,Properties!$D8*Properties!$W8,0) -> 0 | I21: =IF(ROUNDUP(Properties!$U8/'_IRR Engine'!$Q$7,0)=I$4,Properties!$D8*Properties!$W8,0) -> 0 | J21: =IF(ROUNDUP(Properties!$U8/'_IRR Engine'!$Q$7,0)=J$4,Properties!$D8*Properties!$W8,0) -> 0 | ... L21: =IF(ROUNDUP(Properties!$U8/'_IRR Engine'!$Q$7,0)=L$4,Properties!$D8*Properties!$W8,0) -> 0
B22: =IF(Properties!$D$9=0,"",Properties!E9) -> Casa Montana Lote 2 (Samuel Gaviria House) | C22: =IF(ROUNDUP(Properties!$U9/'_IRR Engine'!$Q$7,0)=C$4,Properties!$D9*Properties!$W9,0) -> 0 | D22: =IF(ROUNDUP(Properties!$U9/'_IRR Engine'!$Q$7,0)=D$4,Properties!$D9*Properties!$W9,0) -> 0 | E22: =IF(ROUNDUP(Properties!$U9/'_IRR Engine'!$Q$7,0)=E$4,Properties!$D9*Properties!$W9,0) -> 0 | F22: =IF(ROUNDUP(Properties!$U9/'_IRR Engine'!$Q$7,0)=F$4,Properties!$D9*Properties!$W9,0) -> 2995795.2 | G22: =IF(ROUNDUP(Properties!$U9/'_IRR Engine'!$Q$7,0)=G$4,Properties!$D9*Properties!$W9,0) -> 0 | H22: =IF(ROUNDUP(Properties!$U9/'_IRR Engine'!$Q$7,0)=H$4,Properties!$D9*Properties!$W9,0) -> 0 | I22: =IF(ROUNDUP(Properties!$U9/'_IRR Engine'!$Q$7,0)=I$4,Properties!$D9*Properties!$W9,0) -> 0 | J22: =IF(ROUNDUP(Properties!$U9/'_IRR Engine'!$Q$7,0)=J$4,Properties!$D9*Properties!$W9,0) -> 0 | ... L22: =IF(ROUNDUP(Properties!$U9/'_IRR Engine'!$Q$7,0)=L$4,Properties!$D9*Properties!$W9,0) -> 0
B23: =IF(Properties!$D$10=0,"",Properties!E10) -> Casa Monte Sereno | C23: =IF(ROUNDUP(Properties!$U10/'_IRR Engine'!$Q$7,0)=C$4,Properties!$D10*Properties!$W10,0) -> 0 | D23: =IF(ROUNDUP(Properties!$U10/'_IRR Engine'!$Q$7,0)=D$4,Properties!$D10*Properties!$W10,0) -> 0 | E23: =IF(ROUNDUP(Properties!$U10/'_IRR Engine'!$Q$7,0)=E$4,Properties!$D10*Properties!$W10,0) -> 0 | F23: =IF(ROUNDUP(Properties!$U10/'_IRR Engine'!$Q$7,0)=F$4,Properties!$D10*Properties!$W10,0) -> 2834606.6 | G23: =IF(ROUNDUP(Properties!$U10/'_IRR Engine'!$Q$7,0)=G$4,Properties!$D10*Properties!$W10,0) -> 0 | H23: =IF(ROUNDUP(Properties!$U10/'_IRR Engine'!$Q$7,0)=H$4,Properties!$D10*Properties!$W10,0) -> 0 | I23: =IF(ROUNDUP(Properties!$U10/'_IRR Engine'!$Q$7,0)=I$4,Properties!$D10*Properties!$W10,0) -> 0 | J23: =IF(ROUNDUP(Properties!$U10/'_IRR Engine'!$Q$7,0)=J$4,Properties!$D10*Properties!$W10,0) -> 0 | ... L23: =IF(ROUNDUP(Properties!$U10/'_IRR Engine'!$Q$7,0)=L$4,Properties!$D10*Properties!$W10,0) -> 0
B24: =IF(Properties!$D$11=0,"",Properties!E11) | C24: =IF(ROUNDUP(Properties!$U11/'_IRR Engine'!$Q$7,0)=C$4,Properties!$D11*Properties!$W11,0) -> 0 | D24: =IF(ROUNDUP(Properties!$U11/'_IRR Engine'!$Q$7,0)=D$4,Properties!$D11*Properties!$W11,0) -> 0 | E24: =IF(ROUNDUP(Properties!$U11/'_IRR Engine'!$Q$7,0)=E$4,Properties!$D11*Properties!$W11,0) -> 0 | F24: =IF(ROUNDUP(Properties!$U11/'_IRR Engine'!$Q$7,0)=F$4,Properties!$D11*Properties!$W11,0) -> 0 | G24: =IF(ROUNDUP(Properties!$U11/'_IRR Engine'!$Q$7,0)=G$4,Properties!$D11*Properties!$W11,0) -> 0 | H24: =IF(ROUNDUP(Properties!$U11/'_IRR Engine'!$Q$7,0)=H$4,Properties!$D11*Properties!$W11,0) -> 0 | I24: =IF(ROUNDUP(Properties!$U11/'_IRR Engine'!$Q$7,0)=I$4,Properties!$D11*Properties!$W11,0) -> 0 | J24: =IF(ROUNDUP(Properties!$U11/'_IRR Engine'!$Q$7,0)=J$4,Properties!$D11*Properties!$W11,0) -> 0 | ... L24: =IF(ROUNDUP(Properties!$U11/'_IRR Engine'!$Q$7,0)=L$4,Properties!$D11*Properties!$W11,0) -> 0
B25: =IF(Properties!$D$12=0,"",Properties!E12) | C25: =IF(ROUNDUP(Properties!$U12/'_IRR Engine'!$Q$7,0)=C$4,Properties!$D12*Properties!$W12,0) -> 0 | D25: =IF(ROUNDUP(Properties!$U12/'_IRR Engine'!$Q$7,0)=D$4,Properties!$D12*Properties!$W12,0) -> 0 | E25: =IF(ROUNDUP(Properties!$U12/'_IRR Engine'!$Q$7,0)=E$4,Properties!$D12*Properties!$W12,0) -> 0 | F25: =IF(ROUNDUP(Properties!$U12/'_IRR Engine'!$Q$7,0)=F$4,Properties!$D12*Properties!$W12,0) -> 0 | G25: =IF(ROUNDUP(Properties!$U12/'_IRR Engine'!$Q$7,0)=G$4,Properties!$D12*Properties!$W12,0) -> 0 | H25: =IF(ROUNDUP(Properties!$U12/'_IRR Engine'!$Q$7,0)=H$4,Properties!$D12*Properties!$W12,0) -> 0 | I25: =IF(ROUNDUP(Properties!$U12/'_IRR Engine'!$Q$7,0)=I$4,Properties!$D12*Properties!$W12,0) -> 0 | J25: =IF(ROUNDUP(Properties!$U12/'_IRR Engine'!$Q$7,0)=J$4,Properties!$D12*Properties!$W12,0) -> 0 | ... L25: =IF(ROUNDUP(Properties!$U12/'_IRR Engine'!$Q$7,0)=L$4,Properties!$D12*Properties!$W12,0) -> 0
B26: =IF(Properties!$D$13=0,"",Properties!E13) | C26: =IF(ROUNDUP(Properties!$U13/'_IRR Engine'!$Q$7,0)=C$4,Properties!$D13*Properties!$W13,0) -> 0 | D26: =IF(ROUNDUP(Properties!$U13/'_IRR Engine'!$Q$7,0)=D$4,Properties!$D13*Properties!$W13,0) -> 0 | E26: =IF(ROUNDUP(Properties!$U13/'_IRR Engine'!$Q$7,0)=E$4,Properties!$D13*Properties!$W13,0) -> 0 | F26: =IF(ROUNDUP(Properties!$U13/'_IRR Engine'!$Q$7,0)=F$4,Properties!$D13*Properties!$W13,0) -> 0 | G26: =IF(ROUNDUP(Properties!$U13/'_IRR Engine'!$Q$7,0)=G$4,Properties!$D13*Properties!$W13,0) -> 0 | H26: =IF(ROUNDUP(Properties!$U13/'_IRR Engine'!$Q$7,0)=H$4,Properties!$D13*Properties!$W13,0) -> 0 | I26: =IF(ROUNDUP(Properties!$U13/'_IRR Engine'!$Q$7,0)=I$4,Properties!$D13*Properties!$W13,0) -> 0 | J26: =IF(ROUNDUP(Properties!$U13/'_IRR Engine'!$Q$7,0)=J$4,Properties!$D13*Properties!$W13,0) -> 0 | ... L26: =IF(ROUNDUP(Properties!$U13/'_IRR Engine'!$Q$7,0)=L$4,Properties!$D13*Properties!$W13,0) -> 0
B27: =IF(Properties!$D$14=0,"",Properties!E14) | C27: =IF(ROUNDUP(Properties!$U14/'_IRR Engine'!$Q$7,0)=C$4,Properties!$D14*Properties!$W14,0) -> 0 | D27: =IF(ROUNDUP(Properties!$U14/'_IRR Engine'!$Q$7,0)=D$4,Properties!$D14*Properties!$W14,0) -> 0 | E27: =IF(ROUNDUP(Properties!$U14/'_IRR Engine'!$Q$7,0)=E$4,Properties!$D14*Properties!$W14,0) -> 0 | F27: =IF(ROUNDUP(Properties!$U14/'_IRR Engine'!$Q$7,0)=F$4,Properties!$D14*Properties!$W14,0) -> 0 | G27: =IF(ROUNDUP(Properties!$U14/'_IRR Engine'!$Q$7,0)=G$4,Properties!$D14*Properties!$W14,0) -> 0 | H27: =IF(ROUNDUP(Properties!$U14/'_IRR Engine'!$Q$7,0)=H$4,Properties!$D14*Properties!$W14,0) -> 0 | I27: =IF(ROUNDUP(Properties!$U14/'_IRR Engine'!$Q$7,0)=I$4,Properties!$D14*Properties!$W14,0) -> 0 | J27: =IF(ROUNDUP(Properties!$U14/'_IRR Engine'!$Q$7,0)=J$4,Properties!$D14*Properties!$W14,0) -> 0 | ... L27: =IF(ROUNDUP(Properties!$U14/'_IRR Engine'!$Q$7,0)=L$4,Properties!$D14*Properties!$W14,0) -> 0
B28: =IF(Properties!$D$15=0,"",Properties!E15) | C28: =IF(ROUNDUP(Properties!$U15/'_IRR Engine'!$Q$7,0)=C$4,Properties!$D15*Properties!$W15,0) -> 0 | D28: =IF(ROUNDUP(Properties!$U15/'_IRR Engine'!$Q$7,0)=D$4,Properties!$D15*Properties!$W15,0) -> 0 | E28: =IF(ROUNDUP(Properties!$U15/'_IRR Engine'!$Q$7,0)=E$4,Properties!$D15*Properties!$W15,0) -> 0 | F28: =IF(ROUNDUP(Properties!$U15/'_IRR Engine'!$Q$7,0)=F$4,Properties!$D15*Properties!$W15,0) -> 0 | G28: =IF(ROUNDUP(Properties!$U15/'_IRR Engine'!$Q$7,0)=G$4,Properties!$D15*Properties!$W15,0) -> 0 | H28: =IF(ROUNDUP(Properties!$U15/'_IRR Engine'!$Q$7,0)=H$4,Properties!$D15*Properties!$W15,0) -> 0 | I28: =IF(ROUNDUP(Properties!$U15/'_IRR Engine'!$Q$7,0)=I$4,Properties!$D15*Properties!$W15,0) -> 0 | J28: =IF(ROUNDUP(Properties!$U15/'_IRR Engine'!$Q$7,0)=J$4,Properties!$D15*Properties!$W15,0) -> 0 | ... L28: =IF(ROUNDUP(Properties!$U15/'_IRR Engine'!$Q$7,0)=L$4,Properties!$D15*Properties!$W15,0) -> 0
B29: Total revenue | C29: =C7+C18 -> 84225.675 | D29: =D7+D18 -> 308211.84 | E29: =E7+E18 -> 5757019.7 | F29: =F7+F18 -> 5870880.8 | G29: =G7+G18 -> 0 | H29: =H7+H18 -> 0 | I29: =I7+I18 -> 0 | J29: =J7+J18 -> 0 | ... L29: =L7+L18 -> 0
B31: Contribution Margin by Property
B32: =$B$8 -> Aires de Campestre Apto 801 (Penthouse)
B33: Rental revenue | C33: =C8 -> 25517.025 | D33: =D8 -> 60811.625 | E33: =E8 -> 26681.485 | F33: =F8 -> 0 | G33: =G8 -> 0 | H33: =H8 -> 0 | I33: =I8 -> 0 | J33: =J8 -> 0 | ... L33: =L8 -> 0
B34: Property sale (gross) | C34: =C19 -> 0 | D34: =D19 -> 0 | E34: =E19 -> 2019763.4 | F34: =F19 -> 0 | G34: =G19 -> 0 | H34: =H19 -> 0 | I34: =I19 -> 0 | J34: =J19 -> 0 | ... L34: =L19 -> 0
B35: Less: housekeeping & turnover | C35: ='Property Detail'!C14 -> 0 | D35: ='Property Detail'!D14 -> 0 | E35: ='Property Detail'!E14 -> 0 | F35: ='Property Detail'!F14 -> 0 | G35: ='Property Detail'!G14 -> 0 | H35: ='Property Detail'!H14 -> 0 | I35: ='Property Detail'!I14 -> 0 | J35: ='Property Detail'!J14 -> 0 | ... L35: ='Property Detail'!L14 -> 0
B36: Less: property management & housekeeping | C36: ='Property Detail'!C16 -> 5103.405 | D36: ='Property Detail'!D16 -> 12162.325 | E36: ='Property Detail'!E16 -> 5336.2969 | F36: ='Property Detail'!F16 -> 0 | G36: ='Property Detail'!G16 -> 0 | H36: ='Property Detail'!H16 -> 0 | I36: ='Property Detail'!I16 -> 0 | J36: ='Property Detail'!J16 -> 0 | ... L36: ='Property Detail'!L16 -> 0
B37: Less: STR revenue taxes (ICA, FONTUR) | C37: ='Property Detail'!C15 -> 318.96281 | D37: ='Property Detail'!D15 -> 760.14531 | E37: ='Property Detail'!E15 -> 333.51856 | F37: ='Property Detail'!F15 -> 0 | G37: ='Property Detail'!G15 -> 0 | H37: ='Property Detail'!H15 -> 0 | I37: ='Property Detail'!I15 -> 0 | J37: ='Property Detail'!J15 -> 0 | ... L37: ='Property Detail'!L15 -> 0
B38: Less: cost basis released on sale | C38: =SUMIF('_Month Engine'!$C$5:$DR$5,C$4,'_Month Engine'!$C$73:$DR$73) -> 0 | D38: =SUMIF('_Month Engine'!$C$5:$DR$5,D$4,'_Month Engine'!$C$73:$DR$73) -> 0 | E38: =SUMIF('_Month Engine'!$C$5:$DR$5,E$4,'_Month Engine'!$C$73:$DR$73) -> 1168770.2 | F38: =SUMIF('_Month Engine'!$C$5:$DR$5,F$4,'_Month Engine'!$C$73:$DR$73) -> 0 | G38: =SUMIF('_Month Engine'!$C$5:$DR$5,G$4,'_Month Engine'!$C$73:$DR$73) -> 0 | H38: =SUMIF('_Month Engine'!$C$5:$DR$5,H$4,'_Month Engine'!$C$73:$DR$73) -> 0 | I38: =SUMIF('_Month Engine'!$C$5:$DR$5,I$4,'_Month Engine'!$C$73:$DR$73) -> 0 | J38: =SUMIF('_Month Engine'!$C$5:$DR$5,J$4,'_Month Engine'!$C$73:$DR$73) -> 0 | ... L38: =SUMIF('_Month Engine'!$C$5:$DR$5,L$4,'_Month Engine'!$C$73:$DR$73) -> 0
B39: Less: selling costs | C39: =C34*Input!$C$15 -> 0 | D39: =D34*Input!$C$15 -> 0 | E39: =E34*Input!$C$15 -> 76751.008 | F39: =F34*Input!$C$15 -> 0 | G39: =G34*Input!$C$15 -> 0 | H39: =H34*Input!$C$15 -> 0 | I39: =I34*Input!$C$15 -> 0 | J39: =J34*Input!$C$15 -> 0 | ... L39: =L34*Input!$C$15 -> 0
B40: Contribution margin | C40: =C33+C34-SUM(C35:C39) -> 20094.657 | D40: =D33+D34-SUM(D35:D39) -> 47889.155 | E40: =E33+E34-SUM(E35:E39) -> 795253.79 | F40: =F33+F34-SUM(F35:F39) -> 0 | G40: =G33+G34-SUM(G35:G39) -> 0 | H40: =H33+H34-SUM(H35:H39) -> 0 | I40: =I33+I34-SUM(I35:I39) -> 0 | J40: =J33+J34-SUM(J35:J39) -> 0 | ... L40: =L33+L34-SUM(L35:L39) -> 0
B41: CM % of revenue | C41: =IF(C33+C34=0,0,C40/(C33+C34)) -> 0.7875 | D41: =IF(D33+D34=0,0,D40/(D33+D34)) -> 0.7875 | E41: =IF(E33+E34=0,0,E40/(E33+E34)) -> 0.3886026 | F41: =IF(F33+F34=0,0,F40/(F33+F34)) -> 0 | G41: =IF(G33+G34=0,0,G40/(G33+G34)) -> 0 | H41: =IF(H33+H34=0,0,H40/(H33+H34)) -> 0 | I41: =IF(I33+I34=0,0,I40/(I33+I34)) -> 0 | J41: =IF(J33+J34=0,0,J40/(J33+J34)) -> 0 | ... L41: =IF(L33+L34=0,0,L40/(L33+L34)) -> 0
B42: Less: direct fixed costs | C42: =SUM('Property Detail'!C9:C13)+'Property Detail'!C17 -> 21836.94 | D42: =SUM('Property Detail'!D9:D13)+'Property Detail'!D17 -> 27965.939 | E42: =SUM('Property Detail'!E9:E13)+'Property Detail'!E17 -> 11652.474 | F42: =SUM('Property Detail'!F9:F13)+'Property Detail'!F17 -> 0 | G42: =SUM('Property Detail'!G9:G13)+'Property Detail'!G17 -> 0 | H42: =SUM('Property Detail'!H9:H13)+'Property Detail'!H17 -> 0 | I42: =SUM('Property Detail'!I9:I13)+'Property Detail'!I17 -> 0 | J42: =SUM('Property Detail'!J9:J13)+'Property Detail'!J17 -> 0 | ... L42: =SUM('Property Detail'!L9:L13)+'Property Detail'!L17 -> 0
B43: Margin after direct fixed costs | C43: =C40-C42 -> -1742.2832 | D43: =D40-D42 -> 19923.216 | E43: =E40-E42 -> 783601.32 | F43: =F40-F42 -> 0 | G43: =G40-G42 -> 0 | H43: =H40-H42 -> 0 | I43: =I40-I42 -> 0 | J43: =J40-J42 -> 0 | ... L43: =L40-L42 -> 0
B44: Margin after direct fixed costs, % of revenue | C44: =IF(C33+C34=0,0,C43/(C33+C34)) -> -0.068279245 | D44: =IF(D33+D34=0,0,D43/(D33+D34)) -> 0.32762183 | E44: =IF(E33+E34=0,0,E43/(E33+E34)) -> 0.38290859 | F44: =IF(F33+F34=0,0,F43/(F33+F34)) -> 0 | G44: =IF(G33+G34=0,0,G43/(G33+G34)) -> 0 | H44: =IF(H33+H34=0,0,H43/(H33+H34)) -> 0 | I44: =IF(I33+I34=0,0,I43/(I33+I34)) -> 0 | J44: =IF(J33+J34=0,0,J43/(J33+J34)) -> 0 | ... L44: =IF(L33+L34=0,0,L43/(L33+L34)) -> 0
B46: =$B$9 -> Fontanar Apto 201 (Penthouse)
B47: Rental revenue | C47: =C9 -> 29441.475 | D47: =D9 -> 60811.625 | E47: =E9 -> 31396.947 | F47: =F9 -> 0 | G47: =G9 -> 0 | H47: =H9 -> 0 | I47: =I9 -> 0 | J47: =J9 -> 0 | ... L47: =L9 -> 0
B48: Property sale (gross) | C48: =C20 -> 0 | D48: =D20 -> 0 | E48: =E20 -> 2261281.6 | F48: =F20 -> 0 | G48: =G20 -> 0 | H48: =H20 -> 0 | I48: =I20 -> 0 | J48: =J20 -> 0 | ... L48: =L20 -> 0
B49: Less: housekeeping & turnover | C49: ='Property Detail'!C30 -> 0 | D49: ='Property Detail'!D30 -> 0 | E49: ='Property Detail'!E30 -> 0 | F49: ='Property Detail'!F30 -> 0 | G49: ='Property Detail'!G30 -> 0 | H49: ='Property Detail'!H30 -> 0 | I49: ='Property Detail'!I30 -> 0 | J49: ='Property Detail'!J30 -> 0 | ... L49: ='Property Detail'!L30 -> 0
B50: Less: property management & housekeeping | C50: ='Property Detail'!C32 -> 5888.295 | D50: ='Property Detail'!D32 -> 12162.325 | E50: ='Property Detail'!E32 -> 6279.3893 | F50: ='Property Detail'!F32 -> 0 | G50: ='Property Detail'!G32 -> 0 | H50: ='Property Detail'!H32 -> 0 | I50: ='Property Detail'!I32 -> 0 | J50: ='Property Detail'!J32 -> 0 | ... L50: ='Property Detail'!L32 -> 0
B51: Less: STR revenue taxes (ICA, FONTUR) | C51: ='Property Detail'!C31 -> 368.01844 | D51: ='Property Detail'!D31 -> 760.14531 | E51: ='Property Detail'!E31 -> 392.46183 | F51: ='Property Detail'!F31 -> 0 | G51: ='Property Detail'!G31 -> 0 | H51: ='Property Detail'!H31 -> 0 | I51: ='Property Detail'!I31 -> 0 | J51: ='Property Detail'!J31 -> 0 | ... L51: ='Property Detail'!L31 -> 0
B52: Less: cost basis released on sale | C52: =SUMIF('_Month Engine'!$C$5:$DR$5,C$4,'_Month Engine'!$C$74:$DR$74) -> 0 | D52: =SUMIF('_Month Engine'!$C$5:$DR$5,D$4,'_Month Engine'!$C$74:$DR$74) -> 0 | E52: =SUMIF('_Month Engine'!$C$5:$DR$5,E$4,'_Month Engine'!$C$74:$DR$74) -> 1290857.6 | F52: =SUMIF('_Month Engine'!$C$5:$DR$5,F$4,'_Month Engine'!$C$74:$DR$74) -> 0 | G52: =SUMIF('_Month Engine'!$C$5:$DR$5,G$4,'_Month Engine'!$C$74:$DR$74) -> 0 | H52: =SUMIF('_Month Engine'!$C$5:$DR$5,H$4,'_Month Engine'!$C$74:$DR$74) -> 0 | I52: =SUMIF('_Month Engine'!$C$5:$DR$5,I$4,'_Month Engine'!$C$74:$DR$74) -> 0 | J52: =SUMIF('_Month Engine'!$C$5:$DR$5,J$4,'_Month Engine'!$C$74:$DR$74) -> 0 | ... L52: =SUMIF('_Month Engine'!$C$5:$DR$5,L$4,'_Month Engine'!$C$74:$DR$74) -> 0
B53: Less: selling costs | C53: =C48*Input!$C$15 -> 0 | D53: =D48*Input!$C$15 -> 0 | E53: =E48*Input!$C$15 -> 85928.7 | F53: =F48*Input!$C$15 -> 0 | G53: =G48*Input!$C$15 -> 0 | H53: =H48*Input!$C$15 -> 0 | I53: =I48*Input!$C$15 -> 0 | J53: =J48*Input!$C$15 -> 0 | ... L53: =L48*Input!$C$15 -> 0
B54: Contribution margin | C54: =C47+C48-SUM(C49:C53) -> 23185.162 | D54: =D47+D48-SUM(D49:D53) -> 47889.155 | E54: =E47+E48-SUM(E49:E53) -> 909220.36 | F54: =F47+F48-SUM(F49:F53) -> 0 | G54: =G47+G48-SUM(G49:G53) -> 0 | H54: =H47+H48-SUM(H49:H53) -> 0 | I54: =I47+I48-SUM(I49:I53) -> 0 | J54: =J47+J48-SUM(J49:J53) -> 0 | ... L54: =L47+L48-SUM(L49:L53) -> 0
B55: CM % of revenue | C55: =IF(C47+C48=0,0,C54/(C47+C48)) -> 0.7875 | D55: =IF(D47+D48=0,0,D54/(D47+D48)) -> 0.7875 | E55: =IF(E47+E48=0,0,E54/(E47+E48)) -> 0.3965756 | F55: =IF(F47+F48=0,0,F54/(F47+F48)) -> 0 | G55: =IF(G47+G48=0,0,G54/(G47+G48)) -> 0 | H55: =IF(H47+H48=0,0,H54/(H47+H48)) -> 0 | I55: =IF(I47+I48=0,0,I54/(I47+I48)) -> 0 | J55: =IF(J47+J48=0,0,J54/(J47+J48)) -> 0 | ... L55: =IF(L47+L48=0,0,L54/(L47+L48)) -> 0
B56: Less: direct fixed costs | C56: =SUM('Property Detail'!C25:C29)+'Property Detail'!C33 -> 25797.229 | D56: =SUM('Property Detail'!D25:D29)+'Property Detail'!D33 -> 29992.516 | E56: =SUM('Property Detail'!E25:E29)+'Property Detail'!E33 -> 14996.258 | F56: =SUM('Property Detail'!F25:F29)+'Property Detail'!F33 -> 0 | G56: =SUM('Property Detail'!G25:G29)+'Property Detail'!G33 -> 0 | H56: =SUM('Property Detail'!H25:H29)+'Property Detail'!H33 -> 0 | I56: =SUM('Property Detail'!I25:I29)+'Property Detail'!I33 -> 0 | J56: =SUM('Property Detail'!J25:J29)+'Property Detail'!J33 -> 0 | ... L56: =SUM('Property Detail'!L25:L29)+'Property Detail'!L33 -> 0
B57: Margin after direct fixed costs | C57: =C54-C56 -> -2612.0674 | D57: =D54-D56 -> 17896.638 | E57: =E54-E56 -> 894224.1 | F57: =F54-F56 -> 0 | G57: =G54-G56 -> 0 | H57: =H54-H56 -> 0 | I57: =I54-I56 -> 0 | J57: =J54-J56 -> 0 | ... L57: =L54-L56 -> 0
B58: Margin after direct fixed costs, % of revenue | C58: =IF(C47+C48=0,0,C57/(C47+C48)) -> -0.08872067 | D58: =IF(D47+D48=0,0,D57/(D47+D48)) -> 0.29429634 | E58: =IF(E47+E48=0,0,E57/(E47+E48)) -> 0.39003467 | F58: =IF(F47+F48=0,0,F57/(F47+F48)) -> 0 | G58: =IF(G47+G48=0,0,G57/(G47+G48)) -> 0 | H58: =IF(H47+H48=0,0,H57/(H47+H48)) -> 0 | I58: =IF(I47+I48=0,0,I57/(I47+I48)) -> 0 | J58: =IF(J47+J48=0,0,J57/(J47+J48)) -> 0 | ... L58: =IF(L47+L48=0,0,L57/(L47+L48)) -> 0
B60: =$B$10 -> San Lucas Apto 101
B61: Rental revenue | C61: =C10 -> 20069.625 | D61: =D10 -> 56307.06 | E61: =E10 -> 14215.505 | F61: =F10 -> 0 | G61: =G10 -> 0 | H61: =H10 -> 0 | I61: =I10 -> 0 | J61: =J10 -> 0 | ... L61: =L10 -> 0
B62: Property sale (gross) | C62: =C21 -> 0 | D62: =D21 -> 0 | E62: =E21 -> 1265464.3 | F62: =F21 -> 0 | G62: =G21 -> 0 | H62: =H21 -> 0 | I62: =I21 -> 0 | J62: =J21 -> 0 | ... L62: =L21 -> 0
B63: Less: housekeeping & turnover | C63: ='Property Detail'!C46 -> 0 | D63: ='Property Detail'!D46 -> 0 | E63: ='Property Detail'!E46 -> 0 | F63: ='Property Detail'!F46 -> 0 | G63: ='Property Detail'!G46 -> 0 | H63: ='Property Detail'!H46 -> 0 | I63: ='Property Detail'!I46 -> 0 | J63: ='Property Detail'!J46 -> 0 | ... L63: ='Property Detail'!L46 -> 0
B64: Less: property management & housekeeping | C64: ='Property Detail'!C48 -> 4013.925 | D64: ='Property Detail'!D48 -> 11261.412 | E64: ='Property Detail'!E48 -> 2843.1011 | F64: ='Property Detail'!F48 -> 0 | G64: ='Property Detail'!G48 -> 0 | H64: ='Property Detail'!H48 -> 0 | I64: ='Property Detail'!I48 -> 0 | J64: ='Property Detail'!J48 -> 0 | ... L64: ='Property Detail'!L48 -> 0
B65: Less: STR revenue taxes (ICA, FONTUR) | C65: ='Property Detail'!C47 -> 250.87031 | D65: ='Property Detail'!D47 -> 703.83825 | E65: ='Property Detail'!E47 -> 177.69382 | F65: ='Property Detail'!F47 -> 0 | G65: ='Property Detail'!G47 -> 0 | H65: ='Property Detail'!H47 -> 0 | I65: ='Property Detail'!I47 -> 0 | J65: ='Property Detail'!J47 -> 0 | ... L65: ='Property Detail'!L47 -> 0
B66: Less: cost basis released on sale | C66: =SUMIF('_Month Engine'!$C$5:$DR$5,C$4,'_Month Engine'!$C$75:$DR$75) -> 0 | D66: =SUMIF('_Month Engine'!$C$5:$DR$5,D$4,'_Month Engine'!$C$75:$DR$75) -> 0 | E66: =SUMIF('_Month Engine'!$C$5:$DR$5,E$4,'_Month Engine'!$C$75:$DR$75) -> 747370.55 | F66: =SUMIF('_Month Engine'!$C$5:$DR$5,F$4,'_Month Engine'!$C$75:$DR$75) -> 0 | G66: =SUMIF('_Month Engine'!$C$5:$DR$5,G$4,'_Month Engine'!$C$75:$DR$75) -> 0 | H66: =SUMIF('_Month Engine'!$C$5:$DR$5,H$4,'_Month Engine'!$C$75:$DR$75) -> 0 | I66: =SUMIF('_Month Engine'!$C$5:$DR$5,I$4,'_Month Engine'!$C$75:$DR$75) -> 0 | J66: =SUMIF('_Month Engine'!$C$5:$DR$5,J$4,'_Month Engine'!$C$75:$DR$75) -> 0 | ... L66: =SUMIF('_Month Engine'!$C$5:$DR$5,L$4,'_Month Engine'!$C$75:$DR$75) -> 0
B67: Less: selling costs | C67: =C62*Input!$C$15 -> 0 | D67: =D62*Input!$C$15 -> 0 | E67: =E62*Input!$C$15 -> 48087.643 | F67: =F62*Input!$C$15 -> 0 | G67: =G62*Input!$C$15 -> 0 | H67: =H62*Input!$C$15 -> 0 | I67: =I62*Input!$C$15 -> 0 | J67: =J62*Input!$C$15 -> 0 | ... L67: =L62*Input!$C$15 -> 0
B68: Contribution margin | C68: =C61+C62-SUM(C63:C67) -> 15804.83 | D68: =D61+D62-SUM(D63:D67) -> 44341.81 | E68: =E61+E62-SUM(E63:E67) -> 481200.81 | F68: =F61+F62-SUM(F63:F67) -> 0 | G68: =G61+G62-SUM(G63:G67) -> 0 | H68: =H61+H62-SUM(H63:H67) -> 0 | I68: =I61+I62-SUM(I63:I67) -> 0 | J68: =J61+J62-SUM(J63:J67) -> 0 | ... L68: =L61+L62-SUM(L63:L67) -> 0
B69: CM % of revenue | C69: =IF(C61+C62=0,0,C68/(C61+C62)) -> 0.7875 | D69: =IF(D61+D62=0,0,D68/(D61+D62)) -> 0.7875 | E69: =IF(E61+E62=0,0,E68/(E61+E62)) -> 0.3760322 | F69: =IF(F61+F62=0,0,F68/(F61+F62)) -> 0 | G69: =IF(G61+G62=0,0,G68/(G61+G62)) -> 0 | H69: =IF(H61+H62=0,0,H68/(H61+H62)) -> 0 | I69: =IF(I61+I62=0,0,I68/(I61+I62)) -> 0 | J69: =IF(J61+J62=0,0,J68/(J61+J62)) -> 0 | ... L69: =IF(L61+L62=0,0,L68/(L61+L62)) -> 0
B70: Less: direct fixed costs | C70: =SUM('Property Detail'!C41:C45)+'Property Detail'!C49 -> 13472.054 | D70: =SUM('Property Detail'!D41:D45)+'Property Detail'!D49 -> 19081.21 | E70: =SUM('Property Detail'!E41:E45)+'Property Detail'!E49 -> 4770.3024 | F70: =SUM('Property Detail'!F41:F45)+'Property Detail'!F49 -> 0 | G70: =SUM('Property Detail'!G41:G45)+'Property Detail'!G49 -> 0 | H70: =SUM('Property Detail'!H41:H45)+'Property Detail'!H49 -> 0 | I70: =SUM('Property Detail'!I41:I45)+'Property Detail'!I49 -> 0 | J70: =SUM('Property Detail'!J41:J45)+'Property Detail'!J49 -> 0 | ... L70: =SUM('Property Detail'!L41:L45)+'Property Detail'!L49 -> 0
B71: Margin after direct fixed costs | C71: =C68-C70 -> 2332.776 | D71: =D68-D70 -> 25260.6 | E71: =E68-E70 -> 476430.51 | F71: =F68-F70 -> 0 | G71: =G68-G70 -> 0 | H71: =H68-H70 -> 0 | I71: =I68-I70 -> 0 | J71: =J68-J70 -> 0 | ... L71: =L68-L70 -> 0
B72: Margin after direct fixed costs, % of revenue | C72: =IF(C61+C62=0,0,C71/(C61+C62)) -> 0.11623416 | D72: =IF(D61+D62=0,0,D71/(D61+D62)) -> 0.44862225 | E72: =IF(E61+E62=0,0,E71/(E61+E62)) -> 0.37230447 | F72: =IF(F61+F62=0,0,F71/(F61+F62)) -> 0 | G72: =IF(G61+G62=0,0,G71/(G61+G62)) -> 0 | H72: =IF(H61+H62=0,0,H71/(H61+H62)) -> 0 | I72: =IF(I61+I62=0,0,I71/(I61+I62)) -> 0 | J72: =IF(J61+J62=0,0,J71/(J61+J62)) -> 0 | ... L72: =IF(L61+L62=0,0,L71/(L61+L62)) -> 0
B74: =$B$11 -> Casa Montana Lote 2 (Samuel Gaviria House)
B75: Rental revenue | C75: =C11 -> 0 | D75: =D11 -> 69124.14 | E75: =E11 -> 75836.01 | F75: =F11 -> 40478.989 | G75: =G11 -> 0 | H75: =H11 -> 0 | I75: =I11 -> 0 | J75: =J11 -> 0 | ... L75: =L11 -> 0
B76: Property sale (gross) | C76: =C22 -> 0 | D76: =D22 -> 0 | E76: =E22 -> 0 | F76: =F22 -> 2995795.2 | G76: =G22 -> 0 | H76: =H22 -> 0 | I76: =I22 -> 0 | J76: =J22 -> 0 | ... L76: =L22 -> 0
B77: Less: housekeeping & turnover | C77: ='Property Detail'!C62 -> 0 | D77: ='Property Detail'!D62 -> 0 | E77: ='Property Detail'!E62 -> 0 | F77: ='Property Detail'!F62 -> 0 | G77: ='Property Detail'!G62 -> 0 | H77: ='Property Detail'!H62 -> 0 | I77: ='Property Detail'!I62 -> 0 | J77: ='Property Detail'!J62 -> 0 | ... L77: ='Property Detail'!L62 -> 0
B78: Less: property management & housekeeping | C78: ='Property Detail'!C64 -> 0 | D78: ='Property Detail'!D64 -> 13824.828 | E78: ='Property Detail'!E64 -> 15167.202 | F78: ='Property Detail'!F64 -> 8095.7977 | G78: ='Property Detail'!G64 -> 0 | H78: ='Property Detail'!H64 -> 0 | I78: ='Property Detail'!I64 -> 0 | J78: ='Property Detail'!J64 -> 0 | ... L78: ='Property Detail'!L64 -> 0
B79: Less: STR revenue taxes (ICA, FONTUR) | C79: ='Property Detail'!C63 -> 0 | D79: ='Property Detail'!D63 -> 864.05175 | E79: ='Property Detail'!E63 -> 947.95012 | F79: ='Property Detail'!F63 -> 505.98736 | G79: ='Property Detail'!G63 -> 0 | H79: ='Property Detail'!H63 -> 0 | I79: ='Property Detail'!I63 -> 0 | J79: ='Property Detail'!J63 -> 0 | ... L79: ='Property Detail'!L63 -> 0
B80: Less: cost basis released on sale | C80: =SUMIF('_Month Engine'!$C$5:$DR$5,C$4,'_Month Engine'!$C$76:$DR$76) -> 0 | D80: =SUMIF('_Month Engine'!$C$5:$DR$5,D$4,'_Month Engine'!$C$76:$DR$76) -> 0 | E80: =SUMIF('_Month Engine'!$C$5:$DR$5,E$4,'_Month Engine'!$C$76:$DR$76) -> 0 | F80: =SUMIF('_Month Engine'!$C$5:$DR$5,F$4,'_Month Engine'!$C$76:$DR$76) -> 1714482.2 | G80: =SUMIF('_Month Engine'!$C$5:$DR$5,G$4,'_Month Engine'!$C$76:$DR$76) -> 0 | H80: =SUMIF('_Month Engine'!$C$5:$DR$5,H$4,'_Month Engine'!$C$76:$DR$76) -> 0 | I80: =SUMIF('_Month Engine'!$C$5:$DR$5,I$4,'_Month Engine'!$C$76:$DR$76) -> 0 | J80: =SUMIF('_Month Engine'!$C$5:$DR$5,J$4,'_Month Engine'!$C$76:$DR$76) -> 0 | ... L80: =SUMIF('_Month Engine'!$C$5:$DR$5,L$4,'_Month Engine'!$C$76:$DR$76) -> 0
B81: Less: selling costs | C81: =C76*Input!$C$15 -> 0 | D81: =D76*Input!$C$15 -> 0 | E81: =E76*Input!$C$15 -> 0 | F81: =F76*Input!$C$15 -> 113840.22 | G81: =G76*Input!$C$15 -> 0 | H81: =H76*Input!$C$15 -> 0 | I81: =I76*Input!$C$15 -> 0 | J81: =J76*Input!$C$15 -> 0 | ... L81: =L76*Input!$C$15 -> 0
B82: Contribution margin | C82: =C75+C76-SUM(C77:C81) -> 0 | D82: =D75+D76-SUM(D77:D81) -> 54435.26 | E82: =E75+E76-SUM(E77:E81) -> 59720.858 | F82: =F75+F76-SUM(F77:F81) -> 1199350 | G82: =G75+G76-SUM(G77:G81) -> 0 | H82: =H75+H76-SUM(H77:H81) -> 0 | I82: =I75+I76-SUM(I77:I81) -> 0 | J82: =J75+J76-SUM(J77:J81) -> 0 | ... L82: =L75+L76-SUM(L77:L81) -> 0
B83: CM % of revenue | C83: =IF(C75+C76=0,0,C82/(C75+C76)) -> 0 | D83: =IF(D75+D76=0,0,D82/(D75+D76)) -> 0.7875 | E83: =IF(E75+E76=0,0,E82/(E75+E76)) -> 0.7875 | F83: =IF(F75+F76=0,0,F82/(F75+F76)) -> 0.39500714 | G83: =IF(G75+G76=0,0,G82/(G75+G76)) -> 0 | H83: =IF(H75+H76=0,0,H82/(H75+H76)) -> 0 | I83: =IF(I75+I76=0,0,I82/(I75+I76)) -> 0 | J83: =IF(J75+J76=0,0,J82/(J75+J76)) -> 0 | ... L83: =IF(L75+L76=0,0,L82/(L75+L76)) -> 0
B84: Less: direct fixed costs | C84: =SUM('Property Detail'!C57:C61)+'Property Detail'!C65 -> 9071.1974 | D84: =SUM('Property Detail'!D57:D61)+'Property Detail'!D65 -> 31986.33 | E84: =SUM('Property Detail'!E57:E61)+'Property Detail'!E65 -> 32915.008 | F84: =SUM('Property Detail'!F57:F61)+'Property Detail'!F65 -> 16457.504 | G84: =SUM('Property Detail'!G57:G61)+'Property Detail'!G65 -> 0 | H84: =SUM('Property Detail'!H57:H61)+'Property Detail'!H65 -> 0 | I84: =SUM('Property Detail'!I57:I61)+'Property Detail'!I65 -> 0 | J84: =SUM('Property Detail'!J57:J61)+'Property Detail'!J65 -> 0 | ... L84: =SUM('Property Detail'!L57:L61)+'Property Detail'!L65 -> 0
B85: Margin after direct fixed costs | C85: =C82-C84 -> -9071.1974 | D85: =D82-D84 -> 22448.93 | E85: =E82-E84 -> 26805.849 | F85: =F82-F84 -> 1182892.5 | G85: =G82-G84 -> 0 | H85: =H82-H84 -> 0 | I85: =I82-I84 -> 0 | J85: =J82-J84 -> 0 | ... L85: =L82-L84 -> 0
B86: Margin after direct fixed costs, % of revenue | C86: =IF(C75+C76=0,0,C85/(C75+C76)) -> 0 | D86: =IF(D75+D76=0,0,D85/(D75+D76)) -> 0.32476252 | E86: =IF(E75+E76=0,0,E85/(E75+E76)) -> 0.35347125 | F86: =IF(F75+F76=0,0,F85/(F75+F76)) -> 0.38958684 | G86: =IF(G75+G76=0,0,G85/(G75+G76)) -> 0 | H86: =IF(H75+H76=0,0,H85/(H75+H76)) -> 0 | I86: =IF(I75+I76=0,0,I85/(I75+I76)) -> 0 | J86: =IF(J75+J76=0,0,J85/(J75+J76)) -> 0 | ... L86: =IF(L75+L76=0,0,L85/(L75+L76)) -> 0
B88: =$B$12 -> Casa Monte Sereno
B89: Rental revenue | C89: =C12 -> 9197.55 | D89: =D12 -> 61157.389 | E89: =E12 -> 62380.537 | F89: =F12 -> 0 | G89: =G12 -> 0 | H89: =H12 -> 0 | I89: =I12 -> 0 | J89: =J12 -> 0 | ... L89: =L12 -> 0
B90: Property sale (gross) | C90: =C23 -> 0 | D90: =D23 -> 0 | E90: =E23 -> 0 | F90: =F23 -> 2834606.6 | G90: =G23 -> 0 | H90: =H23 -> 0 | I90: =I23 -> 0 | J90: =J23 -> 0 | ... L90: =L23 -> 0
B91: Less: housekeeping & turnover | C91: ='Property Detail'!C78 -> 0 | D91: ='Property Detail'!D78 -> 0 | E91: ='Property Detail'!E78 -> 0 | F91: ='Property Detail'!F78 -> 0 | G91: ='Property Detail'!G78 -> 0 | H91: ='Property Detail'!H78 -> 0 | I91: ='Property Detail'!I78 -> 0 | J91: ='Property Detail'!J78 -> 0 | ... L91: ='Property Detail'!L78 -> 0
B92: Less: property management & housekeeping | C92: ='Property Detail'!C80 -> 1839.51 | D92: ='Property Detail'!D80 -> 12231.478 | E92: ='Property Detail'!E80 -> 12476.107 | F92: ='Property Detail'!F80 -> 0 | G92: ='Property Detail'!G80 -> 0 | H92: ='Property Detail'!H80 -> 0 | I92: ='Property Detail'!I80 -> 0 | J92: ='Property Detail'!J80 -> 0 | ... L92: ='Property Detail'!L80 -> 0
B93: Less: STR revenue taxes (ICA, FONTUR) | C93: ='Property Detail'!C79 -> 114.96938 | D93: ='Property Detail'!D79 -> 764.46737 | E93: ='Property Detail'!E79 -> 779.75672 | F93: ='Property Detail'!F79 -> 0 | G93: ='Property Detail'!G79 -> 0 | H93: ='Property Detail'!H79 -> 0 | I93: ='Property Detail'!I79 -> 0 | J93: ='Property Detail'!J79 -> 0 | ... L93: ='Property Detail'!L79 -> 0
B94: Less: cost basis released on sale | C94: =SUMIF('_Month Engine'!$C$5:$DR$5,C$4,'_Month Engine'!$C$77:$DR$77) -> 0 | D94: =SUMIF('_Month Engine'!$C$5:$DR$5,D$4,'_Month Engine'!$C$77:$DR$77) -> 0 | E94: =SUMIF('_Month Engine'!$C$5:$DR$5,E$4,'_Month Engine'!$C$77:$DR$77) -> 0 | F94: =SUMIF('_Month Engine'!$C$5:$DR$5,F$4,'_Month Engine'!$C$77:$DR$77) -> 1650485.4 | G94: =SUMIF('_Month Engine'!$C$5:$DR$5,G$4,'_Month Engine'!$C$77:$DR$77) -> 0 | H94: =SUMIF('_Month Engine'!$C$5:$DR$5,H$4,'_Month Engine'!$C$77:$DR$77) -> 0 | I94: =SUMIF('_Month Engine'!$C$5:$DR$5,I$4,'_Month Engine'!$C$77:$DR$77) -> 0 | J94: =SUMIF('_Month Engine'!$C$5:$DR$5,J$4,'_Month Engine'!$C$77:$DR$77) -> 0 | ... L94: =SUMIF('_Month Engine'!$C$5:$DR$5,L$4,'_Month Engine'!$C$77:$DR$77) -> 0
B95: Less: selling costs | C95: =C90*Input!$C$15 -> 0 | D95: =D90*Input!$C$15 -> 0 | E95: =E90*Input!$C$15 -> 0 | F95: =F90*Input!$C$15 -> 107715.05 | G95: =G90*Input!$C$15 -> 0 | H95: =H90*Input!$C$15 -> 0 | I95: =I90*Input!$C$15 -> 0 | J95: =J90*Input!$C$15 -> 0 | ... L95: =L90*Input!$C$15 -> 0
B96: Contribution margin | C96: =C89+C90-SUM(C91:C95) -> 7243.0706 | D96: =D89+D90-SUM(D91:D95) -> 48161.444 | E96: =E89+E90-SUM(E91:E95) -> 49124.673 | F96: =F89+F90-SUM(F91:F95) -> 1076406.1 | G96: =G89+G90-SUM(G91:G95) -> 0 | H96: =H89+H90-SUM(H91:H95) -> 0 | I96: =I89+I90-SUM(I91:I95) -> 0 | J96: =J89+J90-SUM(J91:J95) -> 0 | ... L96: =L89+L90-SUM(L91:L95) -> 0
B97: CM % of revenue | C97: =IF(C89+C90=0,0,C96/(C89+C90)) -> 0.7875 | D97: =IF(D89+D90=0,0,D96/(D89+D90)) -> 0.7875 | E97: =IF(E89+E90=0,0,E96/(E89+E90)) -> 0.7875 | F97: =IF(F89+F90=0,0,F96/(F89+F90)) -> 0.37973739 | G97: =IF(G89+G90=0,0,G96/(G89+G90)) -> 0 | H97: =IF(H89+H90=0,0,H96/(H89+H90)) -> 0 | I97: =IF(I89+I90=0,0,I96/(I89+I90)) -> 0 | J97: =IF(J89+J90=0,0,J96/(J89+J90)) -> 0 | ... L97: =IF(L89+L90=0,0,L96/(L89+L90)) -> 0
B98: Less: direct fixed costs | C98: =SUM('Property Detail'!C73:C77)+'Property Detail'!C81 -> 17580.906 | D98: =SUM('Property Detail'!D73:D77)+'Property Detail'!D81 -> 34417.476 | E98: =SUM('Property Detail'!E73:E77)+'Property Detail'!E81 -> 34417.476 | F98: =SUM('Property Detail'!F73:F77)+'Property Detail'!F81 -> 0 | G98: =SUM('Property Detail'!G73:G77)+'Property Detail'!G81 -> 0 | H98: =SUM('Property Detail'!H73:H77)+'Property Detail'!H81 -> 0 | I98: =SUM('Property Detail'!I73:I77)+'Property Detail'!I81 -> 0 | J98: =SUM('Property Detail'!J73:J77)+'Property Detail'!J81 -> 0 | ... L98: =SUM('Property Detail'!L73:L77)+'Property Detail'!L81 -> 0
B99: Margin after direct fixed costs | C99: =C96-C98 -> -10337.836 | D99: =D96-D98 -> 13743.969 | E99: =E96-E98 -> 14707.197 | F99: =F96-F98 -> 1076406.1 | G99: =G96-G98 -> 0 | H99: =H96-H98 -> 0 | I99: =I96-I98 -> 0 | J99: =J96-J98 -> 0 | ... L99: =L96-L98 -> 0
B100: Margin after direct fixed costs, % of revenue | C100: =IF(C89+C90=0,0,C99/(C89+C90)) -> -1.1239771 | D100: =IF(D89+D90=0,0,D99/(D89+D90)) -> 0.22473112 | E100: =IF(E89+E90=0,0,E99/(E89+E90)) -> 0.2357658 | F100: =IF(F89+F90=0,0,F99/(F89+F90)) -> 0.37973739 | G100: =IF(G89+G90=0,0,G99/(G89+G90)) -> 0 | H100: =IF(H89+H90=0,0,H99/(H89+H90)) -> 0 | I100: =IF(I89+I90=0,0,I99/(I89+I90)) -> 0 | J100: =IF(J89+J90=0,0,J99/(J89+J90)) -> 0 | ... L100: =IF(L89+L90=0,0,L99/(L89+L90)) -> 0
B102: Portfolio Contribution Margin
B103: Total revenue | C103: =C29 -> 84225.675 | D103: =D29 -> 308211.84 | E103: =E29 -> 5757019.7 | F103: =F29 -> 5870880.8 | G103: =G29 -> 0 | H103: =H29 -> 0 | I103: =I29 -> 0 | J103: =J29 -> 0 | ... L103: =L29 -> 0
B104: Housekeeping & turnover | C104: ='Property Detail'!C238 -> 0 | D104: ='Property Detail'!D238 -> 0 | E104: ='Property Detail'!E238 -> 0 | F104: ='Property Detail'!F238 -> 0 | G104: ='Property Detail'!G238 -> 0 | H104: ='Property Detail'!H238 -> 0 | I104: ='Property Detail'!I238 -> 0 | J104: ='Property Detail'!J238 -> 0 | ... L104: ='Property Detail'!L238 -> 0
B105: Property management & housekeeping | C105: ='Property Detail'!C240 -> 16845.135 | D105: ='Property Detail'!D240 -> 61642.368 | E105: ='Property Detail'!E240 -> 42102.097 | F105: ='Property Detail'!F240 -> 8095.7977 | G105: ='Property Detail'!G240 -> 0 | H105: ='Property Detail'!H240 -> 0 | I105: ='Property Detail'!I240 -> 0 | J105: ='Property Detail'!J240 -> 0 | ... L105: ='Property Detail'!L240 -> 0
B106: STR revenue taxes (ICA, FONTUR) | C106: ='Property Detail'!C239 -> 1052.8209 | D106: ='Property Detail'!D239 -> 3852.648 | E106: ='Property Detail'!E239 -> 2631.381 | F106: ='Property Detail'!F239 -> 505.98736 | G106: ='Property Detail'!G239 -> 0 | H106: ='Property Detail'!H239 -> 0 | I106: ='Property Detail'!I239 -> 0 | J106: ='Property Detail'!J239 -> 0 | ... L106: ='Property Detail'!L239 -> 0
B107: Cost basis of properties sold | C107: =SUMIF('_Month Engine'!$C$5:$DR$5,C$4,'_Month Engine'!$C$83:$DR$83) -> 0 | D107: =SUMIF('_Month Engine'!$C$5:$DR$5,D$4,'_Month Engine'!$C$83:$DR$83) -> 0 | E107: =SUMIF('_Month Engine'!$C$5:$DR$5,E$4,'_Month Engine'!$C$83:$DR$83) -> 3206998.4 | F107: =SUMIF('_Month Engine'!$C$5:$DR$5,F$4,'_Month Engine'!$C$83:$DR$83) -> 3364967.6 | G107: =SUMIF('_Month Engine'!$C$5:$DR$5,G$4,'_Month Engine'!$C$83:$DR$83) -> 0 | H107: =SUMIF('_Month Engine'!$C$5:$DR$5,H$4,'_Month Engine'!$C$83:$DR$83) -> 0 | I107: =SUMIF('_Month Engine'!$C$5:$DR$5,I$4,'_Month Engine'!$C$83:$DR$83) -> 0 | J107: =SUMIF('_Month Engine'!$C$5:$DR$5,J$4,'_Month Engine'!$C$83:$DR$83) -> 0 | ... L107: =SUMIF('_Month Engine'!$C$5:$DR$5,L$4,'_Month Engine'!$C$83:$DR$83) -> 0
...

Sheet Statement of Cash Flows
B1: Dulcinea — Statement of Cash Flows (USD)
B2: Indirect method. See Notes to Financials.
B4: Model year | C4: =COLUMN()-2 -> 1 | D4: =COLUMN()-2 -> 2 | E4: =COLUMN()-2 -> 3 | F4: =COLUMN()-2 -> 4 | G4: =COLUMN()-2 -> 5 | H4: =COLUMN()-2 -> 6 | I4: =COLUMN()-2 -> 7 | J4: =COLUMN()-2 -> 8 | ... L4: =COLUMN()-2 -> 10
B5: Period | C5: =TEXT(EDATE(Input!$C$7,(C4-1)*12),"mmm-yy")&" – "&TEXT(EDATE(Input!$C$7,C4*12-1),"mmm-yy") -> Oct-26 – Sep-27 | D5: =TEXT(EDATE(Input!$C$7,(D4-1)*12),"mmm-yy")&" – "&TEXT(EDATE(Input!$C$7,D4*12-1),"mmm-yy") -> Oct-27 – Sep-28 | E5: =TEXT(EDATE(Input!$C$7,(E4-1)*12),"mmm-yy")&" – "&TEXT(EDATE(Input!$C$7,E4*12-1),"mmm-yy") -> Oct-28 – Sep-29 | F5: =TEXT(EDATE(Input!$C$7,(F4-1)*12),"mmm-yy")&" – "&TEXT(EDATE(Input!$C$7,F4*12-1),"mmm-yy") -> Oct-29 – Sep-30 | G5: =TEXT(EDATE(Input!$C$7,(G4-1)*12),"mmm-yy")&" – "&TEXT(EDATE(Input!$C$7,G4*12-1),"mmm-yy") -> Oct-30 – Sep-31 | H5: =TEXT(EDATE(Input!$C$7,(H4-1)*12),"mmm-yy")&" – "&TEXT(EDATE(Input!$C$7,H4*12-1),"mmm-yy") -> Oct-31 – Sep-32 | I5: =TEXT(EDATE(Input!$C$7,(I4-1)*12),"mmm-yy")&" – "&TEXT(EDATE(Input!$C$7,I4*12-1),"mmm-yy") -> Oct-32 – Sep-33 | J5: =TEXT(EDATE(Input!$C$7,(J4-1)*12),"mmm-yy")&" – "&TEXT(EDATE(Input!$C$7,J4*12-1),"mmm-yy") -> Oct-33 – Sep-34 | ... L5: =TEXT(EDATE(Input!$C$7,(L4-1)*12),"mmm-yy")&" – "&TEXT(EDATE(Input!$C$7,L4*12-1),"mmm-yy") -> Oct-35 – Sep-36
B6: Cash Flow from Operating Activities
B7: Net income | C7: ='Income Statement'!C155 -> -126083.61 | D7: ='Income Statement'!D155 -> 1968.2859 | E7: ='Income Statement'!E155 -> 1837337.1 | F7: ='Income Statement'!F155 -> 1945121.1 | G7: ='Income Statement'!G155 -> 0 | H7: ='Income Statement'!H155 -> 0 | I7: ='Income Statement'!I155 -> 0 | J7: ='Income Statement'!J155 -> 0 | ... L7: ='Income Statement'!L155 -> 0
A8: 1 | B8: {=IF(Properties!$D$6=0,"",INDEX(Properties!$E:$E,$A8+5))} -> Aires de Campestre Apto 801 (Penthouse) | C8: =SUMIF('_Month Engine'!$C$5:$DR$5,C$4,INDEX('_Month Engine'!$C:$DR,MATCH("Cost Basis Released on Sale",'_Month Engine'!$A:$A,0)+MATCH($A8,'_Month Engine'!$B$73:$B$82,0),0)) -> 0 | D8: =SUMIF('_Month Engine'!$C$5:$DR$5,D$4,INDEX('_Month Engine'!$C:$DR,MATCH("Cost Basis Released on Sale",'_Month Engine'!$A:$A,0)+MATCH($A8,'_Month Engine'!$B$73:$B$82,0),0)) -> 0 | E8: =SUMIF('_Month Engine'!$C$5:$DR$5,E$4,INDEX('_Month Engine'!$C:$DR,MATCH("Cost Basis Released on Sale",'_Month Engine'!$A:$A,0)+MATCH($A8,'_Month Engine'!$B$73:$B$82,0),0)) -> 1168770.2 | F8: =SUMIF('_Month Engine'!$C$5:$DR$5,F$4,INDEX('_Month Engine'!$C:$DR,MATCH("Cost Basis Released on Sale",'_Month Engine'!$A:$A,0)+MATCH($A8,'_Month Engine'!$B$73:$B$82,0),0)) -> 0 | G8: =SUMIF('_Month Engine'!$C$5:$DR$5,G$4,INDEX('_Month Engine'!$C:$DR,MATCH("Cost Basis Released on Sale",'_Month Engine'!$A:$A,0)+MATCH($A8,'_Month Engine'!$B$73:$B$82,0),0)) -> 0 | H8: =SUMIF('_Month Engine'!$C$5:$DR$5,H$4,INDEX('_Month Engine'!$C:$DR,MATCH("Cost Basis Released on Sale",'_Month Engine'!$A:$A,0)+MATCH($A8,'_Month Engine'!$B$73:$B$82,0),0)) -> 0 | I8: =SUMIF('_Month Engine'!$C$5:$DR$5,I$4,INDEX('_Month Engine'!$C:$DR,MATCH("Cost Basis Released on Sale",'_Month Engine'!$A:$A,0)+MATCH($A8,'_Month Engine'!$B$73:$B$82,0),0)) -> 0 | J8: =SUMIF('_Month Engine'!$C$5:$DR$5,J$4,INDEX('_Month Engine'!$C:$DR,MATCH("Cost Basis Released on Sale",'_Month Engine'!$A:$A,0)+MATCH($A8,'_Month Engine'!$B$73:$B$82,0),0)) -> 0 | ... L8: =SUMIF('_Month Engine'!$C$5:$DR$5,L$4,INDEX('_Month Engine'!$C:$DR,MATCH("Cost Basis Released on Sale",'_Month Engine'!$A:$A,0)+MATCH($A8,'_Month Engine'!$B$73:$B$82,0),0)) -> 0
A9: 2 | B9: {=IF(Properties!$D$7=0,"",INDEX(Properties!$E:$E,$A9+5))} -> Fontanar Apto 201 (Penthouse) | C9: =SUMIF('_Month Engine'!$C$5:$DR$5,C$4,INDEX('_Month Engine'!$C:$DR,MATCH("Cost Basis Released on Sale",'_Month Engine'!$A:$A,0)+MATCH($A9,'_Month Engine'!$B$73:$B$82,0),0)) -> 0 | D9: =SUMIF('_Month Engine'!$C$5:$DR$5,D$4,INDEX('_Month Engine'!$C:$DR,MATCH("Cost Basis Released on Sale",'_Month Engine'!$A:$A,0)+MATCH($A9,'_Month Engine'!$B$73:$B$82,0),0)) -> 0 | E9: =SUMIF('_Month Engine'!$C$5:$DR$5,E$4,INDEX('_Month Engine'!$C:$DR,MATCH("Cost Basis Released on Sale",'_Month Engine'!$A:$A,0)+MATCH($A9,'_Month Engine'!$B$73:$B$82,0),0)) -> 1290857.6 | F9: =SUMIF('_Month Engine'!$C$5:$DR$5,F$4,INDEX('_Month Engine'!$C:$DR,MATCH("Cost Basis Released on Sale",'_Month Engine'!$A:$A,0)+MATCH($A9,'_Month Engine'!$B$73:$B$82,0),0)) -> 0 | G9: =SUMIF('_Month Engine'!$C$5:$DR$5,G$4,INDEX('_Month Engine'!$C:$DR,MATCH("Cost Basis Released on Sale",'_Month Engine'!$A:$A,0)+MATCH($A9,'_Month Engine'!$B$73:$B$82,0),0)) -> 0 | H9: =SUMIF('_Month Engine'!$C$5:$DR$5,H$4,INDEX('_Month Engine'!$C:$DR,MATCH("Cost Basis Released on Sale",'_Month Engine'!$A:$A,0)+MATCH($A9,'_Month Engine'!$B$73:$B$82,0),0)) -> 0 | I9: =SUMIF('_Month Engine'!$C$5:$DR$5,I$4,INDEX('_Month Engine'!$C:$DR,MATCH("Cost Basis Released on Sale",'_Month Engine'!$A:$A,0)+MATCH($A9,'_Month Engine'!$B$73:$B$82,0),0)) -> 0 | J9: =SUMIF('_Month Engine'!$C$5:$DR$5,J$4,INDEX('_Month Engine'!$C:$DR,MATCH("Cost Basis Released on Sale",'_Month Engine'!$A:$A,0)+MATCH($A9,'_Month Engine'!$B$73:$B$82,0),0)) -> 0 | ... L9: =SUMIF('_Month Engine'!$C$5:$DR$5,L$4,INDEX('_Month Engine'!$C:$DR,MATCH("Cost Basis Released on Sale",'_Month Engine'!$A:$A,0)+MATCH($A9,'_Month Engine'!$B$73:$B$82,0),0)) -> 0
A10: 3 | B10: {=IF(Properties!$D$8=0,"",INDEX(Properties!$E:$E,$A10+5))} -> San Lucas Apto 101 | C10: =SUMIF('_Month Engine'!$C$5:$DR$5,C$4,INDEX('_Month Engine'!$C:$DR,MATCH("Cost Basis Released on Sale",'_Month Engine'!$A:$A,0)+MATCH($A10,'_Month Engine'!$B$73:$B$82,0),0)) -> 0 | D10: =SUMIF('_Month Engine'!$C$5:$DR$5,D$4,INDEX('_Month Engine'!$C:$DR,MATCH("Cost Basis Released on Sale",'_Month Engine'!$A:$A,0)+MATCH($A10,'_Month Engine'!$B$73:$B$82,0),0)) -> 0 | E10: =SUMIF('_Month Engine'!$C$5:$DR$5,E$4,INDEX('_Month Engine'!$C:$DR,MATCH("Cost Basis Released on Sale",'_Month Engine'!$A:$A,0)+MATCH($A10,'_Month Engine'!$B$73:$B$82,0),0)) -> 747370.55 | F10: =SUMIF('_Month Engine'!$C$5:$DR$5,F$4,INDEX('_Month Engine'!$C:$DR,MATCH("Cost Basis Released on Sale",'_Month Engine'!$A:$A,0)+MATCH($A10,'_Month Engine'!$B$73:$B$82,0),0)) -> 0 | G10: =SUMIF('_Month Engine'!$C$5:$DR$5,G$4,INDEX('_Month Engine'!$C:$DR,MATCH("Cost Basis Released on Sale",'_Month Engine'!$A:$A,0)+MATCH($A10,'_Month Engine'!$B$73:$B$82,0),0)) -> 0 | H10: =SUMIF('_Month Engine'!$C$5:$DR$5,H$4,INDEX('_Month Engine'!$C:$DR,MATCH("Cost Basis Released on Sale",'_Month Engine'!$A:$A,0)+MATCH($A10,'_Month Engine'!$B$73:$B$82,0),0)) -> 0 | I10: =SUMIF('_Month Engine'!$C$5:$DR$5,I$4,INDEX('_Month Engine'!$C:$DR,MATCH("Cost Basis Released on Sale",'_Month Engine'!$A:$A,0)+MATCH($A10,'_Month Engine'!$B$73:$B$82,0),0)) -> 0 | J10: =SUMIF('_Month Engine'!$C$5:$DR$5,J$4,INDEX('_Month Engine'!$C:$DR,MATCH("Cost Basis Released on Sale",'_Month Engine'!$A:$A,0)+MATCH($A10,'_Month Engine'!$B$73:$B$82,0),0)) -> 0 | ... L10: =SUMIF('_Month Engine'!$C$5:$DR$5,L$4,INDEX('_Month Engine'!$C:$DR,MATCH("Cost Basis Released on Sale",'_Month Engine'!$A:$A,0)+MATCH($A10,'_Month Engine'!$B$73:$B$82,0),0)) -> 0
A11: 4 | B11: {=IF(Properties!$D$9=0,"",INDEX(Properties!$E:$E,$A11+5))} -> Casa Montana Lote 2 (Samuel Gaviria House) | C11: =SUMIF('_Month Engine'!$C$5:$DR$5,C$4,INDEX('_Month Engine'!$C:$DR,MATCH("Cost Basis Released on Sale",'_Month Engine'!$A:$A,0)+MATCH($A11,'_Month Engine'!$B$73:$B$82,0),0)) -> 0 | D11: =SUMIF('_Month Engine'!$C$5:$DR$5,D$4,INDEX('_Month Engine'!$C:$DR,MATCH("Cost Basis Released on Sale",'_Month Engine'!$A:$A,0)+MATCH($A11,'_Month Engine'!$B$73:$B$82,0),0)) -> 0 | E11: =SUMIF('_Month Engine'!$C$5:$DR$5,E$4,INDEX('_Month Engine'!$C:$DR,MATCH("Cost Basis Released on Sale",'_Month Engine'!$A:$A,0)+MATCH($A11,'_Month Engine'!$B$73:$B$82,0),0)) -> 0 | F11: =SUMIF('_Month Engine'!$C$5:$DR$5,F$4,INDEX('_Month Engine'!$C:$DR,MATCH("Cost Basis Released on Sale",'_Month Engine'!$A:$A,0)+MATCH($A11,'_Month Engine'!$B$73:$B$82,0),0)) -> 1714482.2 | G11: =SUMIF('_Month Engine'!$C$5:$DR$5,G$4,INDEX('_Month Engine'!$C:$DR,MATCH("Cost Basis Released on Sale",'_Month Engine'!$A:$A,0)+MATCH($A11,'_Month Engine'!$B$73:$B$82,0),0)) -> 0 | H11: =SUMIF('_Month Engine'!$C$5:$DR$5,H$4,INDEX('_Month Engine'!$C:$DR,MATCH("Cost Basis Released on Sale",'_Month Engine'!$A:$A,0)+MATCH($A11,'_Month Engine'!$B$73:$B$82,0),0)) -> 0 | I11: =SUMIF('_Month Engine'!$C$5:$DR$5,I$4,INDEX('_Month Engine'!$C:$DR,MATCH("Cost Basis Released on Sale",'_Month Engine'!$A:$A,0)+MATCH($A11,'_Month Engine'!$B$73:$B$82,0),0)) -> 0 | J11: =SUMIF('_Month Engine'!$C$5:$DR$5,J$4,INDEX('_Month Engine'!$C:$DR,MATCH("Cost Basis Released on Sale",'_Month Engine'!$A:$A,0)+MATCH($A11,'_Month Engine'!$B$73:$B$82,0),0)) -> 0 | ... L11: =SUMIF('_Month Engine'!$C$5:$DR$5,L$4,INDEX('_Month Engine'!$C:$DR,MATCH("Cost Basis Released on Sale",'_Month Engine'!$A:$A,0)+MATCH($A11,'_Month Engine'!$B$73:$B$82,0),0)) -> 0
A12: 5 | B12: {=IF(Properties!$D$10=0,"",INDEX(Properties!$E:$E,$A12+5))} -> Casa Monte Sereno | C12: =SUMIF('_Month Engine'!$C$5:$DR$5,C$4,INDEX('_Month Engine'!$C:$DR,MATCH("Cost Basis Released on Sale",'_Month Engine'!$A:$A,0)+MATCH($A12,'_Month Engine'!$B$73:$B$82,0),0)) -> 0 | D12: =SUMIF('_Month Engine'!$C$5:$DR$5,D$4,INDEX('_Month Engine'!$C:$DR,MATCH("Cost Basis Released on Sale",'_Month Engine'!$A:$A,0)+MATCH($A12,'_Month Engine'!$B$73:$B$82,0),0)) -> 0 | E12: =SUMIF('_Month Engine'!$C$5:$DR$5,E$4,INDEX('_Month Engine'!$C:$DR,MATCH("Cost Basis Released on Sale",'_Month Engine'!$A:$A,0)+MATCH($A12,'_Month Engine'!$B$73:$B$82,0),0)) -> 0 | F12: =SUMIF('_Month Engine'!$C$5:$DR$5,F$4,INDEX('_Month Engine'!$C:$DR,MATCH("Cost Basis Released on Sale",'_Month Engine'!$A:$A,0)+MATCH($A12,'_Month Engine'!$B$73:$B$82,0),0)) -> 1650485.4 | G12: =SUMIF('_Month Engine'!$C$5:$DR$5,G$4,INDEX('_Month Engine'!$C:$DR,MATCH("Cost Basis Released on Sale",'_Month Engine'!$A:$A,0)+MATCH($A12,'_Month Engine'!$B$73:$B$82,0),0)) -> 0 | H12: =SUMIF('_Month Engine'!$C$5:$DR$5,H$4,INDEX('_Month Engine'!$C:$DR,MATCH("Cost Basis Released on Sale",'_Month Engine'!$A:$A,0)+MATCH($A12,'_Month Engine'!$B$73:$B$82,0),0)) -> 0 | I12: =SUMIF('_Month Engine'!$C$5:$DR$5,I$4,INDEX('_Month Engine'!$C:$DR,MATCH("Cost Basis Released on Sale",'_Month Engine'!$A:$A,0)+MATCH($A12,'_Month Engine'!$B$73:$B$82,0),0)) -> 0 | J12: =SUMIF('_Month Engine'!$C$5:$DR$5,J$4,INDEX('_Month Engine'!$C:$DR,MATCH("Cost Basis Released on Sale",'_Month Engine'!$A:$A,0)+MATCH($A12,'_Month Engine'!$B$73:$B$82,0),0)) -> 0 | ... L12: =SUMIF('_Month Engine'!$C$5:$DR$5,L$4,INDEX('_Month Engine'!$C:$DR,MATCH("Cost Basis Released on Sale",'_Month Engine'!$A:$A,0)+MATCH($A12,'_Month Engine'!$B$73:$B$82,0),0)) -> 0
A13: 6 | B13: {=IF(Properties!$D$11=0,"",INDEX(Properties!$E:$E,$A13+5))} | C13: =SUMIF('_Month Engine'!$C$5:$DR$5,C$4,INDEX('_Month Engine'!$C:$DR,MATCH("Cost Basis Released on Sale",'_Month Engine'!$A:$A,0)+MATCH($A13,'_Month Engine'!$B$73:$B$82,0),0)) -> 0 | D13: =SUMIF('_Month Engine'!$C$5:$DR$5,D$4,INDEX('_Month Engine'!$C:$DR,MATCH("Cost Basis Released on Sale",'_Month Engine'!$A:$A,0)+MATCH($A13,'_Month Engine'!$B$73:$B$82,0),0)) -> 0 | E13: =SUMIF('_Month Engine'!$C$5:$DR$5,E$4,INDEX('_Month Engine'!$C:$DR,MATCH("Cost Basis Released on Sale",'_Month Engine'!$A:$A,0)+MATCH($A13,'_Month Engine'!$B$73:$B$82,0),0)) -> 0 | F13: =SUMIF('_Month Engine'!$C$5:$DR$5,F$4,INDEX('_Month Engine'!$C:$DR,MATCH("Cost Basis Released on Sale",'_Month Engine'!$A:$A,0)+MATCH($A13,'_Month Engine'!$B$73:$B$82,0),0)) -> 0 | G13: =SUMIF('_Month Engine'!$C$5:$DR$5,G$4,INDEX('_Month Engine'!$C:$DR,MATCH("Cost Basis Released on Sale",'_Month Engine'!$A:$A,0)+MATCH($A13,'_Month Engine'!$B$73:$B$82,0),0)) -> 0 | H13: =SUMIF('_Month Engine'!$C$5:$DR$5,H$4,INDEX('_Month Engine'!$C:$DR,MATCH("Cost Basis Released on Sale",'_Month Engine'!$A:$A,0)+MATCH($A13,'_Month Engine'!$B$73:$B$82,0),0)) -> 0 | I13: =SUMIF('_Month Engine'!$C$5:$DR$5,I$4,INDEX('_Month Engine'!$C:$DR,MATCH("Cost Basis Released on Sale",'_Month Engine'!$A:$A,0)+MATCH($A13,'_Month Engine'!$B$73:$B$82,0),0)) -> 0 | J13: =SUMIF('_Month Engine'!$C$5:$DR$5,J$4,INDEX('_Month Engine'!$C:$DR,MATCH("Cost Basis Released on Sale",'_Month Engine'!$A:$A,0)+MATCH($A13,'_Month Engine'!$B$73:$B$82,0),0)) -> 0 | ... L13: =SUMIF('_Month Engine'!$C$5:$DR$5,L$4,INDEX('_Month Engine'!$C:$DR,MATCH("Cost Basis Released on Sale",'_Month Engine'!$A:$A,0)+MATCH($A13,'_Month Engine'!$B$73:$B$82,0),0)) -> 0
A14: 7 | B14: {=IF(Properties!$D$12=0,"",INDEX(Properties!$E:$E,$A14+5))} | C14: =SUMIF('_Month Engine'!$C$5:$DR$5,C$4,INDEX('_Month Engine'!$C:$DR,MATCH("Cost Basis Released on Sale",'_Month Engine'!$A:$A,0)+MATCH($A14,'_Month Engine'!$B$73:$B$82,0),0)) -> 0 | D14: =SUMIF('_Month Engine'!$C$5:$DR$5,D$4,INDEX('_Month Engine'!$C:$DR,MATCH("Cost Basis Released on Sale",'_Month Engine'!$A:$A,0)+MATCH($A14,'_Month Engine'!$B$73:$B$82,0),0)) -> 0 | E14: =SUMIF('_Month Engine'!$C$5:$DR$5,E$4,INDEX('_Month Engine'!$C:$DR,MATCH("Cost Basis Released on Sale",'_Month Engine'!$A:$A,0)+MATCH($A14,'_Month Engine'!$B$73:$B$82,0),0)) -> 0 | F14: =SUMIF('_Month Engine'!$C$5:$DR$5,F$4,INDEX('_Month Engine'!$C:$DR,MATCH("Cost Basis Released on Sale",'_Month Engine'!$A:$A,0)+MATCH($A14,'_Month Engine'!$B$73:$B$82,0),0)) -> 0 | G14: =SUMIF('_Month Engine'!$C$5:$DR$5,G$4,INDEX('_Month Engine'!$C:$DR,MATCH("Cost Basis Released on Sale",'_Month Engine'!$A:$A,0)+MATCH($A14,'_Month Engine'!$B$73:$B$82,0),0)) -> 0 | H14: =SUMIF('_Month Engine'!$C$5:$DR$5,H$4,INDEX('_Month Engine'!$C:$DR,MATCH("Cost Basis Released on Sale",'_Month Engine'!$A:$A,0)+MATCH($A14,'_Month Engine'!$B$73:$B$82,0),0)) -> 0 | I14: =SUMIF('_Month Engine'!$C$5:$DR$5,I$4,INDEX('_Month Engine'!$C:$DR,MATCH("Cost Basis Released on Sale",'_Month Engine'!$A:$A,0)+MATCH($A14,'_Month Engine'!$B$73:$B$82,0),0)) -> 0 | J14: =SUMIF('_Month Engine'!$C$5:$DR$5,J$4,INDEX('_Month Engine'!$C:$DR,MATCH("Cost Basis Released on Sale",'_Month Engine'!$A:$A,0)+MATCH($A14,'_Month Engine'!$B$73:$B$82,0),0)) -> 0 | ... L14: =SUMIF('_Month Engine'!$C$5:$DR$5,L$4,INDEX('_Month Engine'!$C:$DR,MATCH("Cost Basis Released on Sale",'_Month Engine'!$A:$A,0)+MATCH($A14,'_Month Engine'!$B$73:$B$82,0),0)) -> 0
A15: 8 | B15: {=IF(Properties!$D$13=0,"",INDEX(Properties!$E:$E,$A15+5))} | C15: =SUMIF('_Month Engine'!$C$5:$DR$5,C$4,INDEX('_Month Engine'!$C:$DR,MATCH("Cost Basis Released on Sale",'_Month Engine'!$A:$A,0)+MATCH($A15,'_Month Engine'!$B$73:$B$82,0),0)) -> 0 | D15: =SUMIF('_Month Engine'!$C$5:$DR$5,D$4,INDEX('_Month Engine'!$C:$DR,MATCH("Cost Basis Released on Sale",'_Month Engine'!$A:$A,0)+MATCH($A15,'_Month Engine'!$B$73:$B$82,0),0)) -> 0 | E15: =SUMIF('_Month Engine'!$C$5:$DR$5,E$4,INDEX('_Month Engine'!$C:$DR,MATCH("Cost Basis Released on Sale",'_Month Engine'!$A:$A,0)+MATCH($A15,'_Month Engine'!$B$73:$B$82,0),0)) -> 0 | F15: =SUMIF('_Month Engine'!$C$5:$DR$5,F$4,INDEX('_Month Engine'!$C:$DR,MATCH("Cost Basis Released on Sale",'_Month Engine'!$A:$A,0)+MATCH($A15,'_Month Engine'!$B$73:$B$82,0),0)) -> 0 | G15: =SUMIF('_Month Engine'!$C$5:$DR$5,G$4,INDEX('_Month Engine'!$C:$DR,MATCH("Cost Basis Released on Sale",'_Month Engine'!$A:$A,0)+MATCH($A15,'_Month Engine'!$B$73:$B$82,0),0)) -> 0 | H15: =SUMIF('_Month Engine'!$C$5:$DR$5,H$4,INDEX('_Month Engine'!$C:$DR,MATCH("Cost Basis Released on Sale",'_Month Engine'!$A:$A,0)+MATCH($A15,'_Month Engine'!$B$73:$B$82,0),0)) -> 0 | I15: =SUMIF('_Month Engine'!$C$5:$DR$5,I$4,INDEX('_Month Engine'!$C:$DR,MATCH("Cost Basis Released on Sale",'_Month Engine'!$A:$A,0)+MATCH($A15,'_Month Engine'!$B$73:$B$82,0),0)) -> 0 | J15: =SUMIF('_Month Engine'!$C$5:$DR$5,J$4,INDEX('_Month Engine'!$C:$DR,MATCH("Cost Basis Released on Sale",'_Month Engine'!$A:$A,0)+MATCH($A15,'_Month Engine'!$B$73:$B$82,0),0)) -> 0 | ... L15: =SUMIF('_Month Engine'!$C$5:$DR$5,L$4,INDEX('_Month Engine'!$C:$DR,MATCH("Cost Basis Released on Sale",'_Month Engine'!$A:$A,0)+MATCH($A15,'_Month Engine'!$B$73:$B$82,0),0)) -> 0
A16: 9 | B16: {=IF(Properties!$D$14=0,"",INDEX(Properties!$E:$E,$A16+5))} | C16: =SUMIF('_Month Engine'!$C$5:$DR$5,C$4,INDEX('_Month Engine'!$C:$DR,MATCH("Cost Basis Released on Sale",'_Month Engine'!$A:$A,0)+MATCH($A16,'_Month Engine'!$B$73:$B$82,0),0)) -> 0 | D16: =SUMIF('_Month Engine'!$C$5:$DR$5,D$4,INDEX('_Month Engine'!$C:$DR,MATCH("Cost Basis Released on Sale",'_Month Engine'!$A:$A,0)+MATCH($A16,'_Month Engine'!$B$73:$B$82,0),0)) -> 0 | E16: =SUMIF('_Month Engine'!$C$5:$DR$5,E$4,INDEX('_Month Engine'!$C:$DR,MATCH("Cost Basis Released on Sale",'_Month Engine'!$A:$A,0)+MATCH($A16,'_Month Engine'!$B$73:$B$82,0),0)) -> 0 | F16: =SUMIF('_Month Engine'!$C$5:$DR$5,F$4,INDEX('_Month Engine'!$C:$DR,MATCH("Cost Basis Released on Sale",'_Month Engine'!$A:$A,0)+MATCH($A16,'_Month Engine'!$B$73:$B$82,0),0)) -> 0 | G16: =SUMIF('_Month Engine'!$C$5:$DR$5,G$4,INDEX('_Month Engine'!$C:$DR,MATCH("Cost Basis Released on Sale",'_Month Engine'!$A:$A,0)+MATCH($A16,'_Month Engine'!$B$73:$B$82,0),0)) -> 0 | H16: =SUMIF('_Month Engine'!$C$5:$DR$5,H$4,INDEX('_Month Engine'!$C:$DR,MATCH("Cost Basis Released on Sale",'_Month Engine'!$A:$A,0)+MATCH($A16,'_Month Engine'!$B$73:$B$82,0),0)) -> 0 | I16: =SUMIF('_Month Engine'!$C$5:$DR$5,I$4,INDEX('_Month Engine'!$C:$DR,MATCH("Cost Basis Released on Sale",'_Month Engine'!$A:$A,0)+MATCH($A16,'_Month Engine'!$B$73:$B$82,0),0)) -> 0 | J16: =SUMIF('_Month Engine'!$C$5:$DR$5,J$4,INDEX('_Month Engine'!$C:$DR,MATCH("Cost Basis Released on Sale",'_Month Engine'!$A:$A,0)+MATCH($A16,'_Month Engine'!$B$73:$B$82,0),0)) -> 0 | ... L16: =SUMIF('_Month Engine'!$C$5:$DR$5,L$4,INDEX('_Month Engine'!$C:$DR,MATCH("Cost Basis Released on Sale",'_Month Engine'!$A:$A,0)+MATCH($A16,'_Month Engine'!$B$73:$B$82,0),0)) -> 0
A17: 10 | B17: {=IF(Properties!$D$15=0,"",INDEX(Properties!$E:$E,$A17+5))} | C17: =SUMIF('_Month Engine'!$C$5:$DR$5,C$4,INDEX('_Month Engine'!$C:$DR,MATCH("Cost Basis Released on Sale",'_Month Engine'!$A:$A,0)+MATCH($A17,'_Month Engine'!$B$73:$B$82,0),0)) -> 0 | D17: =SUMIF('_Month Engine'!$C$5:$DR$5,D$4,INDEX('_Month Engine'!$C:$DR,MATCH("Cost Basis Released on Sale",'_Month Engine'!$A:$A,0)+MATCH($A17,'_Month Engine'!$B$73:$B$82,0),0)) -> 0 | E17: =SUMIF('_Month Engine'!$C$5:$DR$5,E$4,INDEX('_Month Engine'!$C:$DR,MATCH("Cost Basis Released on Sale",'_Month Engine'!$A:$A,0)+MATCH($A17,'_Month Engine'!$B$73:$B$82,0),0)) -> 0 | F17: =SUMIF('_Month Engine'!$C$5:$DR$5,F$4,INDEX('_Month Engine'!$C:$DR,MATCH("Cost Basis Released on Sale",'_Month Engine'!$A:$A,0)+MATCH($A17,'_Month Engine'!$B$73:$B$82,0),0)) -> 0 | G17: =SUMIF('_Month Engine'!$C$5:$DR$5,G$4,INDEX('_Month Engine'!$C:$DR,MATCH("Cost Basis Released on Sale",'_Month Engine'!$A:$A,0)+MATCH($A17,'_Month Engine'!$B$73:$B$82,0),0)) -> 0 | H17: =SUMIF('_Month Engine'!$C$5:$DR$5,H$4,INDEX('_Month Engine'!$C:$DR,MATCH("Cost Basis Released on Sale",'_Month Engine'!$A:$A,0)+MATCH($A17,'_Month Engine'!$B$73:$B$82,0),0)) -> 0 | I17: =SUMIF('_Month Engine'!$C$5:$DR$5,I$4,INDEX('_Month Engine'!$C:$DR,MATCH("Cost Basis Released on Sale",'_Month Engine'!$A:$A,0)+MATCH($A17,'_Month Engine'!$B$73:$B$82,0),0)) -> 0 | J17: =SUMIF('_Month Engine'!$C$5:$DR$5,J$4,INDEX('_Month Engine'!$C:$DR,MATCH("Cost Basis Released on Sale",'_Month Engine'!$A:$A,0)+MATCH($A17,'_Month Engine'!$B$73:$B$82,0),0)) -> 0 | ... L17: =SUMIF('_Month Engine'!$C$5:$DR$5,L$4,INDEX('_Month Engine'!$C:$DR,MATCH("Cost Basis Released on Sale",'_Month Engine'!$A:$A,0)+MATCH($A17,'_Month Engine'!$B$73:$B$82,0),0)) -> 0
B18: Add back: cost basis of properties sold (non-cash) | C18: =SUM(C8:C17) -> 0 | D18: =SUM(D8:D17) -> 0 | E18: =SUM(E8:E17) -> 3206998.4 | F18: =SUM(F8:F17) -> 3364967.6 | G18: =SUM(G8:G17) -> 0 | H18: =SUM(H8:H17) -> 0 | I18: =SUM(I8:I17) -> 0 | J18: =SUM(J8:J17) -> 0 | ... L18: =SUM(L8:L17) -> 0
B19: Net Cash from Operating Activities | C19: =C7+C18 -> -126083.61 | D19: =D7+D18 -> 1968.2859 | E19: =E7+E18 -> 5044335.5 | F19: =F7+F18 -> 5310088.8 | G19: =G7+G18 -> 0 | H19: =H7+H18 -> 0 | I19: =I7+I18 -> 0 | J19: =J7+J18 -> 0 | ... L19: =L7+L18 -> 0
B21: Cash Flow from Investing Activities
A22: 1 | B22: {=IF(Properties!$D$6=0,"",INDEX(Properties!$E:$E,$A22+5))} -> Aires de Campestre Apto 801 (Penthouse) | C22: =-SUMIF('_Month Engine'!$C$5:$DR$5,C$4,INDEX('_Month Engine'!$C:$DR,MATCH("Acquisition Outflow (Purchase + Closing)",'_Month Engine'!$A:$A,0)+MATCH($A22,'_Month Engine'!$B$8:$B$17,0),0)) -> -683333.33 | D22: =-SUMIF('_Month Engine'!$C$5:$DR$5,D$4,INDEX('_Month Engine'!$C:$DR,MATCH("Acquisition Outflow (Purchase + Closing)",'_Month Engine'!$A:$A,0)+MATCH($A22,'_Month Engine'!$B$8:$B$17,0),0)) -> 0 | E22: =-SUMIF('_Month Engine'!$C$5:$DR$5,E$4,INDEX('_Month Engine'!$C:$DR,MATCH("Acquisition Outflow (Purchase + Closing)",'_Month Engine'!$A:$A,0)+MATCH($A22,'_Month Engine'!$B$8:$B$17,0),0)) -> 0 | F22: =-SUMIF('_Month Engine'!$C$5:$DR$5,F$4,INDEX('_Month Engine'!$C:$DR,MATCH("Acquisition Outflow (Purchase + Closing)",'_Month Engine'!$A:$A,0)+MATCH($A22,'_Month Engine'!$B$8:$B$17,0),0)) -> 0 | G22: =-SUMIF('_Month Engine'!$C$5:$DR$5,G$4,INDEX('_Month Engine'!$C:$DR,MATCH("Acquisition Outflow (Purchase + Closing)",'_Month Engine'!$A:$A,0)+MATCH($A22,'_Month Engine'!$B$8:$B$17,0),0)) -> 0 | H22: =-SUMIF('_Month Engine'!$C$5:$DR$5,H$4,INDEX('_Month Engine'!$C:$DR,MATCH("Acquisition Outflow (Purchase + Closing)",'_Month Engine'!$A:$A,0)+MATCH($A22,'_Month Engine'!$B$8:$B$17,0),0)) -> 0 | I22: =-SUMIF('_Month Engine'!$C$5:$DR$5,I$4,INDEX('_Month Engine'!$C:$DR,MATCH("Acquisition Outflow (Purchase + Closing)",'_Month Engine'!$A:$A,0)+MATCH($A22,'_Month Engine'!$B$8:$B$17,0),0)) -> 0 | J22: =-SUMIF('_Month Engine'!$C$5:$DR$5,J$4,INDEX('_Month Engine'!$C:$DR,MATCH("Acquisition Outflow (Purchase + Closing)",'_Month Engine'!$A:$A,0)+MATCH($A22,'_Month Engine'!$B$8:$B$17,0),0)) -> 0 | ... L22: =-SUMIF('_Month Engine'!$C$5:$DR$5,L$4,INDEX('_Month Engine'!$C:$DR,MATCH("Acquisition Outflow (Purchase + Closing)",'_Month Engine'!$A:$A,0)+MATCH($A22,'_Month Engine'!$B$8:$B$17,0),0)) -> 0
A23: 2 | B23: {=IF(Properties!$D$7=0,"",INDEX(Properties!$E:$E,$A23+5))} -> Fontanar Apto 201 (Penthouse) | C23: =-SUMIF('_Month Engine'!$C$5:$DR$5,C$4,INDEX('_Month Engine'!$C:$DR,MATCH("Acquisition Outflow (Purchase + Closing)",'_Month Engine'!$A:$A,0)+MATCH($A23,'_Month Engine'!$B$8:$B$17,0),0)) -> -1044902.9 | D23: =-SUMIF('_Month Engine'!$C$5:$DR$5,D$4,INDEX('_Month Engine'!$C:$DR,MATCH("Acquisition Outflow (Purchase + Closing)",'_Month Engine'!$A:$A,0)+MATCH($A23,'_Month Engine'!$B$8:$B$17,0),0)) -> 0 | E23: =-SUMIF('_Month Engine'!$C$5:$DR$5,E$4,INDEX('_Month Engine'!$C:$DR,MATCH("Acquisition Outflow (Purchase + Closing)",'_Month Engine'!$A:$A,0)+MATCH($A23,'_Month Engine'!$B$8:$B$17,0),0)) -> 0 | F23: =-SUMIF('_Month Engine'!$C$5:$DR$5,F$4,INDEX('_Month Engine'!$C:$DR,MATCH("Acquisition Outflow (Purchase + Closing)",'_Month Engine'!$A:$A,0)+MATCH($A23,'_Month Engine'!$B$8:$B$17,0),0)) -> 0 | G23: =-SUMIF('_Month Engine'!$C$5:$DR$5,G$4,INDEX('_Month Engine'!$C:$DR,MATCH("Acquisition Outflow (Purchase + Closing)",'_Month Engine'!$A:$A,0)+MATCH($A23,'_Month Engine'!$B$8:$B$17,0),0)) -> 0 | H23: =-SUMIF('_Month Engine'!$C$5:$DR$5,H$4,INDEX('_Month Engine'!$C:$DR,MATCH("Acquisition Outflow (Purchase + Closing)",'_Month Engine'!$A:$A,0)+MATCH($A23,'_Month Engine'!$B$8:$B$17,0),0)) -> 0 | I23: =-SUMIF('_Month Engine'!$C$5:$DR$5,I$4,INDEX('_Month Engine'!$C:$DR,MATCH("Acquisition Outflow (Purchase + Closing)",'_Month Engine'!$A:$A,0)+MATCH($A23,'_Month Engine'!$B$8:$B$17,0),0)) -> 0 | J23: =-SUMIF('_Month Engine'!$C$5:$DR$5,J$4,INDEX('_Month Engine'!$C:$DR,MATCH("Acquisition Outflow (Purchase + Closing)",'_Month Engine'!$A:$A,0)+MATCH($A23,'_Month Engine'!$B$8:$B$17,0),0)) -> 0 | ... L23: =-SUMIF('_Month Engine'!$C$5:$DR$5,L$4,INDEX('_Month Engine'!$C:$DR,MATCH("Acquisition Outflow (Purchase + Closing)",'_Month Engine'!$A:$A,0)+MATCH($A23,'_Month Engine'!$B$8:$B$17,0),0)) -> 0
A24: 3 | B24: {=IF(Properties!$D$8=0,"",INDEX(Properties!$E:$E,$A24+5))} -> San Lucas Apto 101 | C24: =-SUMIF('_Month Engine'!$C$5:$DR$5,C$4,INDEX('_Month Engine'!$C:$DR,MATCH("Acquisition Outflow (Purchase + Closing)",'_Month Engine'!$A:$A,0)+MATCH($A24,'_Month Engine'!$B$8:$B$17,0),0)) -> -456108.41 | D24: =-SUMIF('_Month Engine'!$C$5:$DR$5,D$4,INDEX('_Month Engine'!$C:$DR,MATCH("Acquisition Outflow (Purchase + Closing)",'_Month Engine'!$A:$A,0)+MATCH($A24,'_Month Engine'!$B$8:$B$17,0),0)) -> 0 | E24: =-SUMIF('_Month Engine'!$C$5:$DR$5,E$4,INDEX('_Month Engine'!$C:$DR,MATCH("Acquisition Outflow (Purchase + Closing)",'_Month Engine'!$A:$A,0)+MATCH($A24,'_Month Engine'!$B$8:$B$17,0),0)) -> 0 | F24: =-SUMIF('_Month Engine'!$C$5:$DR$5,F$4,INDEX('_Month Engine'!$C:$DR,MATCH("Acquisition Outflow (Purchase + Closing)",'_Month Engine'!$A:$A,0)+MATCH($A24,'_Month Engine'!$B$8:$B$17,0),0)) -> 0 | G24: =-SUMIF('_Month Engine'!$C$5:$DR$5,G$4,INDEX('_Month Engine'!$C:$DR,MATCH("Acquisition Outflow (Purchase + Closing)",'_Month Engine'!$A:$A,0)+MATCH($A24,'_Month Engine'!$B$8:$B$17,0),0)) -> 0 | H24: =-SUMIF('_Month Engine'!$C$5:$DR$5,H$4,INDEX('_Month Engine'!$C:$DR,MATCH("Acquisition Outflow (Purchase + Closing)",'_Month Engine'!$A:$A,0)+MATCH($A24,'_Month Engine'!$B$8:$B$17,0),0)) -> 0 | I24: =-SUMIF('_Month Engine'!$C$5:$DR$5,I$4,INDEX('_Month Engine'!$C:$DR,MATCH("Acquisition Outflow (Purchase + Closing)",'_Month Engine'!$A:$A,0)+MATCH($A24,'_Month Engine'!$B$8:$B$17,0),0)) -> 0 | J24: =-SUMIF('_Month Engine'!$C$5:$DR$5,J$4,INDEX('_Month Engine'!$C:$DR,MATCH("Acquisition Outflow (Purchase + Closing)",'_Month Engine'!$A:$A,0)+MATCH($A24,'_Month Engine'!$B$8:$B$17,0),0)) -> 0 | ... L24: =-SUMIF('_Month Engine'!$C$5:$DR$5,L$4,INDEX('_Month Engine'!$C:$DR,MATCH("Acquisition Outflow (Purchase + Closing)",'_Month Engine'!$A:$A,0)+MATCH($A24,'_Month Engine'!$B$8:$B$17,0),0)) -> 0
A25: 4 | B25: {=IF(Properties!$D$9=0,"",INDEX(Properties!$E:$E,$A25+5))} -> Casa Montana Lote 2 (Samuel Gaviria House) | C25: =-SUMIF('_Month Engine'!$C$5:$DR$5,C$4,INDEX('_Month Engine'!$C:$DR,MATCH("Acquisition Outflow (Purchase + Closing)",'_Month Engine'!$A:$A,0)+MATCH($A25,'_Month Engine'!$B$8:$B$17,0),0)) -> -1164320.4 | D25: =-SUMIF('_Month Engine'!$C$5:$DR$5,D$4,INDEX('_Month Engine'!$C:$DR,MATCH("Acquisition Outflow (Purchase + Closing)",'_Month Engine'!$A:$A,0)+MATCH($A25,'_Month Engine'!$B$8:$B$17,0),0)) -> 0 | E25: =-SUMIF('_Month Engine'!$C$5:$DR$5,E$4,INDEX('_Month Engine'!$C:$DR,MATCH("Acquisition Outflow (Purchase + Closing)",'_Month Engine'!$A:$A,0)+MATCH($A25,'_Month Engine'!$B$8:$B$17,0),0)) -> 0 | F25: =-SUMIF('_Month Engine'!$C$5:$DR$5,F$4,INDEX('_Month Engine'!$C:$DR,MATCH("Acquisition Outflow (Purchase + Closing)",'_Month Engine'!$A:$A,0)+MATCH($A25,'_Month Engine'!$B$8:$B$17,0),0)) -> 0 | G25: =-SUMIF('_Month Engine'!$C$5:$DR$5,G$4,INDEX('_Month Engine'!$C:$DR,MATCH("Acquisition Outflow (Purchase + Closing)",'_Month Engine'!$A:$A,0)+MATCH($A25,'_Month Engine'!$B$8:$B$17,0),0)) -> 0 | H25: =-SUMIF('_Month Engine'!$C$5:$DR$5,H$4,INDEX('_Month Engine'!$C:$DR,MATCH("Acquisition Outflow (Purchase + Closing)",'_Month Engine'!$A:$A,0)+MATCH($A25,'_Month Engine'!$B$8:$B$17,0),0)) -> 0 | I25: =-SUMIF('_Month Engine'!$C$5:$DR$5,I$4,INDEX('_Month Engine'!$C:$DR,MATCH("Acquisition Outflow (Purchase + Closing)",'_Month Engine'!$A:$A,0)+MATCH($A25,'_Month Engine'!$B$8:$B$17,0),0)) -> 0 | J25: =-SUMIF('_Month Engine'!$C$5:$DR$5,J$4,INDEX('_Month Engine'!$C:$DR,MATCH("Acquisition Outflow (Purchase + Closing)",'_Month Engine'!$A:$A,0)+MATCH($A25,'_Month Engine'!$B$8:$B$17,0),0)) -> 0 | ... L25: =-SUMIF('_Month Engine'!$C$5:$DR$5,L$4,INDEX('_Month Engine'!$C:$DR,MATCH("Acquisition Outflow (Purchase + Closing)",'_Month Engine'!$A:$A,0)+MATCH($A25,'_Month Engine'!$B$8:$B$17,0),0)) -> 0
A26: 5 | B26: {=IF(Properties!$D$10=0,"",INDEX(Properties!$E:$E,$A26+5))} -> Casa Monte Sereno | C26: =-SUMIF('_Month Engine'!$C$5:$DR$5,C$4,INDEX('_Month Engine'!$C:$DR,MATCH("Acquisition Outflow (Purchase + Closing)",'_Month Engine'!$A:$A,0)+MATCH($A26,'_Month Engine'!$B$8:$B$17,0),0)) -> -1326860.8 | D26: =-SUMIF('_Month Engine'!$C$5:$DR$5,D$4,INDEX('_Month Engine'!$C:$DR,MATCH("Acquisition Outflow (Purchase + Closing)",'_Month Engine'!$A:$A,0)+MATCH($A26,'_Month Engine'!$B$8:$B$17,0),0)) -> 0 | E26: =-SUMIF('_Month Engine'!$C$5:$DR$5,E$4,INDEX('_Month Engine'!$C:$DR,MATCH("Acquisition Outflow (Purchase + Closing)",'_Month Engine'!$A:$A,0)+MATCH($A26,'_Month Engine'!$B$8:$B$17,0),0)) -> 0 | F26: =-SUMIF('_Month Engine'!$C$5:$DR$5,F$4,INDEX('_Month Engine'!$C:$DR,MATCH("Acquisition Outflow (Purchase + Closing)",'_Month Engine'!$A:$A,0)+MATCH($A26,'_Month Engine'!$B$8:$B$17,0),0)) -> 0 | G26: =-SUMIF('_Month Engine'!$C$5:$DR$5,G$4,INDEX('_Month Engine'!$C:$DR,MATCH("Acquisition Outflow (Purchase + Closing)",'_Month Engine'!$A:$A,0)+MATCH($A26,'_Month Engine'!$B$8:$B$17,0),0)) -> 0 | H26: =-SUMIF('_Month Engine'!$C$5:$DR$5,H$4,INDEX('_Month Engine'!$C:$DR,MATCH("Acquisition Outflow (Purchase + Closing)",'_Month Engine'!$A:$A,0)+MATCH($A26,'_Month Engine'!$B$8:$B$17,0),0)) -> 0 | I26: =-SUMIF('_Month Engine'!$C$5:$DR$5,I$4,INDEX('_Month Engine'!$C:$DR,MATCH("Acquisition Outflow (Purchase + Closing)",'_Month Engine'!$A:$A,0)+MATCH($A26,'_Month Engine'!$B$8:$B$17,0),0)) -> 0 | J26: =-SUMIF('_Month Engine'!$C$5:$DR$5,J$4,INDEX('_Month Engine'!$C:$DR,MATCH("Acquisition Outflow (Purchase + Closing)",'_Month Engine'!$A:$A,0)+MATCH($A26,'_Month Engine'!$B$8:$B$17,0),0)) -> 0 | ... L26: =-SUMIF('_Month Engine'!$C$5:$DR$5,L$4,INDEX('_Month Engine'!$C:$DR,MATCH("Acquisition Outflow (Purchase + Closing)",'_Month Engine'!$A:$A,0)+MATCH($A26,'_Month Engine'!$B$8:$B$17,0),0)) -> 0
A27: 6 | B27: {=IF(Properties!$D$11=0,"",INDEX(Properties!$E:$E,$A27+5))} | C27: =-SUMIF('_Month Engine'!$C$5:$DR$5,C$4,INDEX('_Month Engine'!$C:$DR,MATCH("Acquisition Outflow (Purchase + Closing)",'_Month Engine'!$A:$A,0)+MATCH($A27,'_Month Engine'!$B$8:$B$17,0),0)) -> 0 | D27: =-SUMIF('_Month Engine'!$C$5:$DR$5,D$4,INDEX('_Month Engine'!$C:$DR,MATCH("Acquisition Outflow (Purchase + Closing)",'_Month Engine'!$A:$A,0)+MATCH($A27,'_Month Engine'!$B$8:$B$17,0),0)) -> 0 | E27: =-SUMIF('_Month Engine'!$C$5:$DR$5,E$4,INDEX('_Month Engine'!$C:$DR,MATCH("Acquisition Outflow (Purchase + Closing)",'_Month Engine'!$A:$A,0)+MATCH($A27,'_Month Engine'!$B$8:$B$17,0),0)) -> 0 | F27: =-SUMIF('_Month Engine'!$C$5:$DR$5,F$4,INDEX('_Month Engine'!$C:$DR,MATCH("Acquisition Outflow (Purchase + Closing)",'_Month Engine'!$A:$A,0)+MATCH($A27,'_Month Engine'!$B$8:$B$17,0),0)) -> 0 | G27: =-SUMIF('_Month Engine'!$C$5:$DR$5,G$4,INDEX('_Month Engine'!$C:$DR,MATCH("Acquisition Outflow (Purchase + Closing)",'_Month Engine'!$A:$A,0)+MATCH($A27,'_Month Engine'!$B$8:$B$17,0),0)) -> 0 | H27: =-SUMIF('_Month Engine'!$C$5:$DR$5,H$4,INDEX('_Month Engine'!$C:$DR,MATCH("Acquisition Outflow (Purchase + Closing)",'_Month Engine'!$A:$A,0)+MATCH($A27,'_Month Engine'!$B$8:$B$17,0),0)) -> 0 | I27: =-SUMIF('_Month Engine'!$C$5:$DR$5,I$4,INDEX('_Month Engine'!$C:$DR,MATCH("Acquisition Outflow (Purchase + Closing)",'_Month Engine'!$A:$A,0)+MATCH($A27,'_Month Engine'!$B$8:$B$17,0),0)) -> 0 | J27: =-SUMIF('_Month Engine'!$C$5:$DR$5,J$4,INDEX('_Month Engine'!$C:$DR,MATCH("Acquisition Outflow (Purchase + Closing)",'_Month Engine'!$A:$A,0)+MATCH($A27,'_Month Engine'!$B$8:$B$17,0),0)) -> 0 | ... L27: =-SUMIF('_Month Engine'!$C$5:$DR$5,L$4,INDEX('_Month Engine'!$C:$DR,MATCH("Acquisition Outflow (Purchase + Closing)",'_Month Engine'!$A:$A,0)+MATCH($A27,'_Month Engine'!$B$8:$B$17,0),0)) -> 0
A28: 7 | B28: {=IF(Properties!$D$12=0,"",INDEX(Properties!$E:$E,$A28+5))} | C28: =-SUMIF('_Month Engine'!$C$5:$DR$5,C$4,INDEX('_Month Engine'!$C:$DR,MATCH("Acquisition Outflow (Purchase + Closing)",'_Month Engine'!$A:$A,0)+MATCH($A28,'_Month Engine'!$B$8:$B$17,0),0)) -> 0 | D28: =-SUMIF('_Month Engine'!$C$5:$DR$5,D$4,INDEX('_Month Engine'!$C:$DR,MATCH("Acquisition Outflow (Purchase + Closing)",'_Month Engine'!$A:$A,0)+MATCH($A28,'_Month Engine'!$B$8:$B$17,0),0)) -> 0 | E28: =-SUMIF('_Month Engine'!$C$5:$DR$5,E$4,INDEX('_Month Engine'!$C:$DR,MATCH("Acquisition Outflow (Purchase + Closing)",'_Month Engine'!$A:$A,0)+MATCH($A28,'_Month Engine'!$B$8:$B$17,0),0)) -> 0 | F28: =-SUMIF('_Month Engine'!$C$5:$DR$5,F$4,INDEX('_Month Engine'!$C:$DR,MATCH("Acquisition Outflow (Purchase + Closing)",'_Month Engine'!$A:$A,0)+MATCH($A28,'_Month Engine'!$B$8:$B$17,0),0)) -> 0 | G28: =-SUMIF('_Month Engine'!$C$5:$DR$5,G$4,INDEX('_Month Engine'!$C:$DR,MATCH("Acquisition Outflow (Purchase + Closing)",'_Month Engine'!$A:$A,0)+MATCH($A28,'_Month Engine'!$B$8:$B$17,0),0)) -> 0 | H28: =-SUMIF('_Month Engine'!$C$5:$DR$5,H$4,INDEX('_Month Engine'!$C:$DR,MATCH("Acquisition Outflow (Purchase + Closing)",'_Month Engine'!$A:$A,0)+MATCH($A28,'_Month Engine'!$B$8:$B$17,0),0)) -> 0 | I28: =-SUMIF('_Month Engine'!$C$5:$DR$5,I$4,INDEX('_Month Engine'!$C:$DR,MATCH("Acquisition Outflow (Purchase + Closing)",'_Month Engine'!$A:$A,0)+MATCH($A28,'_Month Engine'!$B$8:$B$17,0),0)) -> 0 | J28: =-SUMIF('_Month Engine'!$C$5:$DR$5,J$4,INDEX('_Month Engine'!$C:$DR,MATCH("Acquisition Outflow (Purchase + Closing)",'_Month Engine'!$A:$A,0)+MATCH($A28,'_Month Engine'!$B$8:$B$17,0),0)) -> 0 | ... L28: =-SUMIF('_Month Engine'!$C$5:$DR$5,L$4,INDEX('_Month Engine'!$C:$DR,MATCH("Acquisition Outflow (Purchase + Closing)",'_Month Engine'!$A:$A,0)+MATCH($A28,'_Month Engine'!$B$8:$B$17,0),0)) -> 0
A29: 8 | B29: {=IF(Properties!$D$13=0,"",INDEX(Properties!$E:$E,$A29+5))} | C29: =-SUMIF('_Month Engine'!$C$5:$DR$5,C$4,INDEX('_Month Engine'!$C:$DR,MATCH("Acquisition Outflow (Purchase + Closing)",'_Month Engine'!$A:$A,0)+MATCH($A29,'_Month Engine'!$B$8:$B$17,0),0)) -> 0 | D29: =-SUMIF('_Month Engine'!$C$5:$DR$5,D$4,INDEX('_Month Engine'!$C:$DR,MATCH("Acquisition Outflow (Purchase + Closing)",'_Month Engine'!$A:$A,0)+MATCH($A29,'_Month Engine'!$B$8:$B$17,0),0)) -> 0 | E29: =-SUMIF('_Month Engine'!$C$5:$DR$5,E$4,INDEX('_Month Engine'!$C:$DR,MATCH("Acquisition Outflow (Purchase + Closing)",'_Month Engine'!$A:$A,0)+MATCH($A29,'_Month Engine'!$B$8:$B$17,0),0)) -> 0 | F29: =-SUMIF('_Month Engine'!$C$5:$DR$5,F$4,INDEX('_Month Engine'!$C:$DR,MATCH("Acquisition Outflow (Purchase + Closing)",'_Month Engine'!$A:$A,0)+MATCH($A29,'_Month Engine'!$B$8:$B$17,0),0)) -> 0 | G29: =-SUMIF('_Month Engine'!$C$5:$DR$5,G$4,INDEX('_Month Engine'!$C:$DR,MATCH("Acquisition Outflow (Purchase + Closing)",'_Month Engine'!$A:$A,0)+MATCH($A29,'_Month Engine'!$B$8:$B$17,0),0)) -> 0 | H29: =-SUMIF('_Month Engine'!$C$5:$DR$5,H$4,INDEX('_Month Engine'!$C:$DR,MATCH("Acquisition Outflow (Purchase + Closing)",'_Month Engine'!$A:$A,0)+MATCH($A29,'_Month Engine'!$B$8:$B$17,0),0)) -> 0 | I29: =-SUMIF('_Month Engine'!$C$5:$DR$5,I$4,INDEX('_Month Engine'!$C:$DR,MATCH("Acquisition Outflow (Purchase + Closing)",'_Month Engine'!$A:$A,0)+MATCH($A29,'_Month Engine'!$B$8:$B$17,0),0)) -> 0 | J29: =-SUMIF('_Month Engine'!$C$5:$DR$5,J$4,INDEX('_Month Engine'!$C:$DR,MATCH("Acquisition Outflow (Purchase + Closing)",'_Month Engine'!$A:$A,0)+MATCH($A29,'_Month Engine'!$B$8:$B$17,0),0)) -> 0 | ... L29: =-SUMIF('_Month Engine'!$C$5:$DR$5,L$4,INDEX('_Month Engine'!$C:$DR,MATCH("Acquisition Outflow (Purchase + Closing)",'_Month Engine'!$A:$A,0)+MATCH($A29,'_Month Engine'!$B$8:$B$17,0),0)) -> 0
A30: 9 | B30: {=IF(Properties!$D$14=0,"",INDEX(Properties!$E:$E,$A30+5))} | C30: =-SUMIF('_Month Engine'!$C$5:$DR$5,C$4,INDEX('_Month Engine'!$C:$DR,MATCH("Acquisition Outflow (Purchase + Closing)",'_Month Engine'!$A:$A,0)+MATCH($A30,'_Month Engine'!$B$8:$B$17,0),0)) -> 0 | D30: =-SUMIF('_Month Engine'!$C$5:$DR$5,D$4,INDEX('_Month Engine'!$C:$DR,MATCH("Acquisition Outflow (Purchase + Closing)",'_Month Engine'!$A:$A,0)+MATCH($A30,'_Month Engine'!$B$8:$B$17,0),0)) -> 0 | E30: =-SUMIF('_Month Engine'!$C$5:$DR$5,E$4,INDEX('_Month Engine'!$C:$DR,MATCH("Acquisition Outflow (Purchase + Closing)",'_Month Engine'!$A:$A,0)+MATCH($A30,'_Month Engine'!$B$8:$B$17,0),0)) -> 0 | F30: =-SUMIF('_Month Engine'!$C$5:$DR$5,F$4,INDEX('_Month Engine'!$C:$DR,MATCH("Acquisition Outflow (Purchase + Closing)",'_Month Engine'!$A:$A,0)+MATCH($A30,'_Month Engine'!$B$8:$B$17,0),0)) -> 0 | G30: =-SUMIF('_Month Engine'!$C$5:$DR$5,G$4,INDEX('_Month Engine'!$C:$DR,MATCH("Acquisition Outflow (Purchase + Closing)",'_Month Engine'!$A:$A,0)+MATCH($A30,'_Month Engine'!$B$8:$B$17,0),0)) -> 0 | H30: =-SUMIF('_Month Engine'!$C$5:$DR$5,H$4,INDEX('_Month Engine'!$C:$DR,MATCH("Acquisition Outflow (Purchase + Closing)",'_Month Engine'!$A:$A,0)+MATCH($A30,'_Month Engine'!$B$8:$B$17,0),0)) -> 0 | I30: =-SUMIF('_Month Engine'!$C$5:$DR$5,I$4,INDEX('_Month Engine'!$C:$DR,MATCH("Acquisition Outflow (Purchase + Closing)",'_Month Engine'!$A:$A,0)+MATCH($A30,'_Month Engine'!$B$8:$B$17,0),0)) -> 0 | J30: =-SUMIF('_Month Engine'!$C$5:$DR$5,J$4,INDEX('_Month Engine'!$C:$DR,MATCH("Acquisition Outflow (Purchase + Closing)",'_Month Engine'!$A:$A,0)+MATCH($A30,'_Month Engine'!$B$8:$B$17,0),0)) -> 0 | ... L30: =-SUMIF('_Month Engine'!$C$5:$DR$5,L$4,INDEX('_Month Engine'!$C:$DR,MATCH("Acquisition Outflow (Purchase + Closing)",'_Month Engine'!$A:$A,0)+MATCH($A30,'_Month Engine'!$B$8:$B$17,0),0)) -> 0
A31: 10 | B31: {=IF(Properties!$D$15=0,"",INDEX(Properties!$E:$E,$A31+5))} | C31: =-SUMIF('_Month Engine'!$C$5:$DR$5,C$4,INDEX('_Month Engine'!$C:$DR,MATCH("Acquisition Outflow (Purchase + Closing)",'_Month Engine'!$A:$A,0)+MATCH($A31,'_Month Engine'!$B$8:$B$17,0),0)) -> 0 | D31: =-SUMIF('_Month Engine'!$C$5:$DR$5,D$4,INDEX('_Month Engine'!$C:$DR,MATCH("Acquisition Outflow (Purchase + Closing)",'_Month Engine'!$A:$A,0)+MATCH($A31,'_Month Engine'!$B$8:$B$17,0),0)) -> 0 | E31: =-SUMIF('_Month Engine'!$C$5:$DR$5,E$4,INDEX('_Month Engine'!$C:$DR,MATCH("Acquisition Outflow (Purchase + Closing)",'_Month Engine'!$A:$A,0)+MATCH($A31,'_Month Engine'!$B$8:$B$17,0),0)) -> 0 | F31: =-SUMIF('_Month Engine'!$C$5:$DR$5,F$4,INDEX('_Month Engine'!$C:$DR,MATCH("Acquisition Outflow (Purchase + Closing)",'_Month Engine'!$A:$A,0)+MATCH($A31,'_Month Engine'!$B$8:$B$17,0),0)) -> 0 | G31: =-SUMIF('_Month Engine'!$C$5:$DR$5,G$4,INDEX('_Month Engine'!$C:$DR,MATCH("Acquisition Outflow (Purchase + Closing)",'_Month Engine'!$A:$A,0)+MATCH($A31,'_Month Engine'!$B$8:$B$17,0),0)) -> 0 | H31: =-SUMIF('_Month Engine'!$C$5:$DR$5,H$4,INDEX('_Month Engine'!$C:$DR,MATCH("Acquisition Outflow (Purchase + Closing)",'_Month Engine'!$A:$A,0)+MATCH($A31,'_Month Engine'!$B$8:$B$17,0),0)) -> 0 | I31: =-SUMIF('_Month Engine'!$C$5:$DR$5,I$4,INDEX('_Month Engine'!$C:$DR,MATCH("Acquisition Outflow (Purchase + Closing)",'_Month Engine'!$A:$A,0)+MATCH($A31,'_Month Engine'!$B$8:$B$17,0),0)) -> 0 | J31: =-SUMIF('_Month Engine'!$C$5:$DR$5,J$4,INDEX('_Month Engine'!$C:$DR,MATCH("Acquisition Outflow (Purchase + Closing)",'_Month Engine'!$A:$A,0)+MATCH($A31,'_Month Engine'!$B$8:$B$17,0),0)) -> 0 | ... L31: =-SUMIF('_Month Engine'!$C$5:$DR$5,L$4,INDEX('_Month Engine'!$C:$DR,MATCH("Acquisition Outflow (Purchase + Closing)",'_Month Engine'!$A:$A,0)+MATCH($A31,'_Month Engine'!$B$8:$B$17,0),0)) -> 0
B32: Property acquisitions (purchase + closing) | C32: =SUM(C22:C31) -> -4675525.9 | D32: =SUM(D22:D31) -> 0 | E32: =SUM(E22:E31) -> 0 | F32: =SUM(F22:F31) -> 0 | G32: =SUM(G22:G31) -> 0 | H32: =SUM(H22:H31) -> 0 | I32: =SUM(I22:I31) -> 0 | J32: =SUM(J22:J31) -> 0 | ... L32: =SUM(L22:L31) -> 0
A33: 1 | B33: {=IF(Properties!$D$6=0,"",INDEX(Properties!$E:$E,$A33+5))} -> Aires de Campestre Apto 801 (Penthouse) | C33: =-SUMIF('_Month Engine'!$C$5:$DR$5,C$4,INDEX('_Month Engine'!$C:$DR,MATCH("Renovation Capex",'_Month Engine'!$A:$A,0)+MATCH($A33,'_Month Engine'!$B$21:$B$30,0),0)) -> -485436.89 | D33: =-SUMIF('_Month Engine'!$C$5:$DR$5,D$4,INDEX('_Month Engine'!$C:$DR,MATCH("Renovation Capex",'_Month Engine'!$A:$A,0)+MATCH($A33,'_Month Engine'!$B$21:$B$30,0),0)) -> 0 | E33: =-SUMIF('_Month Engine'!$C$5:$DR$5,E$4,INDEX('_Month Engine'!$C:$DR,MATCH("Renovation Capex",'_Month Engine'!$A:$A,0)+MATCH($A33,'_Month Engine'!$B$21:$B$30,0),0)) -> 0 | F33: =-SUMIF('_Month Engine'!$C$5:$DR$5,F$4,INDEX('_Month Engine'!$C:$DR,MATCH("Renovation Capex",'_Month Engine'!$A:$A,0)+MATCH($A33,'_Month Engine'!$B$21:$B$30,0),0)) -> 0 | G33: =-SUMIF('_Month Engine'!$C$5:$DR$5,G$4,INDEX('_Month Engine'!$C:$DR,MATCH("Renovation Capex",'_Month Engine'!$A:$A,0)+MATCH($A33,'_Month Engine'!$B$21:$B$30,0),0)) -> 0 | H33: =-SUMIF('_Month Engine'!$C$5:$DR$5,H$4,INDEX('_Month Engine'!$C:$DR,MATCH("Renovation Capex",'_Month Engine'!$A:$A,0)+MATCH($A33,'_Month Engine'!$B$21:$B$30,0),0)) -> 0 | I33: =-SUMIF('_Month Engine'!$C$5:$DR$5,I$4,INDEX('_Month Engine'!$C:$DR,MATCH("Renovation Capex",'_Month Engine'!$A:$A,0)+MATCH($A33,'_Month Engine'!$B$21:$B$30,0),0)) -> 0 | J33: =-SUMIF('_Month Engine'!$C$5:$DR$5,J$4,INDEX('_Month Engine'!$C:$DR,MATCH("Renovation Capex",'_Month Engine'!$A:$A,0)+MATCH($A33,'_Month Engine'!$B$21:$B$30,0),0)) -> 0 | ... L33: =-SUMIF('_Month Engine'!$C$5:$DR$5,L$4,INDEX('_Month Engine'!$C:$DR,MATCH("Renovation Capex",'_Month Engine'!$A:$A,0)+MATCH($A33,'_Month Engine'!$B$21:$B$30,0),0)) -> 0
A34: 2 | B34: {=IF(Properties!$D$7=0,"",INDEX(Properties!$E:$E,$A34+5))} -> Fontanar Apto 201 (Penthouse) | C34: =-SUMIF('_Month Engine'!$C$5:$DR$5,C$4,INDEX('_Month Engine'!$C:$DR,MATCH("Renovation Capex",'_Month Engine'!$A:$A,0)+MATCH($A34,'_Month Engine'!$B$21:$B$30,0),0)) -> -245954.69 | D34: =-SUMIF('_Month Engine'!$C$5:$DR$5,D$4,INDEX('_Month Engine'!$C:$DR,MATCH("Renovation Capex",'_Month Engine'!$A:$A,0)+MATCH($A34,'_Month Engine'!$B$21:$B$30,0),0)) -> 0 | E34: =-SUMIF('_Month Engine'!$C$5:$DR$5,E$4,INDEX('_Month Engine'!$C:$DR,MATCH("Renovation Capex",'_Month Engine'!$A:$A,0)+MATCH($A34,'_Month Engine'!$B$21:$B$30,0),0)) -> 0 | F34: =-SUMIF('_Month Engine'!$C$5:$DR$5,F$4,INDEX('_Month Engine'!$C:$DR,MATCH("Renovation Capex",'_Month Engine'!$A:$A,0)+MATCH($A34,'_Month Engine'!$B$21:$B$30,0),0)) -> 0 | G34: =-SUMIF('_Month Engine'!$C$5:$DR$5,G$4,INDEX('_Month Engine'!$C:$DR,MATCH("Renovation Capex",'_Month Engine'!$A:$A,0)+MATCH($A34,'_Month Engine'!$B$21:$B$30,0),0)) -> 0 | H34: =-SUMIF('_Month Engine'!$C$5:$DR$5,H$4,INDEX('_Month Engine'!$C:$DR,MATCH("Renovation Capex",'_Month Engine'!$A:$A,0)+MATCH($A34,'_Month Engine'!$B$21:$B$30,0),0)) -> 0 | I34: =-SUMIF('_Month Engine'!$C$5:$DR$5,I$4,INDEX('_Month Engine'!$C:$DR,MATCH("Renovation Capex",'_Month Engine'!$A:$A,0)+MATCH($A34,'_Month Engine'!$B$21:$B$30,0),0)) -> 0 | J34: =-SUMIF('_Month Engine'!$C$5:$DR$5,J$4,INDEX('_Month Engine'!$C:$DR,MATCH("Renovation Capex",'_Month Engine'!$A:$A,0)+MATCH($A34,'_Month Engine'!$B$21:$B$30,0),0)) -> 0 | ... L34: =-SUMIF('_Month Engine'!$C$5:$DR$5,L$4,INDEX('_Month Engine'!$C:$DR,MATCH("Renovation Capex",'_Month Engine'!$A:$A,0)+MATCH($A34,'_Month Engine'!$B$21:$B$30,0),0)) -> 0
A35: 3 | B35: {=IF(Properties!$D$8=0,"",INDEX(Properties!$E:$E,$A35+5))} -> San Lucas Apto 101 | C35: =-SUMIF('_Month Engine'!$C$5:$DR$5,C$4,INDEX('_Month Engine'!$C:$DR,MATCH("Renovation Capex",'_Month Engine'!$A:$A,0)+MATCH($A35,'_Month Engine'!$B$21:$B$30,0),0)) -> -291262.14 | D35: =-SUMIF('_Month Engine'!$C$5:$DR$5,D$4,INDEX('_Month Engine'!$C:$DR,MATCH("Renovation Capex",'_Month Engine'!$A:$A,0)+MATCH($A35,'_Month Engine'!$B$21:$B$30,0),0)) -> 0 | E35: =-SUMIF('_Month Engine'!$C$5:$DR$5,E$4,INDEX('_Month Engine'!$C:$DR,MATCH("Renovation Capex",'_Month Engine'!$A:$A,0)+MATCH($A35,'_Month Engine'!$B$21:$B$30,0),0)) -> 0 | F35: =-SUMIF('_Month Engine'!$C$5:$DR$5,F$4,INDEX('_Month Engine'!$C:$DR,MATCH("Renovation Capex",'_Month Engine'!$A:$A,0)+MATCH($A35,'_Month Engine'!$B$21:$B$30,0),0)) -> 0 | G35: =-SUMIF('_Month Engine'!$C$5:$DR$5,G$4,INDEX('_Month Engine'!$C:$DR,MATCH("Renovation Capex",'_Month Engine'!$A:$A,0)+MATCH($A35,'_Month Engine'!$B$21:$B$30,0),0)) -> 0 | H35: =-SUMIF('_Month Engine'!$C$5:$DR$5,H$4,INDEX('_Month Engine'!$C:$DR,MATCH("Renovation Capex",'_Month Engine'!$A:$A,0)+MATCH($A35,'_Month Engine'!$B$21:$B$30,0),0)) -> 0 | I35: =-SUMIF('_Month Engine'!$C$5:$DR$5,I$4,INDEX('_Month Engine'!$C:$DR,MATCH("Renovation Capex",'_Month Engine'!$A:$A,0)+MATCH($A35,'_Month Engine'!$B$21:$B$30,0),0)) -> 0 | J35: =-SUMIF('_Month Engine'!$C$5:$DR$5,J$4,INDEX('_Month Engine'!$C:$DR,MATCH("Renovation Capex",'_Month Engine'!$A:$A,0)+MATCH($A35,'_Month Engine'!$B$21:$B$30,0),0)) -> 0 | ... L35: =-SUMIF('_Month Engine'!$C$5:$DR$5,L$4,INDEX('_Month Engine'!$C:$DR,MATCH("Renovation Capex",'_Month Engine'!$A:$A,0)+MATCH($A35,'_Month Engine'!$B$21:$B$30,0),0)) -> 0
A36: 4 | B36: {=IF(Properties!$D$9=0,"",INDEX(Properties!$E:$E,$A36+5))} -> Casa Montana Lote 2 (Samuel Gaviria House) | C36: =-SUMIF('_Month Engine'!$C$5:$DR$5,C$4,INDEX('_Month Engine'!$C:$DR,MATCH("Renovation Capex",'_Month Engine'!$A:$A,0)+MATCH($A36,'_Month Engine'!$B$21:$B$30,0),0)) -> -458468.18 | D36: =-SUMIF('_Month Engine'!$C$5:$DR$5,D$4,INDEX('_Month Engine'!$C:$DR,MATCH("Renovation Capex",'_Month Engine'!$A:$A,0)+MATCH($A36,'_Month Engine'!$B$21:$B$30,0),0)) -> -91693.635 | E36: =-SUMIF('_Month Engine'!$C$5:$DR$5,E$4,INDEX('_Month Engine'!$C:$DR,MATCH("Renovation Capex",'_Month Engine'!$A:$A,0)+MATCH($A36,'_Month Engine'!$B$21:$B$30,0),0)) -> 0 | F36: =-SUMIF('_Month Engine'!$C$5:$DR$5,F$4,INDEX('_Month Engine'!$C:$DR,MATCH("Renovation Capex",'_Month Engine'!$A:$A,0)+MATCH($A36,'_Month Engine'!$B$21:$B$30,0),0)) -> 0 | G36: =-SUMIF('_Month Engine'!$C$5:$DR$5,G$4,INDEX('_Month Engine'!$C:$DR,MATCH("Renovation Capex",'_Month Engine'!$A:$A,0)+MATCH($A36,'_Month Engine'!$B$21:$B$30,0),0)) -> 0 | H36: =-SUMIF('_Month Engine'!$C$5:$DR$5,H$4,INDEX('_Month Engine'!$C:$DR,MATCH("Renovation Capex",'_Month Engine'!$A:$A,0)+MATCH($A36,'_Month Engine'!$B$21:$B$30,0),0)) -> 0 | I36: =-SUMIF('_Month Engine'!$C$5:$DR$5,I$4,INDEX('_Month Engine'!$C:$DR,MATCH("Renovation Capex",'_Month Engine'!$A:$A,0)+MATCH($A36,'_Month Engine'!$B$21:$B$30,0),0)) -> 0 | J36: =-SUMIF('_Month Engine'!$C$5:$DR$5,J$4,INDEX('_Month Engine'!$C:$DR,MATCH("Renovation Capex",'_Month Engine'!$A:$A,0)+MATCH($A36,'_Month Engine'!$B$21:$B$30,0),0)) -> 0 | ... L36: =-SUMIF('_Month Engine'!$C$5:$DR$5,L$4,INDEX('_Month Engine'!$C:$DR,MATCH("Renovation Capex",'_Month Engine'!$A:$A,0)+MATCH($A36,'_Month Engine'!$B$21:$B$30,0),0)) -> 0
A37: 5 | B37: {=IF(Properties!$D$10=0,"",INDEX(Properties!$E:$E,$A37+5))} -> Casa Monte Sereno | C37: =-SUMIF('_Month Engine'!$C$5:$DR$5,C$4,INDEX('_Month Engine'!$C:$DR,MATCH("Renovation Capex",'_Month Engine'!$A:$A,0)+MATCH($A37,'_Month Engine'!$B$21:$B$30,0),0)) -> -323624.6 | D37: =-SUMIF('_Month Engine'!$C$5:$DR$5,D$4,INDEX('_Month Engine'!$C:$DR,MATCH("Renovation Capex",'_Month Engine'!$A:$A,0)+MATCH($A37,'_Month Engine'!$B$21:$B$30,0),0)) -> 0 | E37: =-SUMIF('_Month Engine'!$C$5:$DR$5,E$4,INDEX('_Month Engine'!$C:$DR,MATCH("Renovation Capex",'_Month Engine'!$A:$A,0)+MATCH($A37,'_Month Engine'!$B$21:$B$30,0),0)) -> 0 | F37: =-SUMIF('_Month Engine'!$C$5:$DR$5,F$4,INDEX('_Month Engine'!$C:$DR,MATCH("Renovation Capex",'_Month Engine'!$A:$A,0)+MATCH($A37,'_Month Engine'!$B$21:$B$30,0),0)) -> 0 | G37: =-SUMIF('_Month Engine'!$C$5:$DR$5,G$4,INDEX('_Month Engine'!$C:$DR,MATCH("Renovation Capex",'_Month Engine'!$A:$A,0)+MATCH($A37,'_Month Engine'!$B$21:$B$30,0),0)) -> 0 | H37: =-SUMIF('_Month Engine'!$C$5:$DR$5,H$4,INDEX('_Month Engine'!$C:$DR,MATCH("Renovation Capex",'_Month Engine'!$A:$A,0)+MATCH($A37,'_Month Engine'!$B$21:$B$30,0),0)) -> 0 | I37: =-SUMIF('_Month Engine'!$C$5:$DR$5,I$4,INDEX('_Month Engine'!$C:$DR,MATCH("Renovation Capex",'_Month Engine'!$A:$A,0)+MATCH($A37,'_Month Engine'!$B$21:$B$30,0),0)) -> 0 | J37: =-SUMIF('_Month Engine'!$C$5:$DR$5,J$4,INDEX('_Month Engine'!$C:$DR,MATCH("Renovation Capex",'_Month Engine'!$A:$A,0)+MATCH($A37,'_Month Engine'!$B$21:$B$30,0),0)) -> 0 | ... L37: =-SUMIF('_Month Engine'!$C$5:$DR$5,L$4,INDEX('_Month Engine'!$C:$DR,MATCH("Renovation Capex",'_Month Engine'!$A:$A,0)+MATCH($A37,'_Month Engine'!$B$21:$B$30,0),0)) -> 0
A38: 6 | B38: {=IF(Properties!$D$11=0,"",INDEX(Properties!$E:$E,$A38+5))} | C38: =-SUMIF('_Month Engine'!$C$5:$DR$5,C$4,INDEX('_Month Engine'!$C:$DR,MATCH("Renovation Capex",'_Month Engine'!$A:$A,0)+MATCH($A38,'_Month Engine'!$B$21:$B$30,0),0)) -> 0 | D38: =-SUMIF('_Month Engine'!$C$5:$DR$5,D$4,INDEX('_Month Engine'!$C:$DR,MATCH("Renovation Capex",'_Month Engine'!$A:$A,0)+MATCH($A38,'_Month Engine'!$B$21:$B$30,0),0)) -> 0 | E38: =-SUMIF('_Month Engine'!$C$5:$DR$5,E$4,INDEX('_Month Engine'!$C:$DR,MATCH("Renovation Capex",'_Month Engine'!$A:$A,0)+MATCH($A38,'_Month Engine'!$B$21:$B$30,0),0)) -> 0 | F38: =-SUMIF('_Month Engine'!$C$5:$DR$5,F$4,INDEX('_Month Engine'!$C:$DR,MATCH("Renovation Capex",'_Month Engine'!$A:$A,0)+MATCH($A38,'_Month Engine'!$B$21:$B$30,0),0)) -> 0 | G38: =-SUMIF('_Month Engine'!$C$5:$DR$5,G$4,INDEX('_Month Engine'!$C:$DR,MATCH("Renovation Capex",'_Month Engine'!$A:$A,0)+MATCH($A38,'_Month Engine'!$B$21:$B$30,0),0)) -> 0 | H38: =-SUMIF('_Month Engine'!$C$5:$DR$5,H$4,INDEX('_Month Engine'!$C:$DR,MATCH("Renovation Capex",'_Month Engine'!$A:$A,0)+MATCH($A38,'_Month Engine'!$B$21:$B$30,0),0)) -> 0 | I38: =-SUMIF('_Month Engine'!$C$5:$DR$5,I$4,INDEX('_Month Engine'!$C:$DR,MATCH("Renovation Capex",'_Month Engine'!$A:$A,0)+MATCH($A38,'_Month Engine'!$B$21:$B$30,0),0)) -> 0 | J38: =-SUMIF('_Month Engine'!$C$5:$DR$5,J$4,INDEX('_Month Engine'!$C:$DR,MATCH("Renovation Capex",'_Month Engine'!$A:$A,0)+MATCH($A38,'_Month Engine'!$B$21:$B$30,0),0)) -> 0 | ... L38: =-SUMIF('_Month Engine'!$C$5:$DR$5,L$4,INDEX('_Month Engine'!$C:$DR,MATCH("Renovation Capex",'_Month Engine'!$A:$A,0)+MATCH($A38,'_Month Engine'!$B$21:$B$30,0),0)) -> 0
A39: 7 | B39: {=IF(Properties!$D$12=0,"",INDEX(Properties!$E:$E,$A39+5))} | C39: =-SUMIF('_Month Engine'!$C$5:$DR$5,C$4,INDEX('_Month Engine'!$C:$DR,MATCH("Renovation Capex",'_Month Engine'!$A:$A,0)+MATCH($A39,'_Month Engine'!$B$21:$B$30,0),0)) -> 0 | D39: =-SUMIF('_Month Engine'!$C$5:$DR$5,D$4,INDEX('_Month Engine'!$C:$DR,MATCH("Renovation Capex",'_Month Engine'!$A:$A,0)+MATCH($A39,'_Month Engine'!$B$21:$B$30,0),0)) -> 0 | E39: =-SUMIF('_Month Engine'!$C$5:$DR$5,E$4,INDEX('_Month Engine'!$C:$DR,MATCH("Renovation Capex",'_Month Engine'!$A:$A,0)+MATCH($A39,'_Month Engine'!$B$21:$B$30,0),0)) -> 0 | F39: =-SUMIF('_Month Engine'!$C$5:$DR$5,F$4,INDEX('_Month Engine'!$C:$DR,MATCH("Renovation Capex",'_Month Engine'!$A:$A,0)+MATCH($A39,'_Month Engine'!$B$21:$B$30,0),0)) -> 0 | G39: =-SUMIF('_Month Engine'!$C$5:$DR$5,G$4,INDEX('_Month Engine'!$C:$DR,MATCH("Renovation Capex",'_Month Engine'!$A:$A,0)+MATCH($A39,'_Month Engine'!$B$21:$B$30,0),0)) -> 0 | H39: =-SUMIF('_Month Engine'!$C$5:$DR$5,H$4,INDEX('_Month Engine'!$C:$DR,MATCH("Renovation Capex",'_Month Engine'!$A:$A,0)+MATCH($A39,'_Month Engine'!$B$21:$B$30,0),0)) -> 0 | I39: =-SUMIF('_Month Engine'!$C$5:$DR$5,I$4,INDEX('_Month Engine'!$C:$DR,MATCH("Renovation Capex",'_Month Engine'!$A:$A,0)+MATCH($A39,'_Month Engine'!$B$21:$B$30,0),0)) -> 0 | J39: =-SUMIF('_Month Engine'!$C$5:$DR$5,J$4,INDEX('_Month Engine'!$C:$DR,MATCH("Renovation Capex",'_Month Engine'!$A:$A,0)+MATCH($A39,'_Month Engine'!$B$21:$B$30,0),0)) -> 0 | ... L39: =-SUMIF('_Month Engine'!$C$5:$DR$5,L$4,INDEX('_Month Engine'!$C:$DR,MATCH("Renovation Capex",'_Month Engine'!$A:$A,0)+MATCH($A39,'_Month Engine'!$B$21:$B$30,0),0)) -> 0
A40: 8 | B40: {=IF(Properties!$D$13=0,"",INDEX(Properties!$E:$E,$A40+5))} | C40: =-SUMIF('_Month Engine'!$C$5:$DR$5,C$4,INDEX('_Month Engine'!$C:$DR,MATCH("Renovation Capex",'_Month Engine'!$A:$A,0)+MATCH($A40,'_Month Engine'!$B$21:$B$30,0),0)) -> 0 | D40: =-SUMIF('_Month Engine'!$C$5:$DR$5,D$4,INDEX('_Month Engine'!$C:$DR,MATCH("Renovation Capex",'_Month Engine'!$A:$A,0)+MATCH($A40,'_Month Engine'!$B$21:$B$30,0),0)) -> 0 | E40: =-SUMIF('_Month Engine'!$C$5:$DR$5,E$4,INDEX('_Month Engine'!$C:$DR,MATCH("Renovation Capex",'_Month Engine'!$A:$A,0)+MATCH($A40,'_Month Engine'!$B$21:$B$30,0),0)) -> 0 | F40: =-SUMIF('_Month Engine'!$C$5:$DR$5,F$4,INDEX('_Month Engine'!$C:$DR,MATCH("Renovation Capex",'_Month Engine'!$A:$A,0)+MATCH($A40,'_Month Engine'!$B$21:$B$30,0),0)) -> 0 | G40: =-SUMIF('_Month Engine'!$C$5:$DR$5,G$4,INDEX('_Month Engine'!$C:$DR,MATCH("Renovation Capex",'_Month Engine'!$A:$A,0)+MATCH($A40,'_Month Engine'!$B$21:$B$30,0),0)) -> 0 | H40: =-SUMIF('_Month Engine'!$C$5:$DR$5,H$4,INDEX('_Month Engine'!$C:$DR,MATCH("Renovation Capex",'_Month Engine'!$A:$A,0)+MATCH($A40,'_Month Engine'!$B$21:$B$30,0),0)) -> 0 | I40: =-SUMIF('_Month Engine'!$C$5:$DR$5,I$4,INDEX('_Month Engine'!$C:$DR,MATCH("Renovation Capex",'_Month Engine'!$A:$A,0)+MATCH($A40,'_Month Engine'!$B$21:$B$30,0),0)) -> 0 | J40: =-SUMIF('_Month Engine'!$C$5:$DR$5,J$4,INDEX('_Month Engine'!$C:$DR,MATCH("Renovation Capex",'_Month Engine'!$A:$A,0)+MATCH($A40,'_Month Engine'!$B$21:$B$30,0),0)) -> 0 | ... L40: =-SUMIF('_Month Engine'!$C$5:$DR$5,L$4,INDEX('_Month Engine'!$C:$DR,MATCH("Renovation Capex",'_Month Engine'!$A:$A,0)+MATCH($A40,'_Month Engine'!$B$21:$B$30,0),0)) -> 0
A41: 9 | B41: {=IF(Properties!$D$14=0,"",INDEX(Properties!$E:$E,$A41+5))} | C41: =-SUMIF('_Month Engine'!$C$5:$DR$5,C$4,INDEX('_Month Engine'!$C:$DR,MATCH("Renovation Capex",'_Month Engine'!$A:$A,0)+MATCH($A41,'_Month Engine'!$B$21:$B$30,0),0)) -> 0 | D41: =-SUMIF('_Month Engine'!$C$5:$DR$5,D$4,INDEX('_Month Engine'!$C:$DR,MATCH("Renovation Capex",'_Month Engine'!$A:$A,0)+MATCH($A41,'_Month Engine'!$B$21:$B$30,0),0)) -> 0 | E41: =-SUMIF('_Month Engine'!$C$5:$DR$5,E$4,INDEX('_Month Engine'!$C:$DR,MATCH("Renovation Capex",'_Month Engine'!$A:$A,0)+MATCH($A41,'_Month Engine'!$B$21:$B$30,0),0)) -> 0 | F41: =-SUMIF('_Month Engine'!$C$5:$DR$5,F$4,INDEX('_Month Engine'!$C:$DR,MATCH("Renovation Capex",'_Month Engine'!$A:$A,0)+MATCH($A41,'_Month Engine'!$B$21:$B$30,0),0)) -> 0 | G41: =-SUMIF('_Month Engine'!$C$5:$DR$5,G$4,INDEX('_Month Engine'!$C:$DR,MATCH("Renovation Capex",'_Month Engine'!$A:$A,0)+MATCH($A41,'_Month Engine'!$B$21:$B$30,0),0)) -> 0 | H41: =-SUMIF('_Month Engine'!$C$5:$DR$5,H$4,INDEX('_Month Engine'!$C:$DR,MATCH("Renovation Capex",'_Month Engine'!$A:$A,0)+MATCH($A41,'_Month Engine'!$B$21:$B$30,0),0)) -> 0 | I41: =-SUMIF('_Month Engine'!$C$5:$DR$5,I$4,INDEX('_Month Engine'!$C:$DR,MATCH("Renovation Capex",'_Month Engine'!$A:$A,0)+MATCH($A41,'_Month Engine'!$B$21:$B$30,0),0)) -> 0 | J41: =-SUMIF('_Month Engine'!$C$5:$DR$5,J$4,INDEX('_Month Engine'!$C:$DR,MATCH("Renovation Capex",'_Month Engine'!$A:$A,0)+MATCH($A41,'_Month Engine'!$B$21:$B$30,0),0)) -> 0 | ... L41: =-SUMIF('_Month Engine'!$C$5:$DR$5,L$4,INDEX('_Month Engine'!$C:$DR,MATCH("Renovation Capex",'_Month Engine'!$A:$A,0)+MATCH($A41,'_Month Engine'!$B$21:$B$30,0),0)) -> 0
A42: 10 | B42: {=IF(Properties!$D$15=0,"",INDEX(Properties!$E:$E,$A42+5))} | C42: =-SUMIF('_Month Engine'!$C$5:$DR$5,C$4,INDEX('_Month Engine'!$C:$DR,MATCH("Renovation Capex",'_Month Engine'!$A:$A,0)+MATCH($A42,'_Month Engine'!$B$21:$B$30,0),0)) -> 0 | D42: =-SUMIF('_Month Engine'!$C$5:$DR$5,D$4,INDEX('_Month Engine'!$C:$DR,MATCH("Renovation Capex",'_Month Engine'!$A:$A,0)+MATCH($A42,'_Month Engine'!$B$21:$B$30,0),0)) -> 0 | E42: =-SUMIF('_Month Engine'!$C$5:$DR$5,E$4,INDEX('_Month Engine'!$C:$DR,MATCH("Renovation Capex",'_Month Engine'!$A:$A,0)+MATCH($A42,'_Month Engine'!$B$21:$B$30,0),0)) -> 0 | F42: =-SUMIF('_Month Engine'!$C$5:$DR$5,F$4,INDEX('_Month Engine'!$C:$DR,MATCH("Renovation Capex",'_Month Engine'!$A:$A,0)+MATCH($A42,'_Month Engine'!$B$21:$B$30,0),0)) -> 0 | G42: =-SUMIF('_Month Engine'!$C$5:$DR$5,G$4,INDEX('_Month Engine'!$C:$DR,MATCH("Renovation Capex",'_Month Engine'!$A:$A,0)+MATCH($A42,'_Month Engine'!$B$21:$B$30,0),0)) -> 0 | H42: =-SUMIF('_Month Engine'!$C$5:$DR$5,H$4,INDEX('_Month Engine'!$C:$DR,MATCH("Renovation Capex",'_Month Engine'!$A:$A,0)+MATCH($A42,'_Month Engine'!$B$21:$B$30,0),0)) -> 0 | I42: =-SUMIF('_Month Engine'!$C$5:$DR$5,I$4,INDEX('_Month Engine'!$C:$DR,MATCH("Renovation Capex",'_Month Engine'!$A:$A,0)+MATCH($A42,'_Month Engine'!$B$21:$B$30,0),0)) -> 0 | J42: =-SUMIF('_Month Engine'!$C$5:$DR$5,J$4,INDEX('_Month Engine'!$C:$DR,MATCH("Renovation Capex",'_Month Engine'!$A:$A,0)+MATCH($A42,'_Month Engine'!$B$21:$B$30,0),0)) -> 0 | ... L42: =-SUMIF('_Month Engine'!$C$5:$DR$5,L$4,INDEX('_Month Engine'!$C:$DR,MATCH("Renovation Capex",'_Month Engine'!$A:$A,0)+MATCH($A42,'_Month Engine'!$B$21:$B$30,0),0)) -> 0
B43: Renovation & expansion works | C43: =SUM(C33:C42) -> -1804746.5 | D43: =SUM(D33:D42) -> -91693.635 | E43: =SUM(E33:E42) -> 0 | F43: =SUM(F33:F42) -> 0 | G43: =SUM(G33:G42) -> 0 | H43: =SUM(H33:H42) -> 0 | I43: =SUM(I33:I42) -> 0 | J43: =SUM(J33:J42) -> 0 | ... L43: =SUM(L33:L42) -> 0
B44: Net Cash from Investing Activities | C44: =C32+C43 -> -6480272.4 | D44: =D32+D43 -> -91693.635 | E44: =E32+E43 -> 0 | F44: =F32+F43 -> 0 | G44: =G32+G43 -> 0 | H44: =H32+H43 -> 0 | I44: =I32+I43 -> 0 | J44: =J32+J43 -> 0 | ... L44: =L32+L43 -> 0
B46: Cash Flow from Financing Activities
B47: Equity capital called (per acquisition schedule) | C47: {=MIN(Input!$C$37-SUM($B47:B47),MAX(0,C56-(C53+(C19-(SUMPRODUCT(Properties!$D$6:$D$15*(ROUNDUP(Properties!$U$6:$U$15/'_IRR Engine'!$Q$7,0)=C$4)*Properties!$AB$6:$AB$15)-'Income Statement'!C152))+C44)))*(C$4<=Input!$C$57)} -> 6630682.3 | D47: {=MIN(Input!$C$37-SUM($B47:C47),MAX(0,D56-(D53+(D19-(SUMPRODUCT(Properties!$D$6:$D$15*(ROUNDUP(Properties!$U$6:$U$15/'_IRR Engine'!$Q$7,0)=D$4)*Properties!$AB$6:$AB$15)-'Income Statement'!D152))+D44)))*(D$4<=Input!$C$57)} -> 84829.977 | E47: {=MIN(Input!$C$37-SUM($B47:D47),MAX(0,E56-(E53+(E19-(SUMPRODUCT(Properties!$D$6:$D$15*(ROUNDUP(Properties!$U$6:$U$15/'_IRR Engine'!$Q$7,0)=E$4)*Properties!$AB$6:$AB$15)-'Income Statement'!E152))+E44)))*(E$4<=Input!$C$57)} -> 0 | F47: {=MIN(Input!$C$37-SUM($B47:E47),MAX(0,F56-(F53+(F19-(SUMPRODUCT(Properties!$D$6:$D$15*(ROUNDUP(Properties!$U$6:$U$15/'_IRR Engine'!$Q$7,0)=F$4)*Properties!$AB$6:$AB$15)-'Income Statement'!F152))+F44)))*(F$4<=Input!$C$57)} -> 4287.9994 | G47: {=MIN(Input!$C$37-SUM($B47:F47),MAX(0,G56-(G53+(G19-(SUMPRODUCT(Properties!$D$6:$D$15*(ROUNDUP(Properties!$U$6:$U$15/'_IRR Engine'!$Q$7,0)=G$4)*Properties!$AB$6:$AB$15)-'Income Statement'!G152))+G44)))*(G$4<=Input!$C$57)} -> 0 | H47: {=MIN(Input!$C$37-SUM($B47:G47),MAX(0,H56-(H53+(H19-(SUMPRODUCT(Properties!$D$6:$D$15*(ROUNDUP(Properties!$U$6:$U$15/'_IRR Engine'!$Q$7,0)=H$4)*Properties!$AB$6:$AB$15)-'Income Statement'!H152))+H44)))*(H$4<=Input!$C$57)} -> 0 | I47: {=MIN(Input!$C$37-SUM($B47:H47),MAX(0,I56-(I53+(I19-(SUMPRODUCT(Properties!$D$6:$D$15*(ROUNDUP(Properties!$U$6:$U$15/'_IRR Engine'!$Q$7,0)=I$4)*Properties!$AB$6:$AB$15)-'Income Statement'!I152))+I44)))*(I$4<=Input!$C$57)} -> 0 | J47: {=MIN(Input!$C$37-SUM($B47:I47),MAX(0,J56-(J53+(J19-(SUMPRODUCT(Properties!$D$6:$D$15*(ROUNDUP(Properties!$U$6:$U$15/'_IRR Engine'!$Q$7,0)=J$4)*Properties!$AB$6:$AB$15)-'Income Statement'!J152))+J44)))*(J$4<=Input!$C$57)} -> 0 | ... L47: {=MIN(Input!$C$37-SUM($B47:K47),MAX(0,L56-(L53+(L19-(SUMPRODUCT(Properties!$D$6:$D$15*(ROUNDUP(Properties!$U$6:$U$15/'_IRR Engine'!$Q$7,0)=L$4)*Properties!$AB$6:$AB$15)-'Income Statement'!L152))+L44)))*(L$4<=Input!$C$57)} -> 0
B48: Distributions to Equity Investors (after carry) | C48: =-'Investor Return'!C11 -> 0 | D48: =-'Investor Return'!D11 -> 0 | E48: =-'Investor Return'!E11 -> -5057197.2 | F48: =-'Investor Return'!F11 -> -4589277.4 | G48: =-'Investor Return'!G11 -> 0 | H48: =-'Investor Return'!H11 -> 0 | I48: =-'Investor Return'!I11 -> 0 | J48: =-'Investor Return'!J11 -> 0 | ... L48: =-'Investor Return'!L11 -> 0
B49: Carry distributions to Managing Partner (KIT Capital) | C49: ='Investor Return'!C10 -> 0 | D49: ='Investor Return'!D10 -> 0 | E49: ='Investor Return'!E10 -> 0 | F49: ='Investor Return'!F10 -> -731668.59 | G49: ='Investor Return'!G10 -> 0 | H49: ='Investor Return'!H10 -> 0 | I49: ='Investor Return'!I10 -> 0 | J49: ='Investor Return'!J10 -> 0 | ... L49: ='Investor Return'!L10 -> 0
B50: Net Cash from Financing Activities | C50: =C47+C48+C49 -> 6630682.3 | D50: =D47+D48+D49 -> 84829.977 | E50: =E47+E48+E49 -> -5057197.2 | F50: =F47+F48+F49 -> -5316658 | G50: =G47+G48+G49 -> 0 | H50: =H47+H48+H49 -> 0 | I50: =I47+I48+I49 -> 0 | J50: =J47+J48+J49 -> 0 | ... L50: =L47+L48+L49 -> 0
B52: Net Change in Cash | C52: =C19+C44+C50 -> 24326.267 | D52: =D19+D44+D50 -> -4895.3729 | E52: =E19+E44+E50 -> -12861.655 | F52: =F19+F44+F50 -> -6569.2389 | G52: =G19+G44+G50 -> 0 | H52: =H19+H44+H50 -> 0 | I52: =I19+I44+I50 -> 0 | J52: =J19+J44+J50 -> 0 | ... L52: =L19+L44+L50 -> 0
B53: Beginning cash | C53: =IF(C$4=1,0,B54) -> 0 | D53: =IF(D$4=1,0,C54) -> 24326.267 | E53: =IF(E$4=1,0,D54) -> 19430.894 | F53: =IF(F$4=1,0,E54) -> 6569.2389 | G53: =IF(G$4=1,0,F54) -> -4.2200554e-10 | H53: =IF(H$4=1,0,G54) -> -4.2200554e-10 | I53: =IF(I$4=1,0,H54) -> -4.2200554e-10 | J53: =IF(J$4=1,0,I54) -> -4.2200554e-10 | ... L53: =IF(L$4=1,0,K54) -> -4.2200554e-10
B54: Ending Cash | C54: =C52+C53 -> 24326.267 | D54: =D52+D53 -> 19430.894 | E54: =E52+E53 -> 6569.2389 | F54: =F52+F53 -> -4.2200554e-10 | G54: =G52+G53 -> -4.2200554e-10 | H54: =H52+H53 -> -4.2200554e-10 | I54: =I52+I53 -> -4.2200554e-10 | J54: =J52+J53 -> -4.2200554e-10 | ... L54: =L52+L53 -> -4.2200554e-10
B55: Memo: cash available before distributions | C55: =C53+C19+C44+C47 -> 24326.267 | D55: =D53+D19+D44+D47 -> 19430.894 | E55: =E53+E19+E44+E47 -> 5063766.4 | F55: =F53+F19+F44+F47 -> 5320946 | G55: =G53+G19+G44+G47 -> -4.2200554e-10 | H55: =H53+H19+H44+H47 -> -4.2200554e-10 | I55: =I53+I19+I44+I47 -> -4.2200554e-10 | J55: =J53+J19+J44+J47 -> -4.2200554e-10 | ... L55: =L53+L19+L44+L47 -> -4.2200554e-10
B56: Memo: working-capital reserve target (next-12-months fund G&A; zero at final exit) | C56: {=IF(C$4>=Input!$C$57,0,Input!$C$39/12*INDEX('Income Statement'!$C$144:$L$144,C$4+1))} -> 24326.267 | D56: {=IF(D$4>=Input!$C$57,0,Input!$C$39/12*INDEX('Income Statement'!$C$144:$L$144,D$4+1))} -> 19430.894 | E56: {=IF(E$4>=Input!$C$57,0,Input!$C$39/12*INDEX('Income Statement'!$C$144:$L$144,E$4+1))} -> 6569.2345 | F56: {=IF(F$4>=Input!$C$57,0,Input!$C$39/12*INDEX('Income Statement'!$C$144:$L$144,F$4+1))} -> 0 | G56: {=IF(G$4>=Input!$C$57,0,Input!$C$39/12*INDEX('Income Statement'!$C$144:$L$144,G$4+1))} -> 0 | H56: {=IF(H$4>=Input!$C$57,0,Input!$C$39/12*INDEX('Income Statement'!$C$144:$L$144,H$4+1))} -> 0 | I56: {=IF(I$4>=Input!$C$57,0,Input!$C$39/12*INDEX('Income Statement'!$C$144:$L$144,I$4+1))} -> 0 | J56: {=IF(J$4>=Input!$C$57,0,Input!$C$39/12*INDEX('Income Statement'!$C$144:$L$144,J$4+1))} -> 0 | ... L56: {=IF(L$4>=Input!$C$57,0,Input!$C$39/12*INDEX('Income Statement'!$C$144:$L$144,L$4+1))} -> 0
B58: {="Direct-Method Memo (expand for detail) — ties to net change in cash: "&IF(SUMPRODUCT(ABS($C$68:$L$68))<1,"OK","CHECK")} -> Direct-Method Memo (expand for detail) — ties to net change in cash: OK
B59: Rental revenue received | C59: ='Income Statement'!C7 -> 84225.675 | D59: ='Income Statement'!D7 -> 308211.84 | E59: ='Income Statement'!E7 -> 210510.48 | F59: ='Income Statement'!F7 -> 40478.989 | G59: ='Income Statement'!G7 -> 0 | H59: ='Income Statement'!H7 -> 0 | I59: ='Income Statement'!I7 -> 0 | J59: ='Income Statement'!J7 -> 0 | ... L59: ='Income Statement'!L7 -> 0
B60: Property sales, net of selling costs | C60: ='Income Statement'!C18-'Income Statement'!C108 -> 0 | D60: ='Income Statement'!D18-'Income Statement'!D108 -> 0 | E60: ='Income Statement'!E18-'Income Statement'!E108 -> 5335741.9 | F60: ='Income Statement'!F18-'Income Statement'!F108 -> 5608846.5 | G60: ='Income Statement'!G18-'Income Statement'!G108 -> 0 | H60: ='Income Statement'!H18-'Income Statement'!H108 -> 0 | I60: ='Income Statement'!I18-'Income Statement'!I108 -> 0 | J60: ='Income Statement'!J18-'Income Statement'!J108 -> 0 | ... L60: ='Income Statement'!L18-'Income Statement'!L108 -> 0
B61: Capital called | C61: =C47 -> 6630682.3 | D61: =D47 -> 84829.977 | E61: =E47 -> 0 | F61: =F47 -> 4287.9994 | G61: =G47 -> 0 | H61: =H47 -> 0 | I61: =I47 -> 0 | J61: =J47 -> 0 | ... L61: =L47 -> 0
B62: Total cash in | C62: =SUM(C59:C61) -> 6714907.9 | D62: =SUM(D59:D61) -> 393041.82 | E62: =SUM(E59:E61) -> 5546252.4 | F62: =SUM(F59:F61) -> 5653613.5 | G62: =SUM(G59:G61) -> 0 | H62: =SUM(H59:H61) -> 0 | I62: =SUM(I59:I61) -> 0 | J62: =SUM(J59:J61) -> 0 | ... L62: =SUM(L59:L61) -> 0
B63: Acquisitions and renovation capex | C63: =C32+C43 -> -6480272.4 | D63: =D32+D43 -> -91693.635 | E63: =E32+E43 -> 0 | F63: =F32+F43 -> 0 | G63: =G32+G43 -> 0 | H63: =H32+H43 -> 0 | I63: =I32+I43 -> 0 | J63: =J32+J43 -> 0 | ... L63: =L32+L43 -> 0
B64: Operating expenses | C64: =-'Income Statement'!C163 -> -210309.29 | D64: =-'Income Statement'!D163 -> -306243.55 | E64: =-'Income Statement'!E163 -> -221208.57 | F64: =-'Income Statement'!F163 -> -51336.227 | G64: =-'Income Statement'!G163 -> 0 | H64: =-'Income Statement'!H163 -> 0 | I64: =-'Income Statement'!I163 -> 0 | J64: =-'Income Statement'!J163 -> 0 | ... L64: =-'Income Statement'!L163 -> 0
B65: Taxes | C65: =-'Income Statement'!C153 -> 0 | D65: =-'Income Statement'!D153 -> 0 | E65: =-'Income Statement'!E153 -> -280708.27 | F65: =-'Income Statement'!F153 -> -287900.48 | G65: =-'Income Statement'!G153 -> 0 | H65: =-'Income Statement'!H153 -> 0 | I65: =-'Income Statement'!I153 -> 0 | J65: =-'Income Statement'!J153 -> 0 | ... L65: =-'Income Statement'!L153 -> 0
B66: Distributions to Equity Investors and Carry | C66: =C48+C49 -> 0 | D66: =D48+D49 -> 0 | E66: =E48+E49 -> -5057197.2 | F66: =F48+F49 -> -5320946 | G66: =G48+G49 -> 0 | H66: =H48+H49 -> 0 | I66: =I48+I49 -> 0 | J66: =J48+J49 -> 0 | ... L66: =L48+L49 -> 0
B67: Total cash out | C67: =SUM(C63:C66) -> -6690581.7 | D67: =SUM(D63:D66) -> -397937.19 | E67: =SUM(E63:E66) -> -5559114 | F67: =SUM(F63:F66) -> -5660182.7 | G67: =SUM(G63:G66) -> 0 | H67: =SUM(H63:H66) -> 0 | I67: =SUM(I63:I66) -> 0 | J67: =SUM(J63:J66) -> 0 | ... L67: =SUM(L63:L66) -> 0
B68: Net cash flow — memo check vs. Net Change in Cash | C68: =C62+C67-C52 -> 0 | D68: =D62+D67-D52 -> 1.4551915e-11 | E68: =E62+E67-E52 -> 0 | F68: =F62+F67-F52 -> 0 | G68: =G62+G67-G52 -> 0 | H68: =H62+H67-H52 -> 0 | I68: =I62+I67-I52 -> 0 | J68: =J62+J67-J52 -> 0 | ... L68: =L62+L67-L52 -> 0

Sheet Balance Sheet
B1: Dulcinea — Balance Sheet (USD)
B2: Year-end balances, at cost. See Notes to Financials.
B4: Model year | C4: =COLUMN()-2 -> 1 | D4: =COLUMN()-2 -> 2 | E4: =COLUMN()-2 -> 3 | F4: =COLUMN()-2 -> 4 | G4: =COLUMN()-2 -> 5 | H4: =COLUMN()-2 -> 6 | I4: =COLUMN()-2 -> 7 | J4: =COLUMN()-2 -> 8 | ... L4: =COLUMN()-2 -> 10
B5: Period end | C5: =TEXT(EDATE(Input!$C$7,C4*12-1),"mmm-yy") -> Sep-27 | D5: =TEXT(EDATE(Input!$C$7,D4*12-1),"mmm-yy") -> Sep-28 | E5: =TEXT(EDATE(Input!$C$7,E4*12-1),"mmm-yy") -> Sep-29 | F5: =TEXT(EDATE(Input!$C$7,F4*12-1),"mmm-yy") -> Sep-30 | G5: =TEXT(EDATE(Input!$C$7,G4*12-1),"mmm-yy") -> Sep-31 | H5: =TEXT(EDATE(Input!$C$7,H4*12-1),"mmm-yy") -> Sep-32 | I5: =TEXT(EDATE(Input!$C$7,I4*12-1),"mmm-yy") -> Sep-33 | J5: =TEXT(EDATE(Input!$C$7,J4*12-1),"mmm-yy") -> Sep-34 | ... L5: =TEXT(EDATE(Input!$C$7,L4*12-1),"mmm-yy") -> Sep-36
B6: Assets
B7: Cash & equivalents | C7: ='Statement of Cash Flows'!C54 -> 24326.267 | D7: ='Statement of Cash Flows'!D54 -> 19430.894 | E7: ='Statement of Cash Flows'!E54 -> 6569.2389 | F7: ='Statement of Cash Flows'!F54 -> -4.2200554e-10 | G7: ='Statement of Cash Flows'!G54 -> -4.2200554e-10 | H7: ='Statement of Cash Flows'!H54 -> -4.2200554e-10 | I7: ='Statement of Cash Flows'!I54 -> -4.2200554e-10 | J7: ='Statement of Cash Flows'!J54 -> -4.2200554e-10 | ... L7: ='Statement of Cash Flows'!L54 -> -4.2200554e-10
B8: Real estate held for sale (at cost) | C8: {=SUMPRODUCT(('_Month Engine'!$C$5:$DR$5<=C$4)*('_Month Engine'!$C$18:$DR$18+'_Month Engine'!$C$31:$DR$31-'_Month Engine'!$C$83:$DR$83))} -> 6480272.4 | D8: {=SUMPRODUCT(('_Month Engine'!$C$5:$DR$5<=D$4)*('_Month Engine'!$C$18:$DR$18+'_Month Engine'!$C$31:$DR$31-'_Month Engine'!$C$83:$DR$83))} -> 6571966 | E8: {=SUMPRODUCT(('_Month Engine'!$C$5:$DR$5<=E$4)*('_Month Engine'!$C$18:$DR$18+'_Month Engine'!$C$31:$DR$31-'_Month Engine'!$C$83:$DR$83))} -> 3364967.6 | F8: {=SUMPRODUCT(('_Month Engine'!$C$5:$DR$5<=F$4)*('_Month Engine'!$C$18:$DR$18+'_Month Engine'!$C$31:$DR$31-'_Month Engine'!$C$83:$DR$83))} -> -1.8626451e-09 | G8: {=SUMPRODUCT(('_Month Engine'!$C$5:$DR$5<=G$4)*('_Month Engine'!$C$18:$DR$18+'_Month Engine'!$C$31:$DR$31-'_Month Engine'!$C$83:$DR$83))} -> -1.8626451e-09 | H8: {=SUMPRODUCT(('_Month Engine'!$C$5:$DR$5<=H$4)*('_Month Engine'!$C$18:$DR$18+'_Month Engine'!$C$31:$DR$31-'_Month Engine'!$C$83:$DR$83))} -> -1.8626451e-09 | I8: {=SUMPRODUCT(('_Month Engine'!$C$5:$DR$5<=I$4)*('_Month Engine'!$C$18:$DR$18+'_Month Engine'!$C$31:$DR$31-'_Month Engine'!$C$83:$DR$83))} -> -1.8626451e-09 | J8: {=SUMPRODUCT(('_Month Engine'!$C$5:$DR$5<=J$4)*('_Month Engine'!$C$18:$DR$18+'_Month Engine'!$C$31:$DR$31-'_Month Engine'!$C$83:$DR$83))} -> -1.8626451e-09 | ... L8: {=SUMPRODUCT(('_Month Engine'!$C$5:$DR$5<=L$4)*('_Month Engine'!$C$18:$DR$18+'_Month Engine'!$C$31:$DR$31-'_Month Engine'!$C$83:$DR$83))} -> -1.8626451e-09
B9: Lola & Ber Hospitality Brand Company — equity interest (intangible) | C9: =Input!$C$52 -> 0 | D9: =Input!$C$52 -> 0 | E9: =Input!$C$52 -> 0 | F9: =Input!$C$52 -> 0 | G9: =Input!$C$52 -> 0 | H9: =Input!$C$52 -> 0 | I9: =Input!$C$52 -> 0 | J9: =Input!$C$52 -> 0 | ... L9: =Input!$C$52 -> 0
B10: Total Assets | C10: =C7+C8+C9 -> 6504598.7 | D10: =D7+D8+D9 -> 6591396.9 | E10: =E7+E8+E9 -> 3371536.9 | F10: =F7+F8+F9 -> -2.2846507e-09 | G10: =G7+G8+G9 -> -2.2846507e-09 | H10: =H7+H8+H9 -> -2.2846507e-09 | I10: =I7+I8+I9 -> -2.2846507e-09 | J10: =J7+J8+J9 -> -2.2846507e-09 | ... L10: =L7+L8+L9 -> -2.2846507e-09
B12: Liabilities
B13: Debt and payables | C13: =0 -> 0 | D13: =0 -> 0 | E13: =0 -> 0 | F13: =0 -> 0 | G13: =0 -> 0 | H13: =0 -> 0 | I13: =0 -> 0 | J13: =0 -> 0 | ... L13: =0 -> 0
B14: Total Liabilities | C14: =C13 -> 0 | D14: =D13 -> 0 | E14: =E13 -> 0 | F14: =F13 -> 0 | G14: =G13 -> 0 | H14: =H13 -> 0 | I14: =I13 -> 0 | J14: =J13 -> 0 | ... L14: =L13 -> 0
B16: Equity
B17: Contributed capital (cumulative calls) | C17: ='Statement of Cash Flows'!C47 -> 6630682.3 | D17: =C17+'Statement of Cash Flows'!D47 -> 6715512.2 | E17: =D17+'Statement of Cash Flows'!E47 -> 6715512.2 | F17: =E17+'Statement of Cash Flows'!F47 -> 6719800.2 | G17: =F17+'Statement of Cash Flows'!G47 -> 6719800.2 | H17: =G17+'Statement of Cash Flows'!H47 -> 6719800.2 | I17: =H17+'Statement of Cash Flows'!I47 -> 6719800.2 | J17: =I17+'Statement of Cash Flows'!J47 -> 6719800.2 | K17: =J17+'Statement of Cash Flows'!K47 -> 6719800.2 | L17: =K17+'Statement of Cash Flows'!L47 -> 6719800.2
B18: Retained earnings | C18: ='Income Statement'!C155 -> -126083.61 | D18: =C18+'Income Statement'!D155 -> -124115.33 | E18: =D18+'Income Statement'!E155 -> 1713221.8 | F18: =E18+'Income Statement'!F155 -> 3658342.9 | G18: =F18+'Income Statement'!G155 -> 3658342.9 | H18: =G18+'Income Statement'!H155 -> 3658342.9 | I18: =H18+'Income Statement'!I155 -> 3658342.9 | J18: =I18+'Income Statement'!J155 -> 3658342.9 | K18: =J18+'Income Statement'!K155 -> 3658342.9 | L18: =K18+'Income Statement'!L155 -> 3658342.9
B19: Distributions to Equity Investors (cumulative, incl. Carry) | C19: ='Statement of Cash Flows'!C48+'Statement of Cash Flows'!C49 -> 0 | D19: =C19+'Statement of Cash Flows'!D48+'Statement of Cash Flows'!D49 -> 0 | E19: =D19+'Statement of Cash Flows'!E48+'Statement of Cash Flows'!E49 -> -5057197.2 | F19: =E19+'Statement of Cash Flows'!F48+'Statement of Cash Flows'!F49 -> -10378143 | G19: =F19+'Statement of Cash Flows'!G48+'Statement of Cash Flows'!G49 -> -10378143 | H19: =G19+'Statement of Cash Flows'!H48+'Statement of Cash Flows'!H49 -> -10378143 | I19: =H19+'Statement of Cash Flows'!I48+'Statement of Cash Flows'!I49 -> -10378143 | J19: =I19+'Statement of Cash Flows'!J48+'Statement of Cash Flows'!J49 -> -10378143 | K19: =J19+'Statement of Cash Flows'!K48+'Statement of Cash Flows'!K49 -> -10378143 | L19: =K19+'Statement of Cash Flows'!L48+'Statement of Cash Flows'!L49 -> -10378143
B20: Total Equity | C20: =C17+C18+C19 -> 6504598.7 | D20: =D17+D18+D19 -> 6591396.9 | E20: =E17+E18+E19 -> 3371536.9 | F20: =F17+F18+F19 -> 0 | G20: =G17+G18+G19 -> 0 | H20: =H17+H18+H19 -> 0 | I20: =I17+I18+I19 -> 0 | J20: =J17+J18+J19 -> 0 | ... L20: =L17+L18+L19 -> 0
B22: Balance Check (Assets − Liabilities − Equity) | C22: =C10-C14-C20 -> 0 | D22: =D10-D14-D20 -> 0 | E22: =E10-E14-E20 -> 0 | F22: =F10-F14-F20 -> -2.2846507e-09 | G22: =G10-G14-G20 -> -2.2846507e-09 | H22: =H10-H14-H20 -> -2.2846507e-09 | I22: =I10-I14-I20 -> -2.2846507e-09 | J22: =J10-J14-J20 -> -2.2846507e-09 | ... L22: =L10-L14-L20 -> -2.2846507e-09

Sheet Investor Return
B1: Dulcinea — Investor Return Performance (USD)
B2: ="USD · "&TEXT(SUM('Statement of Cash Flows'!C47:L47),"$#,##0")&" of the "&TEXT(Input!$C$37,"$#,##0")&" commitment drawn · every sale distributed, nothing recycled · final exit Year "&TEXT(Input!$C$57,"0") -> USD · $6,719,800 of the $7,000,000 commitment drawn · every sale distributed, nothing recycled · final exit Year 4
B4: Model year | C4: =COLUMN()-2 -> 1 | D4: =COLUMN()-2 -> 2 | E4: =COLUMN()-2 -> 3 | F4: =COLUMN()-2 -> 4 | G4: =COLUMN()-2 -> 5 | H4: =COLUMN()-2 -> 6 | I4: =COLUMN()-2 -> 7 | J4: =COLUMN()-2 -> 8 | ... L4: =COLUMN()-2 -> 10
B5: Period | C5: =TEXT(EDATE(Input!$C$7,(C4-1)*12),"mmm-yy")&" – "&TEXT(EDATE(Input!$C$7,C4*12-1),"mmm-yy") -> Oct-26 – Sep-27 | D5: =TEXT(EDATE(Input!$C$7,(D4-1)*12),"mmm-yy")&" – "&TEXT(EDATE(Input!$C$7,D4*12-1),"mmm-yy") -> Oct-27 – Sep-28 | E5: =TEXT(EDATE(Input!$C$7,(E4-1)*12),"mmm-yy")&" – "&TEXT(EDATE(Input!$C$7,E4*12-1),"mmm-yy") -> Oct-28 – Sep-29 | F5: =TEXT(EDATE(Input!$C$7,(F4-1)*12),"mmm-yy")&" – "&TEXT(EDATE(Input!$C$7,F4*12-1),"mmm-yy") -> Oct-29 – Sep-30 | G5: =TEXT(EDATE(Input!$C$7,(G4-1)*12),"mmm-yy")&" – "&TEXT(EDATE(Input!$C$7,G4*12-1),"mmm-yy") -> Oct-30 – Sep-31 | H5: =TEXT(EDATE(Input!$C$7,(H4-1)*12),"mmm-yy")&" – "&TEXT(EDATE(Input!$C$7,H4*12-1),"mmm-yy") -> Oct-31 – Sep-32 | I5: =TEXT(EDATE(Input!$C$7,(I4-1)*12),"mmm-yy")&" – "&TEXT(EDATE(Input!$C$7,I4*12-1),"mmm-yy") -> Oct-32 – Sep-33 | J5: =TEXT(EDATE(Input!$C$7,(J4-1)*12),"mmm-yy")&" – "&TEXT(EDATE(Input!$C$7,J4*12-1),"mmm-yy") -> Oct-33 – Sep-34 | ... L5: =TEXT(EDATE(Input!$C$7,(L4-1)*12),"mmm-yy")&" – "&TEXT(EDATE(Input!$C$7,L4*12-1),"mmm-yy") -> Oct-35 – Sep-36
B6: Equity Investor Cash Flows
B7: Capital called (per acquisition schedule) | C7: =-'Statement of Cash Flows'!C47 -> -6630682.3 | D7: =-'Statement of Cash Flows'!D47 -> -84829.977 | E7: =-'Statement of Cash Flows'!E47 -> 0 | F7: =-'Statement of Cash Flows'!F47 -> -4287.9994 | G7: =-'Statement of Cash Flows'!G47 -> 0 | H7: =-'Statement of Cash Flows'!H47 -> 0 | I7: =-'Statement of Cash Flows'!I47 -> 0 | J7: =-'Statement of Cash Flows'!J47 -> 0 | ... L7: =-'Statement of Cash Flows'!L47 -> 0
B8: Interim distributions — surplus cash | C8: =ROUND(MAX(0,'Statement of Cash Flows'!C55-'Statement of Cash Flows'!C56),2)*(C$4<=Input!$C$57)*(C$4>=Input!$C$47) -> 0 | D8: =ROUND(MAX(0,'Statement of Cash Flows'!D55-'Statement of Cash Flows'!D56),2)*(D$4<=Input!$C$57)*(D$4>=Input!$C$47) -> 0 | E8: =ROUND(MAX(0,'Statement of Cash Flows'!E55-'Statement of Cash Flows'!E56),2)*(E$4<=Input!$C$57)*(E$4>=Input!$C$47) -> 5057197.2 | F8: =ROUND(MAX(0,'Statement of Cash Flows'!F55-'Statement of Cash Flows'!F56),2)*(F$4<=Input!$C$57)*(F$4>=Input!$C$47) -> 5320946 | G8: =ROUND(MAX(0,'Statement of Cash Flows'!G55-'Statement of Cash Flows'!G56),2)*(G$4<=Input!$C$57)*(G$4>=Input!$C$47) -> 0 | H8: =ROUND(MAX(0,'Statement of Cash Flows'!H55-'Statement of Cash Flows'!H56),2)*(H$4<=Input!$C$57)*(H$4>=Input!$C$47) -> 0 | I8: =ROUND(MAX(0,'Statement of Cash Flows'!I55-'Statement of Cash Flows'!I56),2)*(I$4<=Input!$C$57)*(I$4>=Input!$C$47) -> 0 | J8: =ROUND(MAX(0,'Statement of Cash Flows'!J55-'Statement of Cash Flows'!J56),2)*(J$4<=Input!$C$57)*(J$4>=Input!$C$47) -> 0 | ... L8: =ROUND(MAX(0,'Statement of Cash Flows'!L55-'Statement of Cash Flows'!L56),2)*(L$4<=Input!$C$57)*(L$4>=Input!$C$47) -> 0
B9: Final liquidation distribution | C9: {=IF(C$4=Input!$C$57,INDEX('Statement of Cash Flows'!$C$55:$L$55,Input!$C$57)-INDEX($C$8:$L$8,Input!$C$57),0)} -> 0 | D9: {=IF(D$4=Input!$C$57,INDEX('Statement of Cash Flows'!$C$55:$L$55,Input!$C$57)-INDEX($C$8:$L$8,Input!$C$57),0)} -> 0 | E9: {=IF(E$4=Input!$C$57,INDEX('Statement of Cash Flows'!$C$55:$L$55,Input!$C$57)-INDEX($C$8:$L$8,Input!$C$57),0)} -> 0 | F9: {=IF(F$4=Input!$C$57,INDEX('Statement of Cash Flows'!$C$55:$L$55,Input!$C$57)-INDEX($C$8:$L$8,Input!$C$57),0)} -> 0.00082941446 | G9: {=IF(G$4=Input!$C$57,INDEX('Statement of Cash Flows'!$C$55:$L$55,Input!$C$57)-INDEX($C$8:$L$8,Input!$C$57),0)} -> 0 | H9: {=IF(H$4=Input!$C$57,INDEX('Statement of Cash Flows'!$C$55:$L$55,Input!$C$57)-INDEX($C$8:$L$8,Input!$C$57),0)} -> 0 | I9: {=IF(I$4=Input!$C$57,INDEX('Statement of Cash Flows'!$C$55:$L$55,Input!$C$57)-INDEX($C$8:$L$8,Input!$C$57),0)} -> 0 | J9: {=IF(J$4=Input!$C$57,INDEX('Statement of Cash Flows'!$C$55:$L$55,Input!$C$57)-INDEX($C$8:$L$8,Input!$C$57),0)} -> 0 | ... L9: {=IF(L$4=Input!$C$57,INDEX('Statement of Cash Flows'!$C$55:$L$55,Input!$C$57)-INDEX($C$8:$L$8,Input!$C$57),0)} -> 0
B10: ="Less: Carry to Managing Partner (KIT Capital) — "&TEXT(Input!$C$46,"0%")&" of distributions above returned capital" -> Less: Carry to Managing Partner (KIT Capital) — 20% of distributions above returned capital | C10: =-MAX(0,Input!$C$46*MAX(0,SUM($C$8:C$9)+SUM($C$7:C$7))+SUM($B$10:B10)) -> 0 | D10: =-MAX(0,Input!$C$46*MAX(0,SUM($C$8:D$9)+SUM($C$7:D$7))+SUM($B$10:C10)) -> 0 | E10: =-MAX(0,Input!$C$46*MAX(0,SUM($C$8:E$9)+SUM($C$7:E$7))+SUM($B$10:D10)) -> 0 | F10: =-MAX(0,Input!$C$46*MAX(0,SUM($C$8:F$9)+SUM($C$7:F$7))+SUM($B$10:E10)) -> -731668.59 | G10: =-MAX(0,Input!$C$46*MAX(0,SUM($C$8:G$9)+SUM($C$7:G$7))+SUM($B$10:F10)) -> 0 | H10: =-MAX(0,Input!$C$46*MAX(0,SUM($C$8:H$9)+SUM($C$7:H$7))+SUM($B$10:G10)) -> 0 | I10: =-MAX(0,Input!$C$46*MAX(0,SUM($C$8:I$9)+SUM($C$7:I$7))+SUM($B$10:H10)) -> 0 | J10: =-MAX(0,Input!$C$46*MAX(0,SUM($C$8:J$9)+SUM($C$7:J$7))+SUM($B$10:I10)) -> 0 | ... L10: =-MAX(0,Input!$C$46*MAX(0,SUM($C$8:L$9)+SUM($C$7:L$7))+SUM($B$10:K10)) -> 0
B11: Net distributions to Equity Investors (after carry) | C11: =C8+C9+C10 -> 0 | D11: =D8+D9+D10 -> 0 | E11: =E8+E9+E10 -> 5057197.2 | F11: =F8+F9+F10 -> 4589277.4 | G11: =G8+G9+G10 -> 0 | H11: =H8+H9+H10 -> 0 | I11: =I8+I9+I10 -> 0 | J11: =J8+J9+J10 -> 0 | ... L11: =L8+L9+L10 -> 0
B12: Net Equity Investor Cash Flow | C12: =C7+C11 -> -6630682.3 | D12: =D7+D11 -> -84829.977 | E12: =E7+E11 -> 5057197.2 | F12: =F7+F11 -> 4584989.4 | G12: =G7+G11 -> 0 | H12: =H7+H11 -> 0 | I12: =I7+I11 -> 0 | J12: =J7+J11 -> 0 | ... L12: =L7+L11 -> 0
B13: Cumulative investor cash flow | C13: =C12 -> -6630682.3 | D13: =C13+D12 -> -6715512.2 | E13: =D13+E12 -> -1658315.1 | F13: =E13+F12 -> 2926674.4 | G13: =F13+G12 -> 2926674.4 | H13: =G13+H12 -> 2926674.4 | I13: =H13+I12 -> 2926674.4 | J13: =I13+J12 -> 2926674.4 | K13: =J13+K12 -> 2926674.4 | L13: =K13+L12 -> 2926674.4
B15: Return Metrics
B16: Total capital invested | C16: =SUM('Statement of Cash Flows'!C47:L47) -> 6719800.2
B17: Gross distributions (before carry) | C17: =SUM(C8:L9) -> 10378143
B18: ="Less: Carry to Managing Partner (KIT Capital) — "&TEXT(Input!$C$46,"0%") -> Less: Carry to Managing Partner (KIT Capital) — 20% | C18: =SUM(C10:L10) -> -731668.59
B19: Total distributions to Equity Investors (after carry) | C19: =SUM(C11:L11) -> 9646474.6
B20: Net profit to Equity Investors | C20: =C19-C16 -> 2926674.4
B21: MOIC | C21: =C19/C16 -> 1.43553
B22: Equity Investor IRR | C22: ='_IRR Engine'!$Q$15 -> 0.15722408
B23: Payback (model year) | C23: {=IFERROR(MATCH(TRUE,INDEX($C$13:$L$13>=0,0),0),"Beyond horizon")} -> 4
B24: Equity Investor IRR — annual approximation (reconciliation) | C24: =IRR($C$12:$L$12) -> 0.15942381
B25: Method: see Notes to Financials

Sheet Sources & Uses
B1: Dulcinea — Sources & Uses of Capital (USD)
B2: Deployment of the capital raise. See Notes to Financials.
B4: Sources
B5: Capital commitment (memo — drawn only as acquisitions close) | C5: =Input!$C$37 -> 7000000
B6: Capital called per the acquisition schedule | C6: =SUM('Statement of Cash Flows'!$C$47:$L$47) -> 6719800.2
B7: Shortfall absorbed by reserve / retained proceeds (commitment cap binding) | C7: =$C$16-$C$6 -> 86801.334
B8: Total sources | C8: =$C$6+$C$7 -> 6806601.6
B9: Uses
B10: Property purchases | C10: =SUMPRODUCT(Properties!$D$6:$D$15,Properties!$M$6:$M$15) -> 4561488.7
B11: Closing costs | C11: =SUMPRODUCT(Properties!$D$6:$D$15,Properties!$O$6:$O$15) -> 114037.22
B12: Renovation, design & fit-out works | C12: =SUMPRODUCT(Properties!$D$6:$D$15,Properties!$N$6:$N$15) -> 1896440.1
B13: Dulcinea operating costs — Year 1 runway (incl. ServCo fees) | C13: ='Income Statement'!C163 -> 210309.29
B14: Working capital reserve (Year-1 target: next-12-months fund overheads) | C14: ='Statement of Cash Flows'!$C$56 -> 24326.267
B16: Total uses | C16: =SUM($C$10:$C$14) -> 6806601.6
B18: Presentation tie (sources − uses; zero by construction) | C18: =$C$8-$C$16 -> 0
B20: Commitment Headroom — every acquisition is funded by called capital; exit proceeds are distributed, not recycled
B21: Total capital commitment | C21: =Input!$C$37 -> 7000000
B22: Capital called through final exit | C22: =$C$6 -> 6719800.2
B23: Undrawn commitment (zero = cap binding; shortfall shown in the sources line above) | C23: =$C$21-$C$22 -> 280199.76
B24: Reserve drawn below target at a year-end (shortfall funded from the reserve) | C24: {=MAX(0,MAX(('Statement of Cash Flows'!$C$4:$L$4<Input!$C$57)*('Statement of Cash Flows'!$C$56:$L$56-'Statement of Cash Flows'!$C$54:$L$54)))} -> 0

Sheet Portfolio Analysis
B1: Dulcinea — Portfolio Analysis: Selection, Exit Sensitivity & Buy Box (USD)
B2: ="Selection, exit sensitivity and acquisition criteria for the "&TEXT(SUM(Properties!$D$6:$D$15),"0")&" active properties · USD · TRM COP "&TEXT(Input!$C$5,"#,##0")&" per USD · sensitivity grids centre on the Input base case" -> Selection, exit sensitivity and acquisition criteria for the 5 active properties · USD · TRM COP 3,090 per USD · sensitivity grids centre on the Input base case
B3: Sensitivity steps: | C3: appreciation ± | D3: =Input!$C$149 -> 0.02 | E3: entry discount ± | F3: =Input!$C$150 -> 0.05 | G3: rent ± | H3: =Input!$C$151 -> 2
C4: ="Total Funds Needed — "&TEXT(SUM(Properties!$D$6:$D$15),"0")&" active properties" -> Total Funds Needed — 5 active properties | D4: =SUMPRODUCT(Properties!$D$6:$D$15,Properties!$P$6:$P$15) -> 6571966
G6: Notes
C7: Exit Sensitivity — Market Appreciation (%/yr) → | D7: =Input!$C$55-$D$3 -> 0.058087751 | E7: =Input!$C$55 -> 0.078087751 | F7: =Input!$C$55+$D$3 -> 0.098087751 | G7: N1 | H7: Exit Sensitivity — Entry Discount → | I7: =Input!$I$80-$F$3 -> 0.25 | J7: =Input!$I$80 -> 0.3 | K7: =Input!$I$80+$F$3 -> 0.35
C8: ="Portfolio exit value ("&TEXT(SUM(Properties!$D$6:$D$15),"0")&" active properties)" -> Portfolio exit value (5 active properties) | D8: {=SUMPRODUCT(Properties!$D$6:$D$15,Properties!$P$6:$P$15/(1-Input!$I$80:$I$89)*(1+Input!$G$80:$G$89+(D$7-Input!$C$55))^Properties!$V$6:$V$15)} -> 10841124 | E8: {=SUMPRODUCT(Properties!$D$6:$D$15,Properties!$P$6:$P$15/(1-Input!$I$80:$I$89)*(1+Input!$G$80:$G$89+(E$7-Input!$C$55))^Properties!$V$6:$V$15)} -> 11376911 | F8: {=SUMPRODUCT(Properties!$D$6:$D$15,Properties!$P$6:$P$15/(1-Input!$I$80:$I$89)*(1+Input!$G$80:$G$89+(F$7-Input!$C$55))^Properties!$V$6:$V$15)} -> 11928908 | G8: N2 | H8: Portfolio exit value | I8: 10618450 | J8: =E8 -> 11376911 | K8: 12252058
C9: Implied gross profit on funds needed | D9: =D8/$D$4-1 -> 0.64960138 | E9: =E8/$D$4-1 -> 0.73112748 | F9: =F8/$D$4-1 -> 0.81512023 | G9: N3 | H9: Deal XIRR after tax | I9: 0.17897506 | J9: =E14 -> 0.2081031 | K9: 0.24050116
C10: Deal cash flow t=0 — acquisitions (all-in) | D10: =-$D$4 -> -6571966 | E10: =-$D$4 -> -6571966 | F10: =-$D$4 -> -6571966 | G10: N4 | H10: Fund-level Equity Investor XIRR | I10: 0.13249684 | J10: =E17 -> 0.15722408 | K10: 0.18494726
C11: ="t=1 — stabilized NOI, months "&TEXT(SUMPRODUCT(Properties!$D$6:$D$15,Properties!$R$6:$R$15)/SUM(Properties!$D$6:$D$15)+1,"0")&"-12" -> t=1 — stabilized NOI, months 7-12 | D11: =SUMPRODUCT(Properties!$D$6:$D$15,Properties!$X$6:$X$15)*MAX(0,12-SUMPRODUCT(Properties!$D$6:$D$15,Properties!$R$6:$R$15)/SUM(Properties!$D$6:$D$15))/12 -> 48809.722 | E11: =SUMPRODUCT(Properties!$D$6:$D$15,Properties!$X$6:$X$15)*MAX(0,12-SUMPRODUCT(Properties!$D$6:$D$15,Properties!$R$6:$R$15)/SUM(Properties!$D$6:$D$15))/12 -> 48809.722 | F11: =SUMPRODUCT(Properties!$D$6:$D$15,Properties!$X$6:$X$15)*MAX(0,12-SUMPRODUCT(Properties!$D$6:$D$15,Properties!$R$6:$R$15)/SUM(Properties!$D$6:$D$15))/12 -> 48809.722 | G11: N5 | H11: Equity Investor MOIC | I11: 1.3616952 | J11: ='Investor Return'!C21 -> 1.43553 | K11: 1.5207239
C12: t=2 — full-year NOI + exit net of selling costs | D12: =SUMPRODUCT(Properties!$D$6:$D$15,Properties!$X$6:$X$15)*(1+Input!$C$8)+D8*(1-Input!$C$15) -> 10528733 | E12: =SUMPRODUCT(Properties!$D$6:$D$15,Properties!$X$6:$X$15)*(1+Input!$C$8)+E8*(1-Input!$C$15) -> 11044160 | F12: =SUMPRODUCT(Properties!$D$6:$D$15,Properties!$X$6:$X$15)*(1+Input!$C$8)+F8*(1-Input!$C$15) -> 11575182 | G12: N6 | H12: Grey-shaded 25% and 35% columns are pasted from a manual sweep of Input!I80:I84 (all five properties set to each discount) on 2026-09-25 after the fee, pricing and tax changes; re-run if inputs change. 30% column is live.
C13: Portfolio deal-level XIRR (monthly dated flows, excl. fund overheads) | D13: {=_xlfn.LET(_xlpm.zact,TRANSPOSE(Properties!$D$6:$D$15),_xlpm.zqtr,TRANSPOSE(Properties!$Q$6:$Q$15),_xlpm.zwks,TRANSPOSE(Properties!$R$6:$R$15),_xlpm.zrst,TRANSPOSE(Properties!$T$6:$T$15),_xlpm.zsel,TRANSPOSE(Properties!$U$6:$U$15),_xlpm.zbas,TRANSPOSE(Properties!$P$6:$P$15),_xlpm.zcap,TRANSPOSE(Properties!$N$6:$N$15),_xlpm.zbuy,TRANSPOSE(Properties!$M$6:$M$15+Properties!$O$6:$O$15),_xlpm.zrnt,TRANSPOSE(Properties!$Y$6:$Y$15),_xlpm.zhld,TRANSPOSE(Properties!$V$6:$V$15),_xlpm.zpre,TRANSPOSE(Input!$C$80:$C$89),_xlpm.zhoa,TRANSPOSE(Input!$D$80:$D$89+Input!$E$80:$E$89),_xlpm.zmy,'_IRR Engine'!$Q$7,_xlpm.zmq,1,_xlpm.zcop,'_IRR Engine'!$Q$9,_xlpm.zdisc,TRANSPOSE(Input!$I$80:$I$89),_xlpm.zgrow,TRANSPOSE(Input!$G$80:$G$89)+(D$7-Input!$C$55),_xlpm.zscale,1,_xlpm.zmon,_xlfn.SEQUENCE('_IRR Engine'!$Q$5),_xlpm.zq,ROUNDUP(_xlpm.zmon/_xlpm.zmq,0),_xlpm.zy,ROUNDUP(_xlpm.zmon/_xlpm.zmy,0),_xlpm.zaccm,(_xlpm.zqtr-1)*_xlpm.zmq+1,_xlpm.zrentm,(_xlpm.zrst-1)*_xlpm.zmq+1,_xlpm.zsalem,(_xlpm.zsel-1)*_xlpm.zmq+1,_xlpm.zowned,(_xlpm.zmon>=_xlpm.zaccm)*(_xlpm.zmon<_xlpm.zsalem),_xlpm.zcapon,(_xlpm.zmon>=_xlpm.zaccm)*(_xlpm.zmon<=_xlpm.zaccm-1+_xlpm.zmq*_xlpm.zwks),_xlpm.zrenting,(_xlpm.zmon>=_xlpm.zrentm)*(_xlpm.zmon<_xlpm.zsalem),_xlpm.zratio,(_xlpm.zq-_xlpm.zrst+1)/Input!$C$11,_xlpm.zramp,_xlpm.zratio-(_xlpm.zratio-1)*(_xlpm.zratio>1),_xlpm.zownfx,_xlpm.zbas*_xlpm.zpre+_xlpm.zhoa*_xlpm.zmy*_xlpm.zcop/Input!$C$5,_xlpm.zrentfx,_xlpm.zbas*(Input!$C$19+Input!$C$18)+Input!$C$32*_xlpm.zmy,_xlpm.zrentnet,_xlpm.zrnt*_xlpm.zscale*(1-Input!$C$20-Input!$C$21-Input!$C$31),_xlpm.znet,_xlpm.zbas/(1-_xlpm.zdisc)*(1+_xlpm.zgrow)^_xlpm.zhld*(1-Input!$C$15),_xlpm.zmat,_xlpm.zact*(-(_xlpm.zmon=_xlpm.zaccm)*_xlpm.zbuy-_xlpm.zcapon*_xlpm.zcap/(_xlpm.zmq*(_xlpm.zwks+(_xlpm.zwks=0)))+_xlpm.zrenting*_xlpm.zramp*_xlpm.zrentnet/_xlpm.zmy*(1+Input!$C$8)^(_xlpm.zy-1)-_xlpm.zowned*_xlpm.zownfx/_xlpm.zmy-_xlpm.zrenting*_xlpm.zrentfx/_xlpm.zmy+(_xlpm.zmon=_xlpm.zsalem)*_xlpm.znet),XIRR(MMULT(_xlpm.zmat,_xlfn.SEQUENCE('_IRR Engine'!$Q$6,1,1,0)),EOMONTH(Input!$C$7,_xlpm.zmon-1)))} -> 0.21078413 | E13: {=_xlfn.LET(_xlpm.zact,TRANSPOSE(Properties!$D$6:$D$15),_xlpm.zqtr,TRANSPOSE(Properties!$Q$6:$Q$15),_xlpm.zwks,TRANSPOSE(Properties!$R$6:$R$15),_xlpm.zrst,TRANSPOSE(Properties!$T$6:$T$15),_xlpm.zsel,TRANSPOSE(Properties!$U$6:$U$15),_xlpm.zbas,TRANSPOSE(Properties!$P$6:$P$15),_xlpm.zcap,TRANSPOSE(Properties!$N$6:$N$15),_xlpm.zbuy,TRANSPOSE(Properties!$M$6:$M$15+Properties!$O$6:$O$15),_xlpm.zrnt,TRANSPOSE(Properties!$Y$6:$Y$15),_xlpm.zhld,TRANSPOSE(Properties!$V$6:$V$15),_xlpm.zpre,TRANSPOSE(Input!$C$80:$C$89),_xlpm.zhoa,TRANSPOSE(Input!$D$80:$D$89+Input!$E$80:$E$89),_xlpm.zmy,'_IRR Engine'!$Q$7,_xlpm.zmq,1,_xlpm.zcop,'_IRR Engine'!$Q$9,_xlpm.zdisc,TRANSPOSE(Input!$I$80:$I$89),_xlpm.zgrow,TRANSPOSE(Input!$G$80:$G$89)+(E$7-Input!$C$55),_xlpm.zscale,1,_xlpm.zmon,_xlfn.SEQUENCE('_IRR Engine'!$Q$5),_xlpm.zq,ROUNDUP(_xlpm.zmon/_xlpm.zmq,0),_xlpm.zy,ROUNDUP(_xlpm.zmon/_xlpm.zmy,0),_xlpm.zaccm,(_xlpm.zqtr-1)*_xlpm.zmq+1,_xlpm.zrentm,(_xlpm.zrst-1)*_xlpm.zmq+1,_xlpm.zsalem,(_xlpm.zsel-1)*_xlpm.zmq+1,_xlpm.zowned,(_xlpm.zmon>=_xlpm.zaccm)*(_xlpm.zmon<_xlpm.zsalem),_xlpm.zcapon,(_xlpm.zmon>=_xlpm.zaccm)*(_xlpm.zmon<=_xlpm.zaccm-1+_xlpm.zmq*_xlpm.zwks),_xlpm.zrenting,(_xlpm.zmon>=_xlpm.zrentm)*(_xlpm.zmon<_xlpm.zsalem),_xlpm.zratio,(_xlpm.zq-_xlpm.zrst+1)/Input!$C$11,_xlpm.zramp,_xlpm.zratio-(_xlpm.zratio-1)*(_xlpm.zratio>1),_xlpm.zownfx,_xlpm.zbas*_xlpm.zpre+_xlpm.zhoa*_xlpm.zmy*_xlpm.zcop/Input!$C$5,_xlpm.zrentfx,_xlpm.zbas*(Input!$C$19+Input!$C$18)+Input!$C$32*_xlpm.zmy,_xlpm.zrentnet,_xlpm.zrnt*_xlpm.zscale*(1-Input!$C$20-Input!$C$21-Input!$C$31),_xlpm.znet,_xlpm.zbas/(1-_xlpm.zdisc)*(1+_xlpm.zgrow)^_xlpm.zhld*(1-Input!$C$15),_xlpm.zmat,_xlpm.zact*(-(_xlpm.zmon=_xlpm.zaccm)*_xlpm.zbuy-_xlpm.zcapon*_xlpm.zcap/(_xlpm.zmq*(_xlpm.zwks+(_xlpm.zwks=0)))+_xlpm.zrenting*_xlpm.zramp*_xlpm.zrentnet/_xlpm.zmy*(1+Input!$C$8)^(_xlpm.zy-1)-_xlpm.zowned*_xlpm.zownfx/_xlpm.zmy-_xlpm.zrenting*_xlpm.zrentfx/_xlpm.zmy+(_xlpm.zmon=_xlpm.zsalem)*_xlpm.znet),XIRR(MMULT(_xlpm.zmat,_xlfn.SEQUENCE('_IRR Engine'!$Q$6,1,1,0)),EOMONTH(Input!$C$7,_xlpm.zmon-1)))} -> 0.23396414 | F13: {=_xlfn.LET(_xlpm.zact,TRANSPOSE(Properties!$D$6:$D$15),_xlpm.zqtr,TRANSPOSE(Properties!$Q$6:$Q$15),_xlpm.zwks,TRANSPOSE(Properties!$R$6:$R$15),_xlpm.zrst,TRANSPOSE(Properties!$T$6:$T$15),_xlpm.zsel,TRANSPOSE(Properties!$U$6:$U$15),_xlpm.zbas,TRANSPOSE(Properties!$P$6:$P$15),_xlpm.zcap,TRANSPOSE(Properties!$N$6:$N$15),_xlpm.zbuy,TRANSPOSE(Properties!$M$6:$M$15+Properties!$O$6:$O$15),_xlpm.zrnt,TRANSPOSE(Properties!$Y$6:$Y$15),_xlpm.zhld,TRANSPOSE(Properties!$V$6:$V$15),_xlpm.zpre,TRANSPOSE(Input!$C$80:$C$89),_xlpm.zhoa,TRANSPOSE(Input!$D$80:$D$89+Input!$E$80:$E$89),_xlpm.zmy,'_IRR Engine'!$Q$7,_xlpm.zmq,1,_xlpm.zcop,'_IRR Engine'!$Q$9,_xlpm.zdisc,TRANSPOSE(Input!$I$80:$I$89),_xlpm.zgrow,TRANSPOSE(Input!$G$80:$G$89)+(F$7-Input!$C$55),_xlpm.zscale,1,_xlpm.zmon,_xlfn.SEQUENCE('_IRR Engine'!$Q$5),_xlpm.zq,ROUNDUP(_xlpm.zmon/_xlpm.zmq,0),_xlpm.zy,ROUNDUP(_xlpm.zmon/_xlpm.zmy,0),_xlpm.zaccm,(_xlpm.zqtr-1)*_xlpm.zmq+1,_xlpm.zrentm,(_xlpm.zrst-1)*_xlpm.zmq+1,_xlpm.zsalem,(_xlpm.zsel-1)*_xlpm.zmq+1,_xlpm.zowned,(_xlpm.zmon>=_xlpm.zaccm)*(_xlpm.zmon<_xlpm.zsalem),_xlpm.zcapon,(_xlpm.zmon>=_xlpm.zaccm)*(_xlpm.zmon<=_xlpm.zaccm-1+_xlpm.zmq*_xlpm.zwks),_xlpm.zrenting,(_xlpm.zmon>=_xlpm.zrentm)*(_xlpm.zmon<_xlpm.zsalem),_xlpm.zratio,(_xlpm.zq-_xlpm.zrst+1)/Input!$C$11,_xlpm.zramp,_xlpm.zratio-(_xlpm.zratio-1)*(_xlpm.zratio>1),_xlpm.zownfx,_xlpm.zbas*_xlpm.zpre+_xlpm.zhoa*_xlpm.zmy*_xlpm.zcop/Input!$C$5,_xlpm.zrentfx,_xlpm.zbas*(Input!$C$19+Input!$C$18)+Input!$C$32*_xlpm.zmy,_xlpm.zrentnet,_xlpm.zrnt*_xlpm.zscale*(1-Input!$C$20-Input!$C$21-Input!$C$31),_xlpm.znet,_xlpm.zbas/(1-_xlpm.zdisc)*(1+_xlpm.zgrow)^_xlpm.zhld*(1-Input!$C$15),_xlpm.zmat,_xlpm.zact*(-(_xlpm.zmon=_xlpm.zaccm)*_xlpm.zbuy-_xlpm.zcapon*_xlpm.zcap/(_xlpm.zmq*(_xlpm.zwks+(_xlpm.zwks=0)))+_xlpm.zrenting*_xlpm.zramp*_xlpm.zrentnet/_xlpm.zmy*(1+Input!$C$8)^(_xlpm.zy-1)-_xlpm.zowned*_xlpm.zownfx/_xlpm.zmy-_xlpm.zrenting*_xlpm.zrentfx/_xlpm.zmy+(_xlpm.zmon=_xlpm.zsalem)*_xlpm.znet),XIRR(MMULT(_xlpm.zmat,_xlfn.SEQUENCE('_IRR Engine'!$Q$6,1,1,0)),EOMONTH(Input!$C$7,_xlpm.zmon-1)))} -> 0.25715562 | G13: N7
